Workbook

Sheet Quant_Structured
A1: Teacher_ID | B1: Name of the interviewer | C1: Name of the note-taker | D1: District of respondent teacher | E1: Gender of respondent | F1: Date of the interview | G1: Subject taught by teacher | H1: Years of teaching experience | I1: Subject taught by teacher__Hindi | J1: Subject taught by teacher__English | K1: Subject taught by teacher__Social Science | L1: Subject taught by teacher__Maths | M1: Subject taught by teacher__Sanskrit | N1: Subject taught by teacher__Science | O1: Subject taught by teacher__Other | P1: Avg no. of classroom periods taken in a day | Q1: Activities participated over 2025-26 academic year__Subject Training | R1: Activities participated over 2025-26 academic year__Digital Training | S1: Activities participated over 2025-26 academic year__CLSS | T1: Activities participated over 2025-26 academic year__SKG | U1: Activities participated over 2025-26 academic year__Webex | V1: Activities participated over 2025-26 academic year__YTL | W1: Activities participated over 2025-26 academic year__APF Demo Sessions | X1: Activities participated over 2025-26 academic year__SIR | Y1: Activities participated over 2025-26 academic year__Muskaan Dreams- DIET Training | Z1: Activities participated over 2025-26 academic year__HM Training | AA1: Activities participated over 2025-26 academic year__Election related Duties | AB1: Activities participated over 2025-26 academic year__Any other | AC1: Do teachers find subject in-person training useful or helpful | AD1: Training resources received from in-person training__PPT | AE1: Training resources received from in-person training__Margdarshika_Teaching Plan__Modules | AF1: Training resources received from in-person training__ToT | AG1: Training resources received from in-person training__Not received | AH1: Have they applied given resources_teaching lesson plan__ modules in their classroom | AI1: Does teacher find SKG Sheekh ki Yatra useful | AJ1: Does teacher find Webex useful | AK1: Does teacher find YTL useful | AL1: Are there any online courses teacher has done in last 1 year | AM1: Does teacher think digital or online courses are an effective way for teachers to learn | AN1: How many hours teacher can allocate to engage with digital courses__ digital learning | AO1: Timing to do online or digital courses__learning__During school hours | AP1: Timing to do online or digital courses__learning__After school | AQ1: Timing to do online or digital courses__learning__During holidays or weekends | AR1: Most engaging features of DIKSHA digital course__Animated videos | AS1: Most engaging features of DIKSHA digital course__Real classroom examples | AT1: Most engaging features of DIKSHA digital course__Interactive questions__quizzes | AU1: Most engaging features of DIKSHA digital course__Readings__resources | AV1: Most engaging features of DIKSHA digital course__Assessments | AW1: Most engaging features of DIKSHA digital course__Post work | AX1: Most engaging features of DIKSHA digital course__Nothing | AY1: Source of information on DIKSHA digital course__WhatsApp posters | AZ1: Source of information on DIKSHA digital course__Dashboard | BA1: Source of information on DIKSHA digital course__JSK Instruction on whatsapp group | BB1: Source of information on DIKSHA digital course__CLSS | BC1: Source of information on DIKSHA digital course__VC | BD1: Source of information on DIKSHA digital course__Word of mouth | BE1: Source of information on DIKSHA digital course__Any other | BF1: Effective source of information to receive program related information | BG1: Effective source of information to receive program related information__JSK Whatsapp | BH1: Effective source of information to receive program related information__School Whatsapp | BI1: Effective source of information to receive program related information__Letter | BJ1: Effective source of information to receive program related information__Other | BK1: Does teacher know about DIKSHA Courses and platform | BL1: Reason for not doing DIKSHA course__Time issue | BM1: Reason for not doing DIKSHA course__Other engagement | BN1: Reason for not doing DIKSHA course__Technical issue | BO1: Reason for not doing DIKSHA course__Not aware | BP1: Reason for not doing DIKSHA course__Not found useful | BQ1: No. of CLSS attended by teacher | BR1: CLSS topics recalled__कक्षा प्रबंधन के शुरुआती प्रयास | BS1: CLSS topics recalled__पूर्वज्ञान से शुरु, समूहकार्य से सीख | BT1: CLSS topics recalled__प्रभावी गृहकार्य | BU1: CLSS topics recalled__पुनरवलोकन एवं समेकन | BV1: CLSS topics recalled__प्रभावी पुनरावृत्ति | BW1: CLSS topics recalled__No topic recalled | BX1: CLSS learning solved classroom challenge | BY1: Processes to cascade CLSS learnings at school level__Resources shared in the school whatsapp group | BZ1: Processes to cascade CLSS learnings at school level__Participating teacher share their notes | CA1: Processes to cascade CLSS learnings at school level__Participating teacher verbally cascade the learning Peer learning discussions | CB1: Processes to cascade CLSS learnings at school level__No learnings shared or no set process adopted | CC1: Processes to cascade CLSS learnings at school level__Other | CD1: Could teacher recall RSK MP as attendance platform for CLSS | CE1: What challenges do they face in filling attendance and feedback form post the samwad__Awareness Issue | CF1: What challenges do they face in filling attendance and feedback form post the samwad__Session end rush for teachers to leave the venue | CG1: What challenges do they face in filling attendance and feedback form post the samwad__Not perceived important | CH1: What challenges do they face in filling attendance and feedback form post the samwad__Unwilling teachers | CI1: What challenges do they face in filling attendance and feedback form post the samwad__others | CJ1: Does teacher know about CLSS and it's format | CK1: Reasons of non-participation in CLSS__Could find time | CL1: Reasons of non-participation in CLSS__Not instructed to attend | CM1: Reasons of non-participation in CLSS__Busy with other work | CN1: Reasons of non-participation in CLSS__Didn't find any information | CO1: Reasons of non-participation in CLSS__Was not aware | CP1: Reasons of non-participation in CLSS__Others | CQ1: Are there any online courses teacher has done in last 1 year If yes, mention course name and platform | CR1: _index | CS1: Name of the online platforms used by the teacher | CT1: Diksha Course | CU1: DIKSHA | CV1: iGOT | CW1: Subject Training | CY1: Did Online Course
A2: 1 | B2: Rashmi Mishra | C2: Vaibhav Tambe | D2: Bhind | E2: Male | F2: 46183 | G2: Social Science | H2: 24 | I2: 0 | J2: 0 | K2: 1 | L2: 0 | M2: 0 | N2: 0 | O2: 0 | P2: 3 | Q2: 1 | R2: 1 | S2: 1 | T2: 0 | U2: 0 | V2: 0 | W2: 0 | X2: 1 | Y2: 0 | Z2: 1 | AA2: 1 | AB2: 1 | AC2: Yes | AD2: 0 | AE2: 1 | AF2: 0 | AG2: 0 | AH2: Not sure | AL2: Yes | AM2: No | AN2: 1 hr | AO2: 1 | AP2: 1 | AQ2: 0 | AR2: 0 | AS2: 0 | AT2: 0 | AU2: 0 | AV2: 1 | AW2: 0 | AY2: 0 | AZ2: 0 | BA2: 1 | BB2: 0 | BC2: 0 | BD2: 0 | BE2: 0 | BF2: JSK Whatsapp | BG2: 1 | BH2: 0 | BI2: 0 | BJ2: 0 | BK2: Yes | BQ2: 3 | BX2: Yes | BY2: 0 | BZ2: 0 | CA2: 0 | CB2: 0 | CC2: 1 | CD2: No | CE2: 0 | CF2: 0 | CG2: 1 | CH2: 0 | CI2: 0 | CJ2: Yes | CK2: 0 | CL2: 0 | CM2: 0 | CN2: 0 | CO2: 0 | CP2: 0 | CR2: 1 | CS2: =Qual_FreeText!Z2 -> DIKSHA | CT2: =Qual_FreeText!X2 -> Education Department (DIET) | CU2: 1 | CV2: 0 | CW2: =Qual_FreeText!M2 -> Subject Training, CLSS, Digital Training (PLC) | CX2: 1 | CY2: 1
A3: 2 | B3: Ritesh Pandey | C3: Vaibhav Kurwade | D3: Balaghat | E3: Male | F3: 46183 | G3: Social Science | H3: 37 | I3: 0 | J3: 0 | K3: 1 | L3: 0 | M3: 0 | N3: 0 | O3: 0 | P3: 4 | Q3: 1 | R3: 1 | S3: 1 | T3: 0 | U3: 0 | V3: 0 | W3: 0 | X3: 0 | Y3: 0 | Z3: 0 | AA3: 0 | AB3: 0 | AC3: Yes | AD3: 0 | AE3: 1 | AF3: 0 | AG3: 0 | AH3: Not sure | AL3: Yes | AM3: Yes | AN3: 4-5 hrs | AO3: 0 | AP3: 1 | AQ3: 0 | AR3: 0 | AS3: 0 | AT3: 1 | AU3: 0 | AV3: 0 | AW3: 1 | AY3: 1 | AZ3: 0 | BA3: 0 | BB3: 0 | BC3: 0 | BD3: 1 | BE3: 0 | BF3: JSK Whatsapp | BG3: 1 | BH3: 0 | BI3: 0 | BJ3: 0 | BK3: Yes | BQ3: 4 | BX3: No | BY3: 0 | BZ3: 0 | CA3: 0 | CB3: 0 | CC3: 1 | CD3: Yes | CE3: 0 | CF3: 0 | CG3: 0 | CH3: 1 | CI3: 0 | CJ3: No | CK3: 0 | CL3: 0 | CM3: 0 | CN3: 0 | CO3: 0 | CP3: 0 | CR3: 2 | CS3: =Qual_FreeText!Z3 -> DIKSHA and Karmayogi | CT3: =Qual_FreeText!X3 -> 0 | CU3: 1 | CV3: 0 | CW3: =Qual_FreeText!M3 -> Teacher took part in three days block level training in the month of July, after that he participated in the almost all CLSS from Aug to Jan. | CY3: 1
A4: 3 | B4: Aishwarya Yadav | C4: Jay Prakash | D4: Rajgarh | E4: Male | F4: 46184 | G4: Social Science | H4: 40 | I4: 0 | J4: 0 | K4: 1 | L4: 0 | M4: 0 | N4: 0 | O4: 0 | P4: 3 | Q4: 1 | R4: 1 | S4: 1 | T4: 0 | U4: 1 | V4: 1 | W4: 0 | X4: 0 | Y4: 0 | Z4: 0 | AA4: 0 | AB4: 0 | AC4: Yes | AD4: 0 | AE4: 0 | AF4: 0 | AG4: 1 | AJ4: No | AK4: No | AL4: Yes | AM4: Yes | AN4: 4-5 hrs | AO4: 1 | AP4: 1 | AQ4: 0 | AR4: 1 | AS4: 0 | AT4: 0 | AU4: 0 | AV4: 0 | AW4: 0 | AY4: 0 | AZ4: 0 | BA4: 1 | BB4: 0 | BC4: 0 | BD4: 1 | BE4: 0 | BF4: JSK Whatsapp | BG4: 1 | BH4: 0 | BI4: 0 | BJ4: 0 | BQ4: 5 | BX4: Yes | BY4: 0 | BZ4: 0 | CA4: 0 | CB4: 0 | CC4: 1 | CD4: No | CE4: 0 | CF4: 0 | CG4: 0 | CH4: 0 | CI4: 1 | CR4: 3 | CS4: =Qual_FreeText!Z4 -> दीक्षा App | CT4: =Qual_FreeText!X4 -> आपने बताया की आपने मानसिक तनाव कैसे कम करें इस पर online कोर्स किया हैं. | CU4: 1 | CV4: 0 | CW4: =Qual_FreeText!M4 -> Digital course, CLSS, sub Training | CY4: 1
A5: 4 | B5: Rajesh Solanki | C5: Shalu Sharma | D5: Betul | E5: Female | F5: 46184 | G5: Hindi Social Science | H5: 31 | I5: 1 | J5: 0 | K5: 1 | L5: 0 | M5: 0 | N5: 0 | O5: 0 | P5: 6 | Q5: 1 | R5: 1 | S5: 1 | T5: 1 | U5: 0 | V5: 1 | W5: 0 | X5: 0 | Y5: 0 | Z5: 0 | AA5: 0 | AB5: 0 | AC5: Yes | AD5: 0 | AE5: 0 | AF5: 1 | AG5: 0 | AH5: No | AI5: No | AK5: No | AL5: Yes | AM5: Yes | AN5: 1 hr | AO5: 0 | AP5: 1 | AQ5: 0 | AR5: 1 | AS5: 0 | AT5: 1 | AU5: 1 | AV5: 0 | AW5: 0 | AY5: 1 | AZ5: 0 | BA5: 1 | BB5: 1 | BC5: 0 | BD5: 0 | BE5: 0 | BF5: JSK Whatsapp | BG5: 1 | BH5: 0 | BI5: 0 | BJ5: 0 | BQ5: 3 | BX5: No | BY5: 0 | BZ5: 0 | CA5: 0 | CB5: 1 | CC5: 0 | CD5: No | CE5: 0 | CF5: 1 | CG5: 0 | CH5: 0 | CI5: 0 | CR5: 4 | CS5: =Qual_FreeText!Z5 -> Mygov and DIKSHA | CT5: =Qual_FreeText!X5 -> Suchna ka adhikar | CU5: 1 | CV5: 0 | CW5: =Qual_FreeText!M5 -> She could not recall | CY5: 1
A6: 5 | B6: Pushpendra Singh | C6: Other | D6: Satna | E6: Male | F6: 46183 | G6: Social Science | H6: 16 | I6: 0 | J6: 0 | K6: 1 | L6: 0 | M6: 0 | N6: 0 | O6: 0 | P6: 6 | Q6: 1 | R6: 0 | S6: 1 | T6: 0 | U6: 0 | V6: 0 | W6: 0 | X6: 0 | Y6: 0 | Z6: 0 | AA6: 0 | AB6: 0 | AC6: Yes | AD6: 1 | AE6: 1 | AF6: 0 | AG6: 0 | AH6: Yes | AL6: Yes | AM6: Yes | AN6: 2 hr | AO6: 1 | AP6: 0 | AQ6: 1 | BK6: Yes | BL6: 1 | BM6: 1 | BN6: 0 | BO6: 0 | BP6: 0 | BQ6: 5 | BX6: Yes | BY6: 0 | BZ6: 1 | CA6: 1 | CB6: 0 | CC6: 0 | CD6: Yes | CE6: 1 | CF6: 0 | CG6: 0 | CH6: 0 | CI6: 1 | CJ6: Yes | CK6: 0 | CL6: 0 | CM6: 0 | CN6: 0 | CO6: 0 | CP6: 0 | CR6: 5 | CS6: =Qual_FreeText!Z6 -> DIKSHA APP | CT6: =Qual_FreeText!X6 -> DIKSHA | CU6: 1 | CV6: 0 | CW6: =Qual_FreeText!M6 -> Teacher has participated in 5 CLSS throughout the year at JSK and one Block level subject training on new NCERT book of Class-6. | CX6: 1 | CY6: 1
A7: 6 | B7: Dharmendra Mishra | C7: Bhanu Priya | D7: Sagar | E7: Male | F7: 46183 | G7: Maths Science | H7: 15 | I7: 0 | J7: 0 | K7: 0 | L7: 1 | M7: 0 | N7: 1 | O7: 0 | P7: 6 | Q7: 1 | R7: 1 | S7: 1 | T7: 1 | U7: 0 | V7: 0 | W7: 0 | X7: 1 | Y7: 0 | Z7: 0 | AA7: 1 | AB7: 1 | AC7: Yes | AD7: 0 | AE7: 0 | AF7: 0 | AG7: 1 | AI7: Yes | AL7: Yes | AM7: Yes | AN7: 4-5 hrs | AO7: 0 | AP7: 1 | AQ7: 0 | AR7: 1 | AS7: 0 | AT7: 1 | AU7: 0 | AV7: 1 | AW7: 0 | AY7: 0 | AZ7: 0 | BA7: 1 | BB7: 0 | BC7: 0 | BD7: 0 | BE7: 0 | BF7: JSK Whatsapp | BG7: 1 | BH7: 0 | BI7: 0 | BJ7: 0 | BQ7: 4 | BX7: Yes | BY7: 0 | BZ7: 0 | CA7: 0 | CB7: 0 | CC7: 1 | CD7: Yes | CE7: 0 | CF7: 0 | CG7: 0 | CH7: 0 | CI7: 1 | CR7: 6 | CS7: =Qual_FreeText!Z7 -> DIKSHA, Karmyogi | CT7: =Qual_FreeText!X7 -> PLC, AI | CU7: 1 | CV7: 0 | CW7: =Qual_FreeText!M7 -> 1. Attended 4 CLSS - August, sept, oct, Jan 2. SIR- Nov- Dec 3. Subject Specific Training- June -July | CX7: 2 | CY7: 1
A8: 7 | B8: Shalu Sharma | C8: Rajesh Solanki | D8: Betul | E8: Male | F8: 46185 | G8: Maths Science | H8: 34 | I8: 0 | J8: 0 | K8: 0 | L8: 1 | M8: 0 | N8: 1 | O8: 0 | P8: 6 | Q8: 1 | R8: 0 | S8: 1 | T8: 0 | U8: 0 | V8: 1 | W8: 0 | X8: 1 | Y8: 0 | Z8: 0 | AA8: 0 | AB8: 0 | AC8: Yes | AD8: 1 | AE8: 1 | AF8: 0 | AG8: 0 | AH8: No | AK8: Yes | AL8: Yes | AM8: Yes | AO8: 1 | AP8: 0 | AQ8: 0 | BK8: Yes | BL8: 1 | BM8: 0 | BN8: 0 | BO8: 0 | BP8: 0 | BQ8: 3 | BX8: No | BY8: 0 | BZ8: 0 | CA8: 1 | CB8: 0 | CC8: 0 | CD8: Yes | CE8: 0 | CF8: 1 | CG8: 0 | CH8: 0 | CI8: 0 | CR8: 7 | CS8: =Qual_FreeText!Z8 -> MyGov and DIKSHA courses | CT8: =Qual_FreeText!X8 -> Some course on mulyanakan, couldn't remember the name of the course done on DIKSHA | CU8: 1 | CV8: 0 | CW8: =Qual_FreeText!M8 -> He participated in both Math and Science in person training. He mentioned that he attends YTL sometimes but he could not recall any topic discussed but he had idea about the paathyojana shared for science. he also shared an example from science training (chumbak). | CX8: 2 | CY8: 1
A9: 8 | B9: Rashmi Mishra | C9: Vaibhav Tambe | D9: Morena | E9: Female | F9: 46185 | G9: Maths | H9: 17 | I9: 0 | J9: 0 | K9: 0 | L9: 1 | M9: 0 | N9: 0 | O9: 0 | P9: 6 | Q9: 1 | R9: 1 | S9: 1 | T9: 0 | U9: 0 | V9: 0 | W9: 0 | X9: 0 | Y9: 0 | Z9: 0 | AA9: 0 | AB9: 0 | AC9: Yes | AD9: 0 | AE9: 1 | AF9: 0 | AG9: 0 | AH9: Yes | AL9: Yes | AM9: No | AO9: 1 | AP9: 0 | AQ9: 0 | AR9: 0 | AS9: 0 | AT9: 1 | AU9: 0 | AV9: 1 | AW9: 0 | AY9: 0 | AZ9: 0 | BA9: 1 | BB9: 0 | BC9: 0 | BD9: 0 | BE9: 0 | BF9: JSK Whatsapp | BG9: 1 | BH9: 0 | BI9: 0 | BJ9: 0 | BQ9: 5 | BX9: Yes | BY9: 0 | BZ9: 0 | CA9: 0 | CB9: 0 | CC9: 1 | CD9: Yes | CE9: 1 | CF9: 0 | CG9: 0 | CH9: 0 | CI9: 1 | CR9: 8 | CS9: =Qual_FreeText!Z9 -> DIKSHA | CT9: =Qual_FreeText!X9 -> Didn't remember course name. | CU9: 1 | CV9: 0 | CW9: =Qual_FreeText!M9 -> Subject training, CLSS, Digital Training | CX9: 1 | CY9: 1
A10: 9 | B10: Ritesh Pandey | C10: Vaibhav Kurwade | D10: Balaghat | E10: Female | F10: 46184 | G10: Hindi Social Science Sanskrit | H10: 18 | I10: 1 | J10: 0 | K10: 1 | L10: 0 | M10: 1 | N10: 0 | O10: 0 | P10: 4 | Q10: 1 | R10: 1 | S10: 1 | T10: 0 | U10: 0 | V10: 0 | W10: 0 | X10: 0 | Y10: 0 | Z10: 0 | AA10: 0 | AB10: 0 | AC10: Yes | AD10: 0 | AE10: 0 | AF10: 0 | AG10: 1 | AL10: Yes | AM10: Yes | AN10: 2 hr | AO10: 1 | AP10: 0 | AQ10: 0 | AR10: 0 | AS10: 0 | AT10: 1 | AU10: 0 | AV10: 0 | AW10: 0 | AY10: 1 | AZ10: 0 | BA10: 0 | BB10: 0 | BC10: 0 | BD10: 0 | BE10: 0 | BF10: JSK Whatsapp | BG10: 1 | BH10: 0 | BI10: 0 | BJ10: 0 | BQ10: 2 | BX10: No | BY10: 0 | BZ10: 0 | CA10: 1 | CB10: 0 | CC10: 0 | CD10: Yes | CE10: 0 | CF10: 0 | CG10: 0 | CH10: 0 | CI10: 1 | CJ10: Yes | CK10: 0 | CL10: 0 | CM10: 0 | CN10: 0 | CO10: 0 | CP10: 0 | CR10: 9 | CS10: =Qual_FreeText!Z10 -> Diksha and I-got | CT10: =Qual_FreeText!X10 -> AI course, Inclusive education (Samavesi shiksha on DIKSHA) | CU10: 1 | CV10: 1 | CW10: =Qual_FreeText!M10 -> Teacher took part in the subject training in the month of july, after that teacher attended 2 CLSS, and she attended digital training on I got karmayogi and on diksha. | CX10: 1 | CY10: 1
A11: 10 | B11: Aishwarya Yadav | C11: Jay Prakash | D11: Rajgarh | E11: Male | F11: 46185 | G11: Maths Science | H11: 27 | I11: 0 | J11: 0 | K11: 0 | L11: 1 | M11: 0 | N11: 1 | O11: 0 | P11: 6 | Q11: 1 | R11: 1 | S11: 1 | T11: 0 | U11: 0 | V11: 1 | W11: 0 | X11: 0 | Y11: 0 | Z11: 1 | AA11: 0 | AB11: 0 | AC11: Yes | AD11: 0 | AE11: 1 | AF11: 0 | AG11: 0 | AH11: Yes | AK11: Yes | AL11: Yes | AM11: Yes | AN11: 1 hr | AO11: 0 | AP11: 1 | AQ11: 0 | AR11: 1 | AS11: 1 | AT11: 1 | AU11: 1 | AV11: 0 | AW11: 0 | AY11: 0 | AZ11: 0 | BA11: 1 | BB11: 0 | BC11: 0 | BD11: 0 | BE11: 0 | BF11: JSK Whatsapp | BG11: 1 | BH11: 0 | BI11: 0 | BJ11: 0 | BQ11: 5 | BX11: Yes | BY11: 1 | BZ11: 0 | CA11: 0 | CB11: 0 | CC11: 0 | CD11: No | CE11: 0 | CF11: 0 | CG11: 0 | CH11: 0 | CI11: 1 | CR11: 10 | CS11: =Qual_FreeText!Z11 -> कर्मयोगी App के माध्यम से किये हैं. And DIKSHA | CT11: =Qual_FreeText!X11 -> कोर्स का नाम याद नहीं आ रहा हैं. | CU11: 1 | CV11: 0 | CW11: =Qual_FreeText!M11 -> SUB TRAININING, DIGITAL COURCE, CLSS, YTL, HM TRAINING | CX11: 1 | CY11: 1
A12: 11 | B12: Ritesh Pandey | C12: Vaibhav Kurwade | D12: Balaghat | E12: Female | F12: 46185 | G12: Social Science | H12: 16 | I12: 0 | J12: 0 | K12: 1 | L12: 0 | M12: 0 | N12: 0 | O12: 0 | P12: 6 | Q12: 1 | R12: 1 | S12: 1 | T12: 1 | U12: 0 | V12: 1 | W12: 0 | X12: 0 | Y12: 0 | Z12: 0 | AA12: 0 | AB12: 0 | AC12: Yes | AD12: 0 | AE12: 0 | AF12: 0 | AG12: 1 | AI12: Yes | AK12: Yes | AL12: Yes | AM12: Yes | AN12: 4-5 hrs | AO12: 1 | AP12: 1 | AQ12: 0 | AR12: 0 | AS12: 0 | AT12: 0 | AU12: 1 | AV12: 0 | AW12: 0 | AY12: 1 | AZ12: 0 | BA12: 0 | BB12: 0 | BC12: 0 | BD12: 0 | BE12: 0 | BF12: JSK Whatsapp | BG12: 1 | BH12: 0 | BI12: 0 | BJ12: 0 | BQ12: 5 | BX12: No | BY12: 0 | BZ12: 0 | CA12: 1 | CB12: 0 | CC12: 0 | CD12: Yes | CE12: 0 | CF12: 0 | CG12: 0 | CH12: 0 | CI12: 1 | CJ12: Yes | CK12: 0 | CL12: 0 | CM12: 0 | CN12: 0 | CO12: 0 | CP12: 0 | CR12: 11 | CS12: =Qual_FreeText!Z12 -> I got Karmayogi, Diksha | CT12: =Qual_FreeText!X12 -> not able to recall the name of the courses | CU12: 1 | CV12: 1 | CW12: =Qual_FreeText!M12 -> Teacher took part in the two days subject training at block level in the month of July, She attended all CLSS from Aug to Jan, and completed the digital course on I got platform. Also did one course on diksha but not able to recall the name of the course. | CX12: 1 | CY12: 1
A13: 12 | B13: Sonali Patidar | C13: Dilip Kag | D13: Khargone | E13: Female | F13: 46184 | G13: Social Science Maths | H13: 3 | I13: 0 | J13: 0 | K13: 1 | L13: 1 | M13: 0 | N13: 0 | O13: 0 | P13: 4 | Q13: 1 | R13: 1 | S13: 1 | T13: 0 | U13: 0 | V13: 1 | W13: 0 | X13: 0 | Y13: 0 | Z13: 0 | AA13: 0 | AB13: 1 | AC13: Yes | AD13: 0 | AE13: 1 | AF13: 0 | AG13: 0 | AH13: Yes | AK13: Yes | AL13: Yes | AM13: Yes | AN13: 2 hr | AO13: 0 | AP13: 1 | AQ13: 1 | AR13: 1 | AS13: 1 | AT13: 1 | AU13: 1 | AV13: 1 | AW13: 1 | AX13: 0 | AY13: 1 | AZ13: 0 | BA13: 1 | BB13: 0 | BC13: 0 | BD13: 0 | BE13: 1 | BF13: JSK Whatsapp School Whatsapp Letter | BG13: 1 | BH13: 1 | BI13: 1 | BJ13: 0 | BQ13: 3 | BX13: Yes | BY13: 1 | BZ13: 0 | CA13: 1 | CB13: 0 | CC13: 0 | CD13: Yes | CE13: 1 | CF13: 0 | CG13: 0 | CH13: 1 | CI13: 0 | CR13: 12 | CS13: =Qual_FreeText!Z13 -> DIKSHA, YouTube, WhatsApp, Attendance App. | CT13: =Qual_FreeText!X13 -> DIKSHA Courses, iGOT Courses. | CU13: 1 | CV13: 0 | CW13: =Qual_FreeText!M13 -> विषय आधारित प्रशिक्षण, अगस्त, सितम्बर और दिसम्बर में शैक्षिक संवाद में सहभागिता, जीवन कौशल प्रशिक्षण, TLM मेला, जनगणना में ड्यूटी आदि SIR ड्यूटी – लगभग 1 से 1.5 माह तक कार्य किया l | CY13: 1
A14: 13 | B14: Rahul Kumar | C14: Ashish Nigam | D14: Ujjain | E14: Female | F14: 46184 | G14: Maths | H14: 25 | I14: 0 | J14: 0 | K14: 0 | L14: 1 | M14: 0 | N14: 0 | O14: 0 | P14: 3 | Q14: 1 | R14: 1 | S14: 1 | T14: 0 | U14: 0 | V14: 0 | W14: 0 | X14: 0 | Y14: 0 | Z14: 0 | AA14: 1 | AB14: 0 | AC14: Not sure | AD14: 0 | AE14: 1 | AF14: 0 | AG14: 0 | AH14: Not sure | AL14: Yes | AM14: Yes | AN14: 1 hr | AO14: 0 | AP14: 1 | AQ14: 0 | AR14: 1 | AS14: 0 | AT14: 1 | AU14: 0 | AV14: 1 | AW14: 0 | AY14: 1 | AZ14: 0 | BA14: 1 | BB14: 0 | BC14: 0 | BD14: 1 | BE14: 0 | BF14: JSK Whatsapp | BG14: 1 | BH14: 0 | BI14: 0 | BJ14: 0 | BK14: Yes | BQ14: 1 | BX14: No | BY14: 0 | BZ14: 0 | CA14: 0 | CB14: 1 | CC14: 0 | CD14: No | CE14: 0 | CF14: 0 | CG14: 0 | CH14: 0 | CI14: 1 | CJ14: Yes | CK14: 0 | CL14: 0 | CM14: 0 | CN14: 0 | CO14: 0 | CP14: 0 | CR14: 13 | CS14: =Qual_FreeText!Z14 -> Diksha, Igot and Education portal | CT14: =Qual_FreeText!X14 -> PLC course, Mansikta Course on IGot on Karmyogi app | CU14: 1 | CV14: 1 | CW14: =Qual_FreeText!M14 -> Participated in Block level subject training, One CLSS in August 2025, one digital course has been completed in December 2025. | CY14: 1
A15: 14 | B15: Rahul Kumar | C15: Ashish Nigam | D15: Ujjain | E15: Female | F15: 46185 | G15: Science | H15: 25 | I15: 0 | J15: 0 | K15: 0 | L15: 0 | M15: 0 | N15: 1 | O15: 0 | P15: 4 | Q15: 1 | R15: 1 | S15: 0 | T15: 0 | U15: 0 | V15: 0 | W15: 0 | X15: 0 | Y15: 0 | Z15: 0 | AA15: 0 | AB15: 1 | AC15: Not sure | AD15: 0 | AE15: 0 | AF15: 0 | AG15: 1 | AL15: Yes | AM15: Not sure | AN15: 2 hr | AO15: 0 | AP15: 1 | AQ15: 0 | AR15: 1 | AS15: 1 | AT15: 0 | AU15: 0 | AV15: 0 | AW15: 0 | AY15: 0 | AZ15: 0 | BA15: 1 | BB15: 0 | BC15: 0 | BD15: 1 | BE15: 1 | BF15: JSK Whatsapp School Whatsapp | BG15: 1 | BH15: 1 | BI15: 0 | BJ15: 0 | BK15: Yes | BX15: No | BY15: 0 | BZ15: 0 | CA15: 0 | CB15: 1 | CC15: 0 | CJ15: No | CK15: 0 | CL15: 1 | CM15: 0 | CN15: 1 | CO15: 0 | CP15: 0 | CR15: 14 | CS15: =Qual_FreeText!Z15 -> Diksha and Igot | CT15: =Qual_FreeText!X15 -> PLC digital course | CU15: 1 | CV15: 1 | CW15: =Qual_FreeText!M15 -> Digital course - PLC Dec, Subject training - July 2025, other 5 Days training - February 2026 | CX15: 1 | CY15: 1
A16: 15 | B16: Rashmi Mishra | C16: Rajshree Behera | D16: Gwalior | E16: Male | F16: 46184 | G16: Social Science Sanskrit | H16: 25 | I16: 0 | J16: 0 | K16: 1 | L16: 0 | M16: 1 | N16: 0 | O16: 0 | P16: 6 | Q16: 1 | R16: 1 | S16: 1 | T16: 0 | U16: 0 | V16: 1 | W16: 0 | X16: 0 | Y16: 0 | Z16: 0 | AA16: 1 | AB16: 1 | AC16: Yes | AD16: 0 | AE16: 1 | AF16: 0 | AG16: 0 | AH16: Yes | AK16: Yes | AL16: Yes | AM16: No | AN16: 4-5 hrs | AO16: 0 | AP16: 1 | AQ16: 0 | AR16: 0 | AS16: 0 | AT16: 1 | AU16: 0 | AV16: 1 | AW16: 0 | AX16: 0 | AY16: 0 | AZ16: 0 | BA16: 1 | BB16: 0 | BC16: 0 | BD16: 1 | BE16: 0 | BF16: JSK Whatsapp | BG16: 1 | BH16: 0 | BI16: 0 | BJ16: 0 | BQ16: 2 | BX16: Yes | BY16: 0 | BZ16: 0 | CA16: 1 | CB16: 0 | CC16: 0 | CD16: Yes | CE16: 0 | CF16: 0 | CG16: 1 | CH16: 0 | CI16: 1 | CR16: 15 | CS16: =Qual_FreeText!Z16 -> DIKSHA and I GoT | CT16: =Qual_FreeText!X16 -> PLC and Karmyogi Course series | CU16: 1 | CV16: 1 | CW16: =Qual_FreeText!M16 -> Subject training (August), CLSS (November & December), I got training (Across the year), Tree plantation (Across the year), YTL ( September), | CX16: 1 | CY16: 1
A17: 16 | B17: Naushad Mirza | C17: Deeksha Singh | D17: Panna | E17: Male | F17: 46183 | G17: Maths | H17: 16 | I17: 0 | J17: 0 | K17: 0 | L17: 1 | M17: 0 | N17: 0 | O17: 0 | P17: 4 | Q17: 1 | R17: 1 | S17: 1 | T17: 1 | U17: 0 | V17: 0 | W17: 0 | X17: 0 | Y17: 0 | Z17: 1 | AA17: 0 | AB17: 0 | AC17: Yes | AD17: 0 | AE17: 1 | AF17: 0 | AG17: 0 | AH17: No | AI17: Not Sure | AL17: Yes | AM17: Not sure | AN17: 3 hr | AO17: 0 | AP17: 1 | AQ17: 0 | AR17: 0 | AS17: 0 | AT17: 0 | AU17: 0 | AV17: 0 | AW17: 0 | AX17: 1 | AY17: 1 | AZ17: 0 | BA17: 0 | BB17: 1 | BC17: 0 | BD17: 1 | BE17: 1 | BF17: JSK Whatsapp Letter Other | BG17: 1 | BH17: 0 | BI17: 1 | BJ17: 1 | BQ17: 3 | BR17: 0 | BS17: 1 | BT17: 1 | BU17: 1 | BV17: 0 | BW17: 0 | BX17: Couldn't remember particular learning from CLSS | BY17: 0 | BZ17: 0 | CA17: 1 | CB17: 0 | CC17: 0 | CD17: Yes | CE17: 0 | CF17: 1 | CG17: 0 | CH17: 0 | CI17: 0 | CR17: 16 | CS17: =Qual_FreeText!Z17 -> diksha app, whatsapp | CT17: =Qual_FreeText!X17 -> It was shared in the group, and the CAC has been consistently encouraging participants and sending timelymessages and nudges to support them in completing the courses. | CU17: 1 | CV17: 0 | CW17: =Qual_FreeText!M17 -> He shared that he participated in a three-day subject training conducted at the block level in Ajaygarh. He alsomentioned completing one or two digital courses; however, he was unable to recall the specifi c names or details ofthese courses. Additionally, he has attended CLSS as participants. | CX17: 1 | CY17: 1
A18: 17 | B18: Pushpendra Singh | C18: Krishna | D18: Rewa | E18: Female | F18: 46188 | G18: Hindi Social Science | H18: 22 | I18: 1 | J18: 0 | K18: 1 | L18: 0 | M18: 0 | N18: 0 | O18: 0 | P18: 4 | Q18: 1 | R18: 1 | S18: 1 | T18: 0 | U18: 0 | V18: 1 | W18: 0 | X18: 1 | Y18: 0 | Z18: 0 | AA18: 1 | AB18: 0 | AC18: Yes | AD18: 0 | AE18: 0 | AF18: 0 | AG18: 1 | AK18: Yes | AL18: Yes | AM18: Yes | AN18: 4-5 hrs | AO18: 0 | AP18: 1 | AQ18: 1 | AR18: 1 | AS18: 0 | AT18: 1 | AU18: 0 | AV18: 1 | AW18: 0 | AX18: 0 | AY18: 1 | AZ18: 0 | BA18: 1 | BB18: 0 | BC18: 0 | BD18: 0 | BE18: 0 | BF18: JSK Whatsapp | BG18: 1 | BH18: 0 | BI18: 0 | BJ18: 0 | BQ18: 3 | BR18: 1 | BS18: 0 | BT18: 1 | BU18: 1 | BV18: 0 | BW18: 0 | BX18: Couldn't remember particular learning from CLSS | BY18: 0 | BZ18: 0 | CA18: 1 | CB18: 0 | CC18: 0 | CD18: Yes | CE18: 0 | CF18: 0 | CG18: 0 | CH18: 0 | CI18: 1 | CR18: 17 | CS18: =Qual_FreeText!Z18 -> The teacher reported using DIKSHA, YouTube Live, and WhatsApp as online platforms for learning and accessing training-related information. | CT18: =Qual_FreeText!X18 -> The teacher reported completing courses on the DIKSHA platform during the last year but was unable to recall the exact course names. | CU18: 1 | CV18: 0 | CW18: =Qual_FreeText!M18 -> The teacher could not recall the exact dates and duration of participation. However, the teacher reported attending Subject Training, CLSS, Digital Training, YouTube Live sessions, follow-up activities, and DIKSHA courses during the academic year. | CX18: 1 | CY18: 1
A19: 18 | B19: Sonali Patidar | C19: Dilip Kag | D19: Harda | E19: Male | F19: 46185 | G19: Social Science Sanskrit | H19: 15 | I19: 0 | J19: 0 | K19: 1 | L19: 0 | M19: 1 | N19: 0 | O19: 0 | P19: 2 | Q19: 1 | R19: 0 | S19: 1 | T19: 1 | U19: 0 | V19: 0 | W19: 0 | X19: 0 | Y19: 0 | Z19: 1 | AA19: 0 | AB19: 1 | AC19: Yes | AD19: 1 | AE19: 1 | AF19: 1 | AG19: 0 | AH19: Yes | AI19: Yes | AL19: No | AN19: 1 hr | AO19: 1 | AP19: 1 | AQ19: 0 | BK19: Yes | BL19: 0 | BM19: 1 | BN19: 1 | BO19: 1 | BP19: 0 | BQ19: 4 | BR19: 1 | BS19: 1 | BT19: 1 | BU19: 0 | BV19: 1 | BW19: 0 | BX19: Yes | BY19: 1 | BZ19: 0 | CA19: 1 | CB19: 0 | CC19: 0 | CD19: Yes | CE19: 0 | CF19: 1 | CG19: 1 | CH19: 0 | CI19: 0 | CR19: 18 | CS19: =Qual_FreeText!Z19 -> 0 | CT19: =Qual_FreeText!X19 -> 0 | CU19: 0 | CV19: 1 | CW19: =Qual_FreeText!M19 -> ELIT प्रशिक्षण 2025, सामाजिक विज्ञान राज्य स्तरीय प्रशिक्षण 2025, CLSS अगस्त 2025 से नियमित, प्रशिक्षण उपरांत सीख की यात्रा , उमंग प्रशिक्षण 2025, जनगणना कार्य 2025-26 | CX19: 1 | CY19: 1
A20: 19 | B20: Rahul Kumar | C20: Ashish Nigam | D20: Neemuch | E20: Male | F20: 46188 | G20: Social Science | H20: 13 | I20: 0 | J20: 0 | K20: 1 | L20: 0 | M20: 0 | N20: 0 | O20: 0 | P20: 6 | Q20: 1 | R20: 1 | S20: 1 | T20: 0 | U20: 0 | V20: 0 | W20: 0 | X20: 1 | Y20: 0 | Z20: 0 | AA20: 1 | AB20: 0 | AC20: Not sure | AD20: 0 | AE20: 1 | AF20: 0 | AG20: 0 | AH20: Not sure | AL20: Yes | AM20: Yes | AN20: 2 hr | AO20: 1 | AP20: 1 | AQ20: 0 | AR20: 0 | AS20: 0 | AT20: 1 | AU20: 0 | AV20: 0 | AW20: 0 | AX20: 0 | AY20: 1 | AZ20: 0 | BA20: 1 | BB20: 0 | BC20: 0 | BD20: 0 | BE20: 0 | BF20: JSK Whatsapp School Whatsapp Letter | BG20: 1 | BH20: 1 | BI20: 1 | BJ20: 0 | BQ20: 4 | BR20: 1 | BS20: 0 | BT20: 1 | BU20: 0 | BV20: 0 | BW20: 0 | BX20: Yes | BY20: 1 | BZ20: 0 | CA20: 1 | CB20: 0 | CC20: 0 | CD20: No | CE20: 0 | CF20: 0 | CG20: 0 | CH20: 0 | CI20: 1 | CR20: 19 | CS20: =Qual_FreeText!Z20 -> Diksha App, I-GOT | CT20: =Qual_FreeText!X20 -> PLC and courses on Karmyogi | CU20: 1 | CV20: 1 | CW20: =Qual_FreeText!M20 -> Participated in all CLSS except last one, In person training- July 2025, Digital course - Jan 2026 | CX20: 1 | CY20: 1
A21: 20 | B21: Rajesh Solanki | C21: Jay Prakash | D21: Shivpuri | E21: Female | F21: 46188 | G21: Maths Science | H21: 24 | I21: 0 | J21: 0 | K21: 0 | L21: 1 | M21: 0 | N21: 1 | O21: 0 | P21: 6 | Q21: 1 | R21: 1 | S21: 1 | T21: 0 | U21: 0 | V21: 0 | W21: 0 | X21: 0 | Y21: 0 | Z21: 0 | AA21: 0 | AB21: 0 | AC21: Yes | AD21: 0 | AE21: 1 | AF21: 0 | AG21: 0 | AH21: Yes | AL21: Yes | AM21: Yes | AO21: 1 | AP21: 1 | AQ21: 0 | AR21: 1 | AS21: 1 | AT21: 0 | AU21: 0 | AV21: 0 | AW21: 0 | AX21: 0 | AY21: 0 | AZ21: 0 | BA21: 1 | BB21: 0 | BC21: 0 | BD21: 0 | BE21: 0 | BF21: JSK Whatsapp | BG21: 1 | BH21: 0 | BI21: 0 | BJ21: 0 | BQ21: 3 | BX21: Yes | BY21: 0 | BZ21: 0 | CA21: 1 | CB21: 0 | CC21: 0 | CD21: Yes | CE21: 1 | CF21: 0 | CG21: 0 | CH21: 0 | CI21: 0 | CR21: 20 | CS21: =Qual_FreeText!Z21 -> Diksha App, I-GOT | CT21: =Qual_FreeText!X21 -> AI, प्रिंट समृद्ध वातावरण, सिख एंड सहयोग, कर्मयोगी के कोर्से में भी भाग लिया था. | CU21: 1 | CV21: 0 | CW21: =Qual_FreeText!M21 -> मैंने 3 CLSS की चर्चा में भाग लिया था जिसमें हमने एक दुसरे के अनुभव से सीखना, पुस्तिका के आधार पर सभी के साथ चर्चा होती थी, किसी भी प्रकार के डिजिटल चीजों का ऊपयोग नहीं होता था. आपने बाद बताया की आपने 3 CLSS और हेल्थ वेलनेस कोर्स में भी भाग लिया था. | CY21: 1
A22: 21 | B22: Ritesh Pandey | C22: Naushad Mirza | D22: Chhindwara | E22: Male | F22: 46189 | G22: Maths Science | H22: 28 | I22: 0 | J22: 0 | K22: 0 | L22: 1 | M22: 0 | N22: 1 | O22: 0 | P22: 6 | Q22: 1 | R22: 0 | S22: 1 | T22: 0 | U22: 0 | V22: 1 | W22: 0 | X22: 0 | Y22: 0 | Z22: 0 | AA22: 0 | AB22: 0 | AC22: Yes | AD22: 0 | AE22: 0 | AF22: 0 | AG22: 1 | AK22: Yes | AL22: Yes | AM22: Yes | AN22: 2 hr | AO22: 0 | AP22: 1 | AQ22: 0 | BK22: Yes | BL22: 0 | BM22: 0 | BN22: 1 | BO22: 0 | BP22: 0 | BQ22: 3 | BR22: 0 | BS22: 0 | BT22: 0 | BU22: 0 | BV22: 1 | BW22: 0 | BX22: Couldn't remember particular learning from CLSS | BY22: 0 | BZ22: 0 | CA22: 0 | CB22: 1 | CC22: 0 | CD22: Yes | CE22: 0 | CF22: 0 | CG22: 0 | CH22: 0 | CI22: 1 | CR22: 21 | CS22: =Qual_FreeText!Z22 -> I GoT | CT22: =Qual_FreeText!X22 -> Karm Yogi | CU22: 0 | CV22: 1 | CW22: =Qual_FreeText!M22 -> 3 CLSS in diffiernt month on the basis of availibility of the teacher in school. 2 days Math and 2 days Science subject training at Block level. 2-3 times Youtube live attended. He also participated in JSK level Science exhibition. He also involved in Sansad khel pratiyogita. Participated in JSK level CAC Organized Samiksha meeting. | CY22: 1
A23: 22 | B23: Rashmi Mishra | C23: Vaibhav Tambe | D23: Datia | E23: Female | F23: 46188 | G23: Social Science | H23: 23 | I23: 0 | J23: 0 | K23: 1 | L23: 0 | M23: 0 | N23: 0 | O23: 0 | P23: 6 | Q23: 1 | R23: 1 | S23: 1 | T23: 0 | U23: 0 | V23: 0 | W23: 0 | X23: 0 | Y23: 0 | Z23: 0 | AA23: 1 | AB23: 1 | AC23: Yes | AD23: 0 | AE23: 1 | AF23: 0 | AG23: 0 | AH23: No | AL23: Yes | AM23: Yes | AN23: 2 hr | AO23: 0 | AP23: 1 | AQ23: 0 | AR23: 0 | AS23: 0 | AT23: 1 | AU23: 0 | AV23: 1 | AW23: 1 | AX23: 0 | AY23: 1 | AZ23: 0 | BA23: 0 | BB23: 0 | BC23: 0 | BD23: 0 | BE23: 0 | BF23: JSK Whatsapp | BG23: 1 | BH23: 0 | BI23: 0 | BJ23: 0 | BQ23: 5 | BR23: 1 | BS23: 0 | BT23: 0 | BU23: 0 | BV23: 0 | BW23: 0 | BX23: Yes | BY23: 0 | BZ23: 0 | CA23: 0 | CB23: 0 | CC23: 1 | CD23: Yes | CE23: 0 | CF23: 0 | CG23: 0 | CH23: 0 | CI23: 1 | CR23: 22 | CS23: =Qual_FreeText!Z23 -> DIKSHA | CT23: =Qual_FreeText!X23 -> बहुविधि शिक्षण और बहुविधि अभिव्यक्ति | CU23: 1 | CV23: 0 | CW23: =Qual_FreeText!M23 -> Shaishik Samvaad, Subject Traning, DIgital Traning, Jangana (Cencus Duty) BRC Meetings | CY23: 1
A24: 23 | B24: Rashmi Mishra | C24: Vaibhav Tambe | D24: Datia | E24: Male | F24: 46189 | G24: Maths | H24: 10 | I24: 0 | J24: 0 | K24: 0 | L24: 1 | M24: 0 | N24: 0 | O24: 0 | P24: 5 | Q24: 1 | R24: 1 | S24: 1 | T24: 0 | U24: 0 | V24: 0 | W24: 0 | X24: 0 | Y24: 0 | Z24: 0 | AA24: 1 | AB24: 1 | AC24: Yes | AD24: 0 | AE24: 1 | AF24: 0 | AG24: 0 | AH24: No | AL24: Yes | AM24: No | AN24: 4-5 hrs | AO24: 0 | AP24: 1 | AQ24: 0 | AR24: 0 | AS24: 0 | AT24: 0 | AU24: 0 | AV24: 0 | AW24: 0 | AX24: 1 | AY24: 1 | AZ24: 0 | BA24: 0 | BB24: 0 | BC24: 0 | BD24: 0 | BE24: 0 | BF24: JSK Whatsapp | BG24: 1 | BH24: 0 | BI24: 0 | BJ24: 0 | BQ24: 5 | BR24: 0 | BS24: 0 | BT24: 0 | BU24: 0 | BV24: 0 | BW24: 1 | BX24: Yes | BY24: 1 | BZ24: 0 | CA24: 0 | CB24: 0 | CC24: 0 | CD24: No | CE24: 0 | CF24: 0 | CG24: 0 | CH24: 0 | CI24: 1 | CR24: 23 | CS24: =Qual_FreeText!Z24 -> DIKSHA | CT24: =Qual_FreeText!X24 -> Teacher not able to recall course name | CU24: 1 | CV24: 0 | CW24: =Qual_FreeText!M24 -> Participated in Subject Training, Digital Training, CLSS (Aug, Dec), and election-related duties during the 2025–26 academic year; no other activities were mentioned. | CY24: 1
A25: 24 | B25: Vaibhav Kurwade | C25: Anjali | D25: Narsinghpur | E25: Male | F25: 46188 | G25: Social Science Sanskrit | H25: 43 | I25: 0 | J25: 0 | K25: 1 | L25: 0 | M25: 1 | N25: 0 | O25: 0 | P25: 2 | Q25: 1 | R25: 1 | S25: 1 | T25: 0 | U25: 0 | V25: 1 | W25: 0 | X25: 0 | Y25: 0 | Z25: 0 | AA25: 0 | AB25: 0 | AC25: Yes | AD25: 0 | AE25: 1 | AF25: 0 | AG25: 0 | AH25: No | AK25: Yes | AL25: Yes | AM25: Yes | AN25: 3 hr | AO25: 0 | AP25: 1 | AQ25: 0 | AR25: 1 | AS25: 0 | AT25: 0 | AU25: 0 | AV25: 1 | AW25: 0 | AX25: 0 | AY25: 0 | AZ25: 0 | BA25: 1 | BB25: 0 | BC25: 0 | BD25: 0 | BE25: 0 | BF25: JSK Whatsapp Letter | BG25: 1 | BH25: 0 | BI25: 1 | BJ25: 0 | BQ25: 1 | BR25: 0 | BS25: 0 | BT25: 0 | BU25: 0 | BV25: 0 | BW25: 1 | BX25: Couldn't remember particular learning from CLSS | BY25: 1 | BZ25: 1 | CA25: 0 | CB25: 0 | CC25: 0 | CD25: Yes | CE25: 0 | CF25: 0 | CG25: 0 | CH25: 0 | CI25: 1 | CR25: 24 | CS25: =Qual_FreeText!Z25 -> DIKSHA and IGOT | CT25: =Qual_FreeText!X25 -> not able to recall | CU25: 1 | CV25: 1 | CW25: =Qual_FreeText!M25 -> CLSS in July, YTL, Digital training, subject training- (not remember the exact time), | CY25: 1
A26: 25 | B26: Rahul Kumar | C26: Devendra Sharma | D26: Ujjain | E26: Female | F26: 46182 | G26: Social Science | H26: 18 | I26: 0 | J26: 0 | K26: 1 | L26: 0 | M26: 0 | N26: 0 | O26: 0 | P26: 4 | Q26: 1 | R26: 1 | S26: 1 | T26: 0 | U26: 0 | V26: 1 | W26: 0 | X26: 0 | Y26: 0 | Z26: 0 | AA26: 0 | AB26: 0 | AC26: Yes | AD26: 0 | AE26: 1 | AF26: 0 | AG26: 1 | AH26: Not sure | AK26: Not Sure | AL26: Yes | AM26: Yes | AN26: 3 hr | AO26: 0 | AP26: 1 | AQ26: 0 | AR26: 0 | AS26: 1 | AT26: 0 | AU26: 1 | AV26: 0 | AW26: 0 | AX26: 0 | AY26: 0 | AZ26: 0 | BA26: 1 | BB26: 0 | BC26: 0 | BD26: 0 | BE26: 0 | BF26: JSK Whatsapp | BG26: 1 | BH26: 0 | BI26: 0 | BJ26: 0 | BQ26: 1 | BR26: 0 | BS26: 0 | BT26: 0 | BU26: 0 | BV26: 0 | BW26: 1 | BX26: Couldn't remember particular learning from CLSS | BY26: 0 | BZ26: 1 | CA26: 0 | CB26: 0 | CC26: 0 | CD26: No | CE26: 0 | CF26: 0 | CG26: 0 | CH26: 0 | CI26: 1 | CR26: 25 | CS26: =Qual_FreeText!Z26 -> courses on Karmyogi app/DIKSHA | CT26: =Qual_FreeText!X26 -> RSK | CU26: 1 | CV26: 0 | CW26: =Qual_FreeText!M26 -> The teacher participated in the following professional development activities: Subject-Specific Training (July 2025), CLSS (September 2025), and the PLC Course (January 2026). | CY26: 1
A27: 26 | B27: Dilip Kag | C27: Sonali Patidar | D27: Dhar | E27: Female | F27: 46189 | G27: English Science | H27: 28 | I27: 0 | J27: 1 | K27: 0 | L27: 0 | M27: 0 | N27: 1 | O27: 0 | P27: 4 | Q27: 1 | R27: 1 | S27: 1 | T27: 0 | U27: 0 | V27: 0 | W27: 0 | X27: 0 | Y27: 0 | Z27: 0 | AA27: 1 | AB27: 0 | AC27: Yes | AD27: 0 | AE27: 1 | AF27: 0 | AG27: 0 | AH27: Yes | AL27: No | AN27: 1 hr | AO27: 0 | AP27: 1 | AQ27: 0 | AR27: 1 | AS27: 0 | AT27: 0 | AU27: 1 | AV27: 0 | AW27: 0 | AX27: 0 | AY27: 0 | AZ27: 0 | BA27: 1 | BB27: 0 | BC27: 0 | BD27: 0 | BE27: 0 | BF27: JSK Whatsapp | BG27: 1 | BH27: 0 | BI27: 0 | BJ27: 0 | BQ27: 4 | BR27: 1 | BS27: 1 | BT27: 0 | BU27: 1 | BV27: 1 | BW27: 0 | BX27: Yes | BY27: 0 | BZ27: 0 | CA27: 1 | CB27: 0 | CC27: 0 | CD27: Yes | CE27: 1 | CF27: 1 | CG27: 0 | CH27: 0 | CI27: 0 | CR27: 26 | CS27: =Qual_FreeText!Z27 -> 0 | CT27: =Qual_FreeText!X27 -> 0 | CU27: 0 | CV27: 0 | CW27: =Qual_FreeText!M27 -> शैक्षिक संवाद अगस्त, सितम्बर, दिसंबर, जनवरी
A28: 27 | B28: Vaibhav Kurwade | C28: Anjali | D28: Jabalpur | E28: Female | F28: 46189 | G28: English Social Science | H28: 16 | I28: 0 | J28: 1 | K28: 1 | L28: 0 | M28: 0 | N28: 0 | O28: 0 | P28: 1 | Q28: 1 | R28: 0 | S28: 1 | T28: 0 | U28: 0 | V28: 0 | W28: 0 | X28: 1 | Y28: 0 | Z28: 0 | AA28: 1 | AB28: 0 | AC28: Yes | AD28: 0 | AE28: 1 | AF28: 0 | AG28: 0 | AH28: Not sure | AL28: No | AN28: 1 hr | AO28: 1 | AP28: 0 | AQ28: 0 | BK28: Yes | BL28: 1 | BM28: 0 | BN28: 0 | BO28: 1 | BP28: 0 | BQ28: 1 | BR28: 0 | BS28: 0 | BT28: 0 | BU28: 0 | BV28: 0 | BW28: 1 | BX28: Couldn't remember particular learning from CLSS | BY28: 0 | BZ28: 0 | CA28: 0 | CB28: 1 | CC28: 0 | CD28: Yes | CE28: 1 | CF28: 0 | CG28: 0 | CH28: 1 | CI28: 0 | CR28: 27 | CS28: =Qual_FreeText!Z28 -> 0 | CT28: =Qual_FreeText!X28 -> 0 | CU28: 0 | CV28: 0 | CW28: =Qual_FreeText!M28 -> Subject Training– April/May, CLSS – 1 session, JSK Meeting – Monthly, SIR – November
A29: 28 | B29: Pushpendra Singh | C29: Krishna | D29: Rewa | E29: Male | F29: 46189 | G29: Maths Science | H29: 19 | I29: 0 | J29: 0 | K29: 0 | L29: 1 | M29: 0 | N29: 1 | O29: 0 | P29: 7 | Q29: 1 | R29: 0 | S29: 1 | T29: 0 | U29: 0 | V29: 0 | W29: 0 | X29: 1 | Y29: 0 | Z29: 0 | AA29: 1 | AB29: 0 | AC29: Yes | AD29: 1 | AE29: 1 | AF29: 0 | AG29: 0 | AH29: Yes | AL29: No | AO29: 1 | AP29: 0 | AQ29: 0 | BK29: Yes | BL29: 1 | BM29: 0 | BN29: 0 | BO29: 1 | BP29: 0 | BQ29: 3 | BR29: 1 | BS29: 1 | BT29: 0 | BU29: 1 | BV29: 0 | BW29: 0 | BX29: Yes | BY29: 0 | BZ29: 0 | CA29: 1 | CB29: 0 | CC29: 0 | CD29: Yes | CE29: 1 | CF29: 1 | CG29: 0 | CH29: 0 | CI29: 0 | CR29: 28 | CS29: =Qual_FreeText!Z29 -> 0 | CT29: =Qual_FreeText!X29 -> 0 | CU29: 0 | CV29: 0 | CW29: =Qual_FreeText!M29 -> During the academic year, the teacher participated in Mathematics MT Training and attended CLSS sessions for Class 3 in August, September, and December
A30: 29 | B30: Rashmi Mishra | C30: Vaibhav Tambe | D30: Datia | E30: Male | F30: 46190 | G30: Hindi Social Science | H30: 26 | I30: 1 | J30: 0 | K30: 1 | L30: 0 | M30: 0 | N30: 0 | O30: 0 | P30: 5 | Q30: 1 | R30: 1 | S30: 1 | T30: 0 | U30: 0 | V30: 0 | W30: 0 | X30: 0 | Y30: 0 | Z30: 0 | AA30: 0 | AB30: 0 | AC30: Yes | AD30: 0 | AE30: 1 | AF30: 0 | AG30: 0 | AH30: No | AL30: Yes | AM30: No | AN30: 2 hr | AO30: 0 | AP30: 1 | AQ30: 0 | AR30: 0 | AS30: 0 | AT30: 0 | AU30: 0 | AV30: 1 | AW30: 0 | AX30: 0 | AY30: 0 | AZ30: 0 | BA30: 1 | BB30: 0 | BC30: 0 | BD30: 0 | BE30: 0 | BF30: JSK Whatsapp | BG30: 1 | BH30: 0 | BI30: 0 | BJ30: 0 | BQ30: 4 | BR30: 1 | BS30: 1 | BT30: 1 | BU30: 0 | BV30: 0 | BW30: 0 | BX30: Yes | BY30: 1 | BZ30: 0 | CA30: 0 | CB30: 0 | CC30: 0 | CD30: Yes | CE30: 0 | CF30: 0 | CG30: 0 | CH30: 1 | CI30: 0 | CR30: 29 | CS30: =Qual_FreeText!Z30 -> DIKSHA | CT30: =Qual_FreeText!X30 -> Shaishik Samwaad: Sath Sahyog aur SIkh | CU30: 1 | CV30: 0 | CW30: =Qual_FreeText!M30 -> Subject Training, CLSS, Digital Training. | CY30: 1
A31: 30 | B31: Ritesh Pandey | C31: Other | D31: Chhindwara | E31: Female | F31: 46191 | G31: Maths | H31: 15 | I31: 0 | J31: 0 | K31: 0 | L31: 1 | M31: 0 | N31: 0 | O31: 0 | P31: 1 | Q31: 1 | R31: 1 | S31: 1 | T31: 0 | U31: 0 | V31: 0 | W31: 0 | X31: 0 | Y31: 0 | Z31: 0 | AA31: 0 | AB31: 1 | AC31: Yes | AD31: 0 | AE31: 1 | AF31: 0 | AG31: 0 | AH31: Not sure | AL31: Yes | AM31: Yes | AN31: 3 hr | AO31: 1 | AP31: 0 | AQ31: 0 | AR31: 1 | AS31: 1 | AT31: 1 | AU31: 0 | AV31: 1 | AW31: 0 | AX31: 0 | AY31: 1 | AZ31: 0 | BA31: 1 | BB31: 1 | BC31: 0 | BD31: 0 | BE31: 0 | BF31: JSK Whatsapp Letter | BG31: 1 | BH31: 0 | BI31: 1 | BJ31: 0 | BQ31: 5 | BR31: 0 | BS31: 0 | BT31: 0 | BU31: 0 | BV31: 0 | BW31: 1 | BX31: Yes | BY31: 0 | BZ31: 0 | CA31: 0 | CB31: 0 | CC31: 1 | CD31: Yes | CE31: 0 | CF31: 1 | CG31: 0 | CH31: 0 | CI31: 1 | CR31: 30 | CS31: =Qual_FreeText!Z31 -> DIksha, Igot | CT31: =Qual_FreeText!X31 -> Karmyogi, Shaikshik Smavad | CU31: 1 | CV31: 1 | CW31: =Qual_FreeText!M31 -> 5 ClSS in all month, she couldnt recall month name. | CY31: 1
A32: 31 | B32: Srujan Deshpande | C32: Devendra Sharma | D32: Shajapur | E32: Female | F32: 46185 | G32: Maths Science | H32: 20 | I32: 0 | J32: 0 | K32: 0 | L32: 1 | M32: 0 | N32: 1 | O32: 0 | P32: 3 | Q32: 1 | R32: 1 | S32: 1 | T32: 0 | U32: 0 | V32: 1 | W32: 0 | X32: 0 | Y32: 0 | Z32: 1 | AA32: 0 | AB32: 0 | AC32: Yes | AD32: 1 | AE32: 1 | AF32: 0 | AG32: 0 | AH32: Yes | AK32: Not Sure | AL32: Yes | AM32: Yes | AN32: 3 hr | AO32: 0 | AP32: 1 | AQ32: 0 | AR32: 1 | AS32: 1 | AT32: 1 | AU32: 1 | AV32: 1 | AW32: 1 | AX32: 0 | AY32: 0 | AZ32: 0 | BA32: 1 | BB32: 0 | BC32: 0 | BD32: 0 | BE32: 0 | BF32: JSK Whatsapp Letter | BG32: 1 | BH32: 0 | BI32: 1 | BJ32: 0 | BQ32: 4 | BR32: 1 | BS32: 1 | BT32: 1 | BU32: 0 | BV32: 1 | BW32: 0 | BX32: Yes | BY32: 0 | BZ32: 0 | CA32: 1 | CB32: 0 | CC32: 0 | CD32: Yes | CE32: 0 | CF32: 0 | CG32: 0 | CH32: 0 | CI32: 1 | CR32: 31 | CS32: =Qual_FreeText!Z32 -> Diksha, iGot कर्मयोगी | CT32: =Qual_FreeText!X32 -> शैक्षिक संवाद, बहुविधि शिक्षण, AI, classroom managment | CU32: 1 | CV32: 1 | CW32: =Qual_FreeText!M32 -> विषय प्रशिक्षण (2025-26), CLSS सत्र (सभी), DIKSHA पाठ्यक्रम एवं विभागीय ऑनलाइन प्रशिक्षण (2 सप्ताह मे 4-6 घंटे)। | CY32: 1
A33: 32 | B33: Srujan Deshpande | C33: Devendra Sharma | D33: Shajapur | E33: Female | F33: 46186 | G33: Maths Science | H33: 22 | I33: 0 | J33: 0 | K33: 0 | L33: 1 | M33: 0 | N33: 1 | O33: 0 | P33: 6 | Q33: 1 | R33: 0 | S33: 1 | T33: 0 | U33: 0 | V33: 1 | W33: 0 | X33: 0 | Y33: 0 | Z33: 0 | AA33: 0 | AB33: 1 | AC33: Yes | AD33: 0 | AE33: 1 | AF33: 0 | AG33: 0 | AH33: Yes | AK33: Yes | AL33: Yes | AM33: Yes | AN33: 2 hr | AO33: 0 | AP33: 1 | AQ33: 1 | BL33: 0 | BM33: 0 | BN33: 1 | BO33: 0 | BP33: 0 | BQ33: 5 | BR33: 0 | BS33: 0 | BT33: 0 | BU33: 0 | BV33: 0 | BW33: 1 | BX33: Couldn't remember particular learning from CLSS | BY33: 0 | BZ33: 1 | CA33: 0 | CB33: 0 | CC33: 0 | CD33: Yes | CE33: 0 | CF33: 0 | CG33: 0 | CH33: 0 | CI33: 1 | CR33: 32 | CS33: =Qual_FreeText!Z33 -> Diksha, कर्मयोगी | CT33: =Qual_FreeText!X33 -> तत्काल याद नहीं आए किन्तु कोर्स किए है। | CU33: 1 | CV33: 0 | CW33: =Qual_FreeText!M33 -> विषय प्रशिक्षण (विज्ञान एवं गणित), CLSS (5 सत्र), YTL ऑनलाइन सत्र, जनगणना कार्य। | CY33: 1
A34: 33 | B34: Srujan Deshpande | C34: Devendra Sharma | D34: Dewas | E34: Male | F34: 46188 | G34: Maths | H34: 20 | I34: 0 | J34: 0 | K34: 0 | L34: 1 | M34: 0 | N34: 0 | O34: 0 | P34: 1 | Q34: 1 | R34: 1 | S34: 1 | T34: 0 | U34: 0 | V34: 0 | W34: 0 | X34: 0 | Y34: 1 | Z34: 0 | AA34: 1 | AB34: 0 | AC34: Yes | AD34: 0 | AE34: 1 | AF34: 0 | AG34: 0 | AH34: Yes | AL34: Yes | AM34: Yes | AN34: 3 hr | AO34: 0 | AP34: 1 | AQ34: 1 | AR34: 1 | AS34: 1 | AT34: 1 | AU34: 1 | AV34: 0 | AW34: 0 | AX34: 0 | AY34: 0 | AZ34: 0 | BA34: 1 | BB34: 0 | BC34: 0 | BD34: 0 | BE34: 0 | BF34: JSK Whatsapp Letter | BG34: 1 | BH34: 0 | BI34: 1 | BJ34: 0 | BQ34: 5 | BR34: 1 | BS34: 0 | BT34: 0 | BU34: 0 | BV34: 0 | BW34: 0 | BX34: Yes | BY34: 0 | BZ34: 1 | CA34: 0 | CB34: 0 | CC34: 0 | CD34: Yes | CE34: 0 | CF34: 0 | CG34: 0 | CH34: 0 | CI34: 1 | CR34: 33 | CS34: =Qual_FreeText!Z34 -> याद नहीं है | CT34: =Qual_FreeText!X34 -> दीक्षा के कोर्स किए है | CU34: 0 | CV34: 0 | CW34: =Qual_FreeText!M34 -> वर्ष 2025-26 के दौरान विषय प्रशिक्षण 3 दिवसीय , PLC/CLSS (20-25 घंटे), DIKSHA डिजिटल कोर्स (4 घंटे) एवं अन्य ऑनलाइन प्रशिक्षणों में भागीदारी की (7-10 घंटे)। | CY34: 1
A35: 34 | B35: Srujan Deshpande | C35: Dilip Kag | D35: Ratlam | E35: Male | F35: 46191 | G35: Hindi Social Science | H35: 28 | I35: 1 | J35: 0 | K35: 1 | L35: 0 | M35: 0 | N35: 0 | O35: 0 | P35: 6 | Q35: 1 | R35: 0 | S35: 1 | T35: 0 | U35: 0 | V35: 0 | W35: 0 | X35: 0 | Y35: 0 | Z35: 0 | AA35: 0 | AB35: 1 | AC35: Yes | AD35: 0 | AE35: 1 | AF35: 0 | AG35: 0 | AH35: No | AL35: No | AO35: 0 | AP35: 1 | AQ35: 0 | BK35: Yes | BL35: 1 | BM35: 1 | BN35: 1 | BO35: 1 | BP35: 0 | BQ35: 4 | BR35: 0 | BS35: 0 | BT35: 0 | BU35: 0 | BV35: 0 | BW35: 1 | BX35: Couldn't remember particular learning from CLSS | BY35: 0 | BZ35: 0 | CA35: 0 | CB35: 1 | CC35: 0 | CD35: Yes | CE35: 0 | CF35: 0 | CG35: 0 | CH35: 0 | CI35: 1 | CR35: 34 | CS35: =Qual_FreeText!Z35 -> 0 | CT35: =Qual_FreeText!X35 -> 0 | CU35: 0 | CV35: 0 | CW35: =Qual_FreeText!M35 -> Social Science Subject Training (Piploda) – 2025-26, CLSS – Monthly, Deworming Training – One day, Science Model Exhibition – 2025-26
A36: 35 | B36: Deeksha Singh | C36: Dharmendra Mishra | D36: Chhatarpur | E36: Male | F36: 46192 | G36: Maths Science | H36: 13 | I36: 0 | J36: 0 | K36: 0 | L36: 1 | M36: 0 | N36: 1 | O36: 0 | P36: 6 | Q36: 1 | R36: 1 | S36: 1 | T36: 1 | U36: 0 | V36: 0 | W36: 0 | X36: 0 | Y36: 0 | Z36: 0 | AA36: 0 | AB36: 1 | AC36: Yes | AD36: 0 | AE36: 0 | AF36: 0 | AG36: 1 | AI36: Not Sure | AL36: Yes | AM36: Yes | AN36: 2 hr | AO36: 0 | AP36: 1 | AQ36: 0 | AR36: 0 | AS36: 0 | AT36: 0 | AU36: 0 | AV36: 0 | AW36: 0 | AX36: 1 | AY36: 1 | AZ36: 1 | BA36: 1 | BB36: 1 | BC36: 0 | BD36: 1 | BE36: 0 | BF36: JSK Whatsapp | BG36: 1 | BH36: 0 | BI36: 0 | BJ36: 0 | BQ36: 5 | BR36: 1 | BS36: 0 | BT36: 0 | BU36: 1 | BV36: 1 | BW36: 0 | BX36: Yes | BY36: 0 | BZ36: 0 | CA36: 0 | CB36: 1 | CC36: 0 | CD36: Yes | CE36: 0 | CF36: 0 | CG36: 0 | CH36: 0 | CI36: 1 | CR36: 35 | CS36: =Qual_FreeText!Z36 -> IGOT Karmyogi App, Diksha Courses | CT36: =Qual_FreeText!X36 -> बाल सुधार, महिलाओं की सुरक्षा, शैक्षणिक अधिगम | CU36: 1 | CV36: 1 | CW36: =Qual_FreeText!M36 -> CLSS 5(Aug to Dec) , Math, Science training 2 days(July), Igot Karmyogi app पर प्रशिक्षण लिया है, Apaar ID और जनगणना की ट्रेनिंग में पार्टिसिपेट | CY36: 1
A37: 36 | B37: Ritesh Pandey | C37: Other | D37: Chhindwara | E37: Male | F37: 46192 | G37: Maths | H37: 12 | I37: 0 | J37: 0 | K37: 0 | L37: 1 | M37: 0 | N37: 0 | O37: 0 | P37: 6 | Q37: 1 | R37: 1 | S37: 1 | T37: 0 | U37: 0 | V37: 0 | W37: 0 | X37: 1 | Y37: 0 | Z37: 0 | AA37: 0 | AB37: 1 | AC37: Yes | AD37: 0 | AE37: 0 | AF37: 0 | AG37: 1 | AL37: Yes | AM37: Not sure | AN37: 4-5 hrs | AO37: 0 | AP37: 1 | AQ37: 0 | AR37: 0 | AS37: 0 | AT37: 0 | AU37: 0 | AV37: 0 | AW37: 0 | AX37: 1 | AY37: 1 | AZ37: 0 | BA37: 0 | BB37: 0 | BC37: 0 | BD37: 0 | BE37: 0 | BF37: JSK Whatsapp School Whatsapp Letter | BG37: 1 | BH37: 1 | BI37: 1 | BJ37: 0 | BQ37: 3 | BR37: 0 | BS37: 0 | BT37: 0 | BU37: 0 | BV37: 0 | BW37: 1 | BX37: Yes | BY37: 0 | BZ37: 0 | CA37: 1 | CB37: 0 | CC37: 0 | CD37: Yes | CE37: 0 | CF37: 0 | CG37: 0 | CH37: 0 | CI37: 1 | CR37: 36 | CS37: =Qual_FreeText!Z37 -> Igot | CT37: =Qual_FreeText!X37 -> 12 | CU37: 0 | CV37: 1 | CW37: =Qual_FreeText!M37 -> It is mentioned, timeline was not told. | CY37: 1
A38: 37 | B38: Deeksha Singh | C38: Dharmendra Mishra | D38: Chhatarpur | E38: Male | F38: 46193 | G38: Social Science Sanskrit | H38: 16 | I38: 0 | J38: 0 | K38: 1 | L38: 0 | M38: 1 | N38: 0 | O38: 0 | P38: 6 | Q38: 1 | R38: 1 | S38: 1 | T38: 0 | U38: 0 | V38: 1 | W38: 0 | X38: 0 | Y38: 0 | Z38: 0 | AA38: 0 | AB38: 1 | AC38: Yes | AD38: 0 | AE38: 0 | AF38: 0 | AG38: 1 | AK38: Yes | AL38: Yes | AM38: Yes | AN38: 2 hr | AO38: 1 | AP38: 1 | AQ38: 0 | AR38: 0 | AS38: 0 | AT38: 0 | AU38: 0 | AV38: 0 | AW38: 0 | AX38: 1 | AY38: 0 | AZ38: 0 | BA38: 1 | BB38: 0 | BC38: 0 | BD38: 0 | BE38: 0 | BF38: JSK Whatsapp | BG38: 1 | BH38: 0 | BI38: 0 | BJ38: 0 | BQ38: 2 | BR38: 0 | BS38: 0 | BT38: 0 | BU38: 0 | BV38: 0 | BW38: 1 | BX38: Couldn't remember particular learning from CLSS | BY38: 0 | BZ38: 0 | CA38: 0 | CB38: 1 | CC38: 0 | CD38: Yes | CE38: 0 | CF38: 0 | CG38: 0 | CH38: 0 | CI38: 1 | CR38: 37 | CS38: =Qual_FreeText!Z38 -> IGOT | CT38: =Qual_FreeText!X38 -> पोस्को एक्ट, मादक पदार्थों से रिलेटेड कोर्स, NEP से रिलेटेड कोर्स IGOT ऐप पर | CU38: 0 | CV38: 1 | CW38: =Qual_FreeText!M38 -> CLSS -2, Subject Training -2day, YTL-1, IGOT पर लगभग 70 घंटे की ट्रेनिंग, दीक्षा ऐप पर शिक्षक संशय में थे। | CY38: 1
A39: 38 | B39: Srujan Deshpande | C39: Devendra Sharma | D39: Dewas | E39: Male | F39: 46189 | G39: Science | H39: 11 | I39: 0 | J39: 0 | K39: 0 | L39: 0 | M39: 0 | N39: 1 | O39: 0 | P39: 4 | Q39: 1 | R39: 1 | S39: 1 | T39: 0 | U39: 0 | V39: 1 | W39: 0 | X39: 0 | Y39: 1 | Z39: 1 | AA39: 0 | AB39: 0 | AC39: Yes | AD39: 0 | AE39: 1 | AF39: 0 | AG39: 0 | AH39: Yes | AK39: Yes | AL39: Yes | AM39: Yes | AN39: 3 hr | AO39: 0 | AP39: 1 | AQ39: 0 | AR39: 1 | AS39: 1 | AT39: 1 | AU39: 1 | AV39: 0 | AW39: 0 | AX39: 0 | AY39: 0 | AZ39: 0 | BA39: 1 | BB39: 0 | BC39: 0 | BD39: 0 | BE39: 0 | BF39: JSK Whatsapp Letter | BG39: 1 | BH39: 0 | BI39: 1 | BJ39: 0 | BQ39: Not Participated | BX39: Couldn't remember particular learning from CLSS | BY39: 0 | BZ39: 0 | CA39: 0 | CB39: 1 | CC39: 0 | CD39: Yes | CE39: 0 | CF39: 0 | CG39: 0 | CH39: 0 | CI39: 1 | CR39: 38 | CS39: =Qual_FreeText!Z39 -> Diksha | CT39: =Qual_FreeText!X39 -> याद नहीं है। | CU39: 1 | CV39: 0 | CW39: =Qual_FreeText!M39 -> NEP 20 प्रशिक्षण, विषय प्रशिक्षण, दीक्षा प्लेटफॉर्म के प्रशिक्षण एवं YTL गतिविधियों में वर्ष 2025-26 के दौरान सहभागिता। | CY39: 1
A40: 39 | B40: Ritesh Pandey | C40: Other | D40: Seoni | E40: Female | F40: 46193 | G40: Maths Science | H40: 3 | I40: 0 | J40: 0 | K40: 0 | L40: 1 | M40: 0 | N40: 1 | O40: 0 | P40: 6 | Q40: 1 | R40: 0 | S40: 1 | T40: 0 | U40: 0 | V40: 0 | W40: 0 | X40: 0 | Y40: 0 | Z40: 0 | AA40: 0 | AB40: 1 | AC40: Yes | AD40: 0 | AE40: 0 | AF40: 0 | AG40: 1 | AL40: Yes | AM40: Yes | AN40: 2 hr | AO40: 0 | AP40: 1 | AQ40: 0 | BK40: Yes | BL40: 0 | BM40: 0 | BN40: 0 | BO40: 1 | BP40: 0 | BQ40: 5 | BR40: 0 | BS40: 0 | BT40: 0 | BU40: 0 | BV40: 0 | BW40: 1 | BX40: Yes | BY40: 0 | BZ40: 0 | CA40: 0 | CB40: 0 | CC40: 1 | CD40: Yes | CE40: 0 | CF40: 0 | CG40: 0 | CH40: 0 | CI40: 1 | CR40: 39 | CS40: =Qual_FreeText!Z40 -> Igot | CT40: =Qual_FreeText!X40 -> Karmyogi | CU40: 0 | CV40: 1 | CW40: =Qual_FreeText!M40 -> She couldn't mention but did mention about subject training and CLSS. | CY40: 1
A41: 40 | B41: Srujan Deshpande | C41: Dilip Kag | D41: Ratlam | E41: Male | F41: 46192 | G41: Hindi English | H41: 19 | I41: 1 | J41: 1 | K41: 0 | L41: 0 | M41: 0 | N41: 0 | O41: 0 | P41: 5 | Q41: 1 | R41: 1 | S41: 1 | T41: 0 | U41: 0 | V41: 0 | W41: 0 | X41: 0 | Y41: 0 | Z41: 0 | AA41: 0 | AB41: 1 | AC41: Yes | AD41: 0 | AE41: 1 | AF41: 0 | AG41: 0 | AH41: No | AL41: Yes | AM41: No | AN41: 3 hr | AO41: 0 | AP41: 1 | AQ41: 0 | AR41: 0 | AS41: 0 | AT41: 0 | AU41: 0 | AV41: 0 | AW41: 0 | AX41: 1 | AY41: 0 | AZ41: 0 | BA41: 1 | BB41: 0 | BC41: 0 | BD41: 0 | BE41: 0 | BF41: JSK Whatsapp Letter | BG41: 1 | BH41: 0 | BI41: 1 | BJ41: 0 | BQ41: 5 | BR41: 1 | BS41: 1 | BT41: 0 | BU41: 0 | BV41: 0 | BW41: 0 | BX41: Couldn't remember particular learning from CLSS | BY41: 0 | BZ41: 0 | CA41: 0 | CB41: 0 | CC41: 1 | CD41: Yes | CE41: 0 | CF41: 1 | CG41: 0 | CH41: 1 | CI41: 0 | CR41: 40 | CS41: =Qual_FreeText!Z41 -> Diksha, कर्मयोगी | CT41: =Qual_FreeText!X41 -> कोर्स के नाम याद नहीं है | CU41: 1 | CV41: 0 | CW41: =Qual_FreeText!M41 -> शैक्षिक संवाद (5 महीने), शिक्षक प्रशिक्षण (सा विज्ञान) 3 दिन, दीक्षा के कोर्स (2), जनगणना (महिना भर ), विज्ञान प्रदर्शनी (3 दिन), | CY41: 1
A42: 41 | B42: Pushpendra Singh | C42: Krishna | D42: Sidhi | E42: Male | F42: 46192 | G42: Hindi English | H42: 27 | I42: 1 | J42: 1 | K42: 0 | L42: 0 | M42: 0 | N42: 0 | O42: 0 | P42: 5 | Q42: 1 | R42: 1 | S42: 1 | T42: 0 | U42: 0 | V42: 1 | W42: 0 | X42: 0 | Y42: 0 | Z42: 0 | AA42: 1 | AB42: 1 | AC42: Yes | AD42: 1 | AE42: 0 | AF42: 0 | AG42: 0 | AH42: No | AK42: Not Sure | AL42: Yes | AM42: Yes | AN42: 3 hr | AO42: 1 | AP42: 1 | AQ42: 1 | AR42: 1 | AS42: 0 | AT42: 1 | AU42: 0 | AV42: 0 | AW42: 0 | AX42: 0 | AY42: 1 | AZ42: 0 | BA42: 1 | BB42: 0 | BC42: 0 | BD42: 0 | BE42: 0 | BF42: JSK Whatsapp | BG42: 1 | BH42: 0 | BI42: 0 | BJ42: 0 | BQ42: 5 | BR42: 1 | BS42: 1 | BT42: 1 | BU42: 1 | BV42: 1 | BW42: 0 | BX42: Yes | BY42: 0 | BZ42: 1 | CA42: 1 | CB42: 0 | CC42: 0 | CD42: Yes | CE42: 0 | CF42: 1 | CG42: 0 | CH42: 1 | CI42: 0 | CR42: 41 | CS42: =Qual_FreeText!Z42 -> Diksha App | CT42: =Qual_FreeText!X42 -> DIKSHA Course | CU42: 1 | CV42: 0 | CW42: =Qual_FreeText!M42 -> The teacher attended five CLSS trainings up to January. Along with these, the teacher also participated in Block Level Subject Training for Science and Mathematics, cancer awareness training, election duty training, YouTube Live sessions, and Diksha App training. | CY42: 1
A43: 42 | B43: Rahul Kumar | C43: Ashish Nigam | D43: Neemuch | E43: Male | F43: 46189 | G43: Social Science Sanskrit | H43: 28 | I43: 0 | J43: 0 | K43: 1 | L43: 0 | M43: 1 | N43: 0 | O43: 0 | P43: 4 | Q43: 1 | R43: 1 | S43: 0 | T43: 0 | U43: 0 | V43: 0 | W43: 0 | X43: 1 | Y43: 0 | Z43: 0 | AA43: 1 | AB43: 0 | AC43: Yes | AD43: 0 | AE43: 0 | AF43: 0 | AG43: 1 | AL43: Yes | AM43: Yes | AN43: 2 hr | AO43: 1 | AP43: 1 | AQ43: 1 | AR43: 0 | AS43: 0 | AT43: 0 | AU43: 0 | AV43: 0 | AW43: 0 | AX43: 1 | AY43: 1 | AZ43: 0 | BA43: 1 | BB43: 0 | BC43: 0 | BD43: 0 | BE43: 0 | BF43: JSK Whatsapp School Whatsapp | BG43: 1 | BH43: 1 | BI43: 0 | BJ43: 0 | CJ43: Yes | CK43: 0 | CL43: 0 | CM43: 1 | CN43: 0 | CO43: 0 | CP43: 0 | CR43: 42 | CS43: =Qual_FreeText!Z43 -> Karmyogi app | CT43: =Qual_FreeText!X43 -> he completed the courses on Karmyogi app- Civial Seva Adhiniyam, CCLE, NEP 2020 | CU43: 0 | CV43: 0 | CW43: =Qual_FreeText!M43 -> Participated in 2 CLSS but not able to recall exact month. He participated in In person teachers training in July 2026.
A44: 43 | B44: Rahul Kumar | C44: Sonali Patidar | D44: Mandsaur | E44: Female | F44: 46192 | G44: Science | H44: 16 | I44: 0 | J44: 0 | K44: 0 | L44: 0 | M44: 0 | N44: 1 | O44: 0 | P44: 6 | Q44: 1 | R44: 1 | S44: 0 | T44: 0 | U44: 0 | V44: 0 | W44: 0 | X44: 0 | Y44: 0 | Z44: 0 | AA44: 0 | AB44: 1 | AC44: Yes | AD44: 0 | AE44: 1 | AF44: 0 | AG44: 0 | AH44: Not sure | AL44: Yes | AM44: Not sure | AN44: 1 hr | AO44: 0 | AP44: 1 | AQ44: 0 | AR44: 0 | AS44: 0 | AT44: 0 | AU44: 0 | AV44: 0 | AW44: 0 | AX44: 1 | AY44: 0 | AZ44: 0 | BA44: 1 | BB44: 0 | BC44: 0 | BD44: 0 | BE44: 0 | BF44: JSK Whatsapp | BG44: 1 | BH44: 0 | BI44: 0 | BJ44: 0 | CJ44: Yes | CK44: 0 | CL44: 0 | CM44: 0 | CN44: 0 | CO44: 0 | CP44: 1 | CR44: 43 | CS44: =Qual_FreeText!Z44 -> Karmyogi | CT44: =Qual_FreeText!X44 -> mp civil cervic adhiniyam on i got | CU44: 0 | CV44: 0 | CW44: =Qual_FreeText!M44 -> she participated in subject wise training in july . she attended 3 CLSS but she was not able to recall exact month. she remembered some content related CLSS i.e about homework.
A45: 44 | B45: Aishwarya Yadav | C45: Swetha | D45: Vidisha | E45: Male | F45: 46188 | G45: Maths Science | H45: 15 | I45: 0 | J45: 0 | K45: 0 | L45: 1 | M45: 0 | N45: 1 | O45: 0 | P45: 4 | Q45: 1 | R45: 0 | S45: 0 | T45: 0 | U45: 0 | V45: 0 | W45: 0 | X45: 0 | Y45: 0 | Z45: 0 | AA45: 0 | AB45: 0 | AC45: Yes | AD45: 0 | AE45: 0 | AF45: 0 | AG45: 1 | AL45: No | AO45: 1 | AP45: 0 | AQ45: 0 | BK45: Yes | BL45: 1 | BM45: 0 | BN45: 1 | BO45: 1 | BP45: 1 | CJ45: Yes | CK45: 0 | CL45: 1 | CM45: 0 | CN45: 0 | CO45: 0 | CP45: 0 | CR45: 44 | CS45: =Qual_FreeText!Z45 -> 0 | CT45: =Qual_FreeText!X45 -> 0 | CU45: 0 | CV45: 0 | CW45: =Qual_FreeText!M45 -> The teacher participated in the Math and Science In person training on class 6 textbooks of 2 days each last July.
A46: 45 | B46: Aishwarya Yadav | C46: Bhanu Priya | D46: Raisen | E46: Female | F46: 46195 | G46: Maths Science | H46: 12 | I46: 0 | J46: 0 | K46: 0 | L46: 1 | M46: 0 | N46: 1 | O46: 0 | P46: 6 | Q46: 1 | R46: 1 | S46: 1 | T46: 0 | U46: 0 | V46: 0 | W46: 0 | X46: 0 | Y46: 0 | Z46: 0 | AA46: 0 | AB46: 0 | AC46: Yes | AD46: 0 | AE46: 1 | AF46: 0 | AG46: 0 | AH46: Yes | AL46: Yes | AM46: Yes | AN46: 3 hr | AO46: 1 | AP46: 1 | AQ46: 0 | AR46: 0 | AS46: 1 | AT46: 1 | AU46: 0 | AV46: 0 | AW46: 0 | AY46: 0 | AZ46: 0 | BA46: 1 | BB46: 0 | BC46: 0 | BD46: 0 | BE46: 0 | BF46: JSK Whatsapp Other | BG46: 1 | BH46: 0 | BI46: 0 | BJ46: 1 | BQ46: 3 | BX46: Yes | BY46: 0 | BZ46: 0 | CA46: 1 | CB46: 0 | CC46: 0 | CD46: Yes | CE46: 0 | CF46: 1 | CG46: 0 | CH46: 1 | CI46: 0 | CR46: 45 | CS46: =Qual_FreeText!Z46 -> DIKSHA & Karm Yogi | CT46: =Qual_FreeText!X46 -> PLC on Diksha and Karm Yogi | CU46: 1 | CV46: 0 | CW46: =Qual_FreeText!M46 -> The teacher has attended 3 CLSS in total | CY46: 1
A47: 46 | B47: Naushad Mirza | C47: Deeksha Singh | D47: Panna | E47: Male | F47: 46182 | G47: Social Science | H47: 26 | I47: 0 | J47: 0 | K47: 1 | L47: 0 | M47: 0 | N47: 0 | O47: 0 | P47: 5 | Q47: 1 | R47: 0 | S47: 1 | T47: 0 | U47: 0 | V47: 0 | W47: 0 | X47: 0 | Y47: 0 | Z47: 0 | AA47: 1 | AB47: 0 | AC47: Not sure | AD47: 0 | AE47: 0 | AF47: 0 | AG47: 1 | AL47: Yes | AM47: No | AN47: 1 hr | AO47: 1 | AP47: 0 | AQ47: 0 | BK47: Yes | BL47: 0 | BM47: 1 | BN47: 1 | BO47: 1 | BP47: 0 | BQ47: 5 | BR47: 0 | BS47: 0 | BT47: 1 | BU47: 0 | BV47: 0 | BW47: 0 | BX47: No | BY47: 0 | BZ47: 0 | CA47: 0 | CB47: 1 | CC47: 0 | CD47: Yes | CE47: 0 | CF47: 1 | CG47: 1 | CH47: 0 | CI47: 0 | CR47: 46 | CS47: =Qual_FreeText!Z47 -> 0 | CT47: =Qual_FreeText!X47 -> 0 | CU47: 0 | CV47: 0 | CW47: =Qual_FreeText!M47 -> he has done saikshik samvaad CLSS as co-facilitator.
A48: 47 | B48: Naushad Mirza | C48: Bhanu Priya | D48: Shahdol | E48: Male | F48: 46191 | G48: Science | H48: 29 | I48: 0 | J48: 0 | K48: 0 | L48: 0 | M48: 0 | N48: 1 | O48: 0 | P48: 1 | Q48: 0 | R48: 0 | S48: 0 | T48: 0 | U48: 0 | V48: 0 | W48: 0 | X48: 0 | Y48: 0 | Z48: 0 | AA48: 0 | AB48: 1 | AL48: No | AO48: 1 | AP48: 0 | AQ48: 0 | BK48: Yes | BL48: 0 | BM48: 0 | BN48: 0 | BO48: 1 | BP48: 0 | CJ48: No | CK48: 0 | CL48: 0 | CM48: 0 | CN48: 0 | CO48: 0 | CP48: 1 | CR48: 47 | CS48: =Qual_FreeText!Z48 -> 0 | CT48: =Qual_FreeText!X48 -> 0 | CU48: 0 | CV48: 0 | CW48: =Qual_FreeText!M48 -> 0
A49: 48 | B49: Rajshree Behera | C49: Jay Prakash | D49: Guna | E49: Male | F49: 46192 | G49: Maths Science | H49: 28 | I49: 0 | J49: 0 | K49: 0 | L49: 1 | M49: 0 | N49: 1 | O49: 0 | P49: 6 | Q49: 1 | R49: 0 | S49: 1 | T49: 0 | U49: 0 | V49: 1 | W49: 0 | X49: 0 | Y49: 0 | Z49: 0 | AA49: 0 | AB49: 0 | AC49: Yes | AD49: 0 | AE49: 1 | AF49: 0 | AG49: 0 | AH49: Yes | AK49: Yes | AL49: Yes | AM49: Yes | AN49: 4-5 hrs | AO49: 0 | AP49: 1 | AQ49: 0 | BK49: Yes | BL49: 0 | BM49: 0 | BN49: 1 | BO49: 0 | BP49: 0 | BQ49: 5 | BR49: 0 | BS49: 0 | BT49: 0 | BU49: 0 | BV49: 0 | BW49: 1 | BX49: Yes | BY49: 1 | BZ49: 0 | CA49: 0 | CB49: 0 | CC49: 0 | CD49: Yes | CE49: 0 | CF49: 0 | CG49: 0 | CH49: 0 | CI49: 1 | CR49: 48 | CS49: =Qual_FreeText!Z49 -> 0 | CT49: =Qual_FreeText!X49 -> Diksha | CU49: 0 | CV49: 0 | CW49: =Qual_FreeText!M49 -> Last year teacher participated in a 2-day subject-based training, in which discussions were held on subject-related problems, group work was conducted, and work was done on geometry shape problems. Apart from this, the teacher told that he participated in 12-15 CLSS last year. | CY49: 1
A50: 49 | B50: Aishwarya Yadav | C50: Swetha | D50: Raisen | E50: Male | F50: 46192 | G50: Social Science | H50: 26 | I50: 0 | J50: 0 | K50: 1 | L50: 0 | M50: 0 | N50: 0 | O50: 0 | P50: 4 | Q50: 0 | R50: 0 | S50: 0 | T50: 0 | U50: 0 | V50: 0 | W50: 0 | X50: 0 | Y50: 0 | Z50: 0 | AA50: 0 | AB50: 1 | AL50: No | AN50: 1 hr | AO50: 1 | AP50: 0 | AQ50: 0 | BK50: Yes | BL50: 0 | BM50: 1 | BN50: 0 | BO50: 1 | BP50: 0 | CJ50: Yes | CK50: 0 | CL50: 1 | CM50: 0 | CN50: 0 | CO50: 0 | CP50: 0 | CR50: 49 | CS50: =Qual_FreeText!Z50 -> 0 | CT50: =Qual_FreeText!X50 -> The teacher could recall doing 40-50 courses on DIKSHA during the Covid Period but not post that. | CU50: 0 | CV50: 0 | CW50: =Qual_FreeText!M50 -> The teacher could not recall any activities he has participated in the last year.
A51: 50 | B51: Rajshree Behera | C51: Ashish G | D51: Ashoknagar | E51: Male | F51: 46191 | G51: Social Science | H51: 25 | I51: 0 | J51: 0 | K51: 1 | L51: 0 | M51: 0 | N51: 0 | O51: 0 | P51: 4 | Q51: 1 | R51: 0 | S51: 1 | T51: 0 | U51: 0 | V51: 0 | W51: 0 | X51: 0 | Y51: 0 | Z51: 0 | AA51: 0 | AB51: 1 | AC51: Yes | AD51: 0 | AE51: 1 | AF51: 0 | AG51: 0 | AH51: Yes | AL51: Yes | AM51: Yes | AN51: 2 hr | AO51: 0 | AP51: 1 | AQ51: 0 | BK51: Yes | BL51: 1 | BM51: 0 | BN51: 0 | BO51: 0 | BP51: 0 | BQ51: 4 | BR51: 0 | BS51: 0 | BT51: 0 | BU51: 0 | BV51: 0 | BW51: 1 | BX51: Yes | BY51: 1 | BZ51: 1 | CA51: 1 | CB51: 0 | CC51: 0 | CD51: Yes | CE51: 0 | CF51: 0 | CG51: 0 | CH51: 0 | CI51: 1 | CR51: 50 | CS51: =Qual_FreeText!Z51 -> iGOT | CT51: =Qual_FreeText!X51 -> Karmyogi Courses | CU51: 0 | CV51: 1 | CW51: =Qual_FreeText!M51 -> Subject Training (July), CLSS (August, October, November and January), iGOT Online (20 Karmyogi Courses) | CY51: 1
A52: 51 | B52: Rajesh Solanki | C52: Ritesh Pandey | D52: Betul | E52: Female | F52: 46196 | G52: Hindi Social Science | H52: 25 | I52: 1 | J52: 0 | K52: 1 | L52: 0 | M52: 0 | N52: 0 | O52: 0 | P52: 6 | Q52: 1 | R52: 0 | S52: 1 | T52: 0 | U52: 0 | V52: 0 | W52: 0 | X52: 0 | Y52: 0 | Z52: 1 | AA52: 0 | AB52: 0 | AC52: Yes | AD52: 1 | AE52: 1 | AF52: 0 | AG52: 0 | AH52: No | AL52: Yes | AM52: Yes | AN52: 2 hr | AO52: 0 | AP52: 1 | AQ52: 0 | BK52: Yes | BL52: 0 | BM52: 0 | BN52: 0 | BO52: 1 | BP52: 0 | BQ52: 5 | BR52: 0 | BS52: 0 | BT52: 0 | BU52: 0 | BV52: 0 | BW52: 1 | BX52: No | BY52: 0 | BZ52: 0 | CA52: 0 | CB52: 1 | CC52: 0 | CD52: Yes | CE52: 0 | CF52: 1 | CG52: 0 | CH52: 0 | CI52: 0 | CR52: 51 | CS52: =Qual_FreeText!Z52 -> I-GOT KARMYOGI एप & DIKSHA (DURING COVID) पर 15 कोर्स किये किसी साधना सप्ताह के दौरान | CT52: =Qual_FreeText!X52 -> 1. AI 2. computer, 3. learning outcome | CU52: 0 | CV52: 1 | CW52: =Qual_FreeText!M52 -> शिक्षिका ने कहाँ कि उन्होंने पूरे पाँच शैक्षिक संवाद में प्रतिभाग किया है, इसके अतिरिक्त कहाँ कि गर्मी की छुट्टियों में सामाजिक विज्ञान में कक्षा 6 की किताब पर प्रशिक्षण प्राप्त किया था। इसके अतिरिक्त 5 दिवसीय स्कूल लीडर्स का प्रशिक्षण डाइट में प्राप्त किया था। ई गोट एप से 15 कोर्स किये जो आर्टफिशल इंटेलिजेंट, और कॉम्प्युटर और लर्निंग आउट्कम जैसे विषय पर थे। | CY52: 1
A53: 52 | B53: Ritesh Pandey | C53: Vaibhav Kurwade | D53: Balaghat | E53: Male | F53: 46186 | G53: Science | H53: 25 | I53: 0 | J53: 0 | K53: 0 | L53: 0 | M53: 0 | N53: 1 | O53: 0 | P53: 6 | Q53: 1 | R53: 1 | S53: 1 | T53: 1 | U53: 0 | V53: 1 | W53: 0 | X53: 0 | Y53: 0 | Z53: 0 | AA53: 0 | AB53: 1 | AC53: Yes | AD53: 0 | AE53: 0 | AF53: 0 | AG53: 1 | AI53: Yes | AK53: Yes | AL53: Yes | AM53: Yes | AN53: 4-5 hrs | AO53: 1 | AP53: 1 | AQ53: 0 | AR53: 1 | AS53: 1 | AT53: 1 | AU53: 0 | AV53: 0 | AW53: 0 | AX53: 0 | AY53: 0 | AZ53: 0 | BA53: 1 | BB53: 0 | BC53: 0 | BD53: 0 | BE53: 0 | BF53: JSK Whatsapp | BG53: 1 | BH53: 0 | BI53: 0 | BJ53: 0 | BQ53: 5 | BR53: 0 | BS53: 0 | BT53: 0 | BU53: 0 | BV53: 0 | BW53: 1 | BX53: Yes | BY53: 0 | BZ53: 0 | CA53: 0 | CB53: 1 | CC53: 0 | CD53: Yes | CE53: 0 | CF53: 0 | CG53: 0 | CH53: 0 | CI53: 1 | CR53: 52 | CS53: =Qual_FreeText!Z53 -> Diksha and iGOT karmayogi | CT53: =Qual_FreeText!X53 -> IGOT And Diksha | CU53: 1 | CV53: 1 | CW53: =Qual_FreeText!M53 -> He participated in Science Subject training in the month of June and July. From August he participated in Shaikshik samvad. In the month of March and April attended digital training on AI from iGOT platform, he also completed digital course on Diksha but unable to recall the name of course and timeline. | CY53: 1
A54: 53 | B54: Naushad Mirza | C54: Pushpendra Singh | D54: Shahdol | E54: Male | F54: 46185 | G54: Social Science Sanskrit | H54: 40 | I54: 0 | J54: 0 | K54: 1 | L54: 0 | M54: 1 | N54: 0 | O54: 0 | P54: 6 | Q54: 1 | R54: 1 | S54: 1 | T54: 0 | U54: 0 | V54: 0 | W54: 0 | X54: 0 | Y54: 0 | Z54: 0 | AA54: 0 | AB54: 1 | AC54: Yes | AD54: 0 | AE54: 0 | AF54: 0 | AG54: 1 | AL54: Yes | AM54: Yes | AN54: 4-5 hrs | AO54: 0 | AP54: 1 | AQ54: 0 | AR54: 0 | AS54: 0 | AT54: 0 | AU54: 0 | AV54: 0 | AW54: 0 | AX54: 1 | AY54: 0 | AZ54: 0 | BA54: 1 | BB54: 0 | BC54: 0 | BD54: 0 | BE54: 0 | BF54: JSK Whatsapp | BG54: 1 | BH54: 0 | BI54: 0 | BJ54: 0 | BQ54: 3 | BR54: 1 | BS54: 0 | BT54: 1 | BU54: 1 | BV54: 0 | BW54: 0 | BX54: Yes | BY54: 0 | BZ54: 0 | CA54: 0 | CB54: 1 | CC54: 0 | CD54: Yes | CE54: 0 | CF54: 0 | CG54: 0 | CH54: 0 | CI54: 1 | CR54: 53 | CS54: =Qual_FreeText!Z54 -> Diksha | CT54: =Qual_FreeText!X54 -> RSK | CU54: 1 | CV54: 0 | CW54: =Qual_FreeText!M54 -> The teacher participated in multiple professional and academic development initiatives during the year, including Subject Training (August), regular Shaikshik Sanvaad (CLSS) sessions, and self-learning through DIKSHA courses. He also contributed to academic enrichment activities such as the District-Level Science Model Exhibition. In addition, he engaged in administrative and school improvement processes through meetings with the DPC regarding school building repairs and participation in Sankul-level meetings facilitated by the CAC. | CY54: 1
A55: 54 | B55: Anjali | C55: Vaibhav Kurwade | D55: Mandla | E55: Female | F55: 46191 | G55: Hindi Maths | H55: 4 | I55: 1 | J55: 0 | K55: 0 | L55: 1 | M55: 0 | N55: 0 | O55: 0 | P55: 5 | Q55: 1 | R55: 1 | S55: 1 | T55: 0 | U55: 0 | V55: 1 | W55: 0 | X55: 0 | Y55: 0 | Z55: 0 | AA55: 0 | AB55: 1 | AC55: Yes | AD55: 1 | AE55: 1 | AF55: 0 | AG55: 0 | AH55: Not sure | AK55: Yes | AL55: Yes | AM55: Yes | AN55: 1 hr | AO55: 0 | AP55: 1 | AQ55: 0 | AR55: 0 | AS55: 1 | AT55: 0 | AU55: 1 | AV55: 0 | AW55: 0 | AX55: 0 | AY55: 1 | AZ55: 0 | BA55: 0 | BB55: 0 | BC55: 0 | BD55: 0 | BE55: 0 | BF55: JSK Whatsapp | BG55: 1 | BH55: 0 | BI55: 0 | BJ55: 0 | BQ55: 2 | BR55: 0 | BS55: 0 | BT55: 0 | BU55: 0 | BV55: 0 | BW55: 1 | BX55: Yes | BY55: 0 | BZ55: 1 | CA55: 0 | CB55: 0 | CC55: 0 | CD55: Yes | CE55: 0 | CF55: 0 | CG55: 0 | CH55: 0 | CI55: 1 | CR55: 54 | CS55: =Qual_FreeText!Z55 -> DIKSHA | CT55: =Qual_FreeText!X55 -> Not able to recall | CU55: 1 | CV55: 0 | CW55: =Qual_FreeText!M55 -> Subject-specific Maths Training, Monthly Shaikshik Samvad, DIKSHA online courses, Panchayat cultural programmes, Health-related awareness programme | CY55: 1
A56: 55 | B56: Anjali | C56: Vaibhav Kurwade | D56: Mandla | E56: Female | F56: 46192 | G56: English Sanskrit Science | H56: 4 | I56: 0 | J56: 1 | K56: 0 | L56: 0 | M56: 1 | N56: 1 | O56: 0 | P56: 6 | Q56: 1 | R56: 1 | S56: 1 | T56: 1 | U56: 0 | V56: 1 | W56: 0 | X56: 0 | Y56: 0 | Z56: 0 | AA56: 0 | AB56: 1 | AC56: Yes | AD56: 0 | AE56: 1 | AF56: 0 | AG56: 0 | AH56: Not sure | AI56: Yes | AK56: Yes | AL56: Yes | AM56: Not sure | AN56: 2 hr | AO56: 0 | AP56: 1 | AQ56: 0 | AR56: 0 | AS56: 0 | AT56: 1 | AU56: 0 | AV56: 1 | AW56: 0 | AX56: 0 | AY56: 1 | AZ56: 0 | BA56: 1 | BB56: 1 | BC56: 0 | BD56: 0 | BE56: 1 | BF56: JSK Whatsapp | BG56: 1 | BH56: 0 | BI56: 0 | BJ56: 0 | BQ56: 5 | BR56: 0 | BS56: 0 | BT56: 0 | BU56: 0 | BV56: 0 | BW56: 1 | BX56: Yes | BY56: 0 | BZ56: 0 | CA56: 1 | CB56: 0 | CC56: 0 | CD56: Yes | CE56: 0 | CF56: 0 | CG56: 0 | CH56: 0 | CI56: 1 | CR56: 55 | CS56: =Qual_FreeText!Z56 -> Diksha and I got | CT56: =Qual_FreeText!X56 -> IGOT Karmayogi, Diksha | CU56: 1 | CV56: 1 | CW56: =Qual_FreeText!M56 -> Teacher took part in the month of June at block level subject training, after that she also lead to the training of Saksham Jivan koshal at block level as MT for three days, She also took part in all CLSS from July to Jan. | CY56: 1
A57: 56 | B57: Aishwarya Yadav | C57: Shalu Sharma | D57: Sehore | E57: Male | F57: 46189 | G57: Hindi English | H57: 13 | I57: 1 | J57: 1 | K57: 0 | L57: 0 | M57: 0 | N57: 0 | O57: 0 | P57: 3 | Q57: 0 | R57: 0 | S57: 1 | T57: 0 | U57: 0 | V57: 0 | W57: 0 | X57: 0 | Y57: 0 | Z57: 0 | AA57: 1 | AB57: 0 | AL57: Yes | AM57: Yes | AN57: 2 hr | AO57: 0 | AP57: 1 | AQ57: 0 | BK57: Yes | BL57: 1 | BM57: 0 | BN57: 0 | BO57: 0 | BP57: 0 | BQ57: 5 | BR57: 0 | BS57: 0 | BT57: 1 | BU57: 0 | BV57: 0 | BW57: 0 | BX57: Yes | BY57: 0 | BZ57: 0 | CA57: 1 | CB57: 0 | CC57: 0 | CD57: Yes | CE57: 0 | CF57: 0 | CG57: 0 | CH57: 0 | CI57: 1 | CR57: 56 | CS57: =Qual_FreeText!Z57 -> DIKSHA | CT57: =Qual_FreeText!X57 -> he could remember PLC course- संवाद से सीख | CU57: 0 | CV57: 0 | CW57: =Qual_FreeText!M57 -> General pedagogy training and CLSS | CY57: 1
A58: 57 | B58: Aishwarya Yadav | C58: Vaibhav Tambe | D58: Narmadapuram | E58: Male | F58: 46197 | G58: Maths | H58: 17 | I58: 0 | J58: 0 | K58: 0 | L58: 1 | M58: 0 | N58: 0 | O58: 0 | P58: 6 | Q58: 1 | R58: 1 | S58: 1 | T58: 1 | U58: 0 | V58: 1 | W58: 0 | X58: 0 | Y58: 0 | Z58: 0 | AA58: 0 | AB58: 0 | AC58: Yes | AD58: 1 | AE58: 1 | AF58: 0 | AG58: 0 | AH58: No | AI58: Yes | AK58: Yes | AL58: Yes | AM58: Yes | AN58: 1 hr | AO58: 0 | AP58: 1 | AQ58: 0 | AR58: 0 | AS58: 0 | AT58: 0 | AU58: 0 | AV58: 1 | AW58: 0 | AX58: 0 | AY58: 0 | AZ58: 0 | BA58: 1 | BB58: 0 | BC58: 0 | BD58: 0 | BE58: 0 | BF58: JSK Whatsapp School Whatsapp | BG58: 1 | BH58: 1 | BI58: 0 | BJ58: 0 | BQ58: 3 | BR58: 1 | BS58: 1 | BT58: 1 | BU58: 0 | BV58: 0 | BW58: 0 | BX58: Couldn't remember particular learning from CLSS | BY58: 1 | BZ58: 0 | CA58: 0 | CB58: 0 | CC58: 0 | CD58: Yes | CE58: 1 | CF58: 0 | CG58: 0 | CH58: 0 | CI58: 0 | CR58: 57 | CS58: =Qual_FreeText!Z58 -> DIKSHA | CT58: =Qual_FreeText!X58 -> DIKSHA | CU58: 1 | CV58: 0 | CW58: =Qual_FreeText!M58 -> CLSS, Digital Traning,SKG | CY58: 1
A59: 58 | B59: Dharmendra Mishra | C59: Deeksha Singh | D59: Sagar | E59: Male | F59: 46184 | G59: Social Science Other | H59: 28 | I59: 0 | J59: 0 | K59: 1 | L59: 0 | M59: 0 | N59: 0 | O59: 1 | P59: 5 | Q59: 1 | R59: 0 | S59: 0 | T59: 0 | U59: 0 | V59: 0 | W59: 0 | X59: 0 | Y59: 0 | Z59: 0 | AA59: 1 | AB59: 1 | AC59: Yes | AD59: 0 | AE59: 0 | AF59: 0 | AG59: 1 | AL59: Yes | AM59: No | AN59: 2 hr | AO59: 0 | AP59: 0 | AQ59: 1 | BK59: Yes | BL59: 1 | BM59: 0 | BN59: 1 | BO59: 1 | BP59: 0 | CJ59: Yes | CK59: 0 | CL59: 0 | CM59: 0 | CN59: 0 | CO59: 0 | CP59: 1 | CR59: 58 | CS59: =Qual_FreeText!Z59 -> May be courses on IGOT (karmayogi).. or diksha courses (teacher wasn't able to recall much) | CT59: =Qual_FreeText!X59 -> 0 | CU59: 1 | CV59: 1 | CW59: =Qual_FreeText!M59 -> He did FLN training from his school as no one was available at that timeline, he has taken sst in person training, and he has attended 1-2 clss as well. He share that he has done some online course.. But he couldn`t recall anything about that and he was not confident at all while telling that he did some courses. | CY59: 1
A60: 59 | B60: Bidisha Bose | C60: Swetha | D60: Vidisha | E60: Male | F60: 46191 | G60: Maths Science | H60: 20 | I60: 0 | J60: 0 | K60: 0 | L60: 1 | M60: 0 | N60: 1 | O60: 0 | P60: 4 | Q60: 1 | R60: 0 | S60: 1 | T60: 0 | U60: 0 | V60: 0 | W60: 0 | X60: 0 | Y60: 0 | Z60: 0 | AA60: 0 | AB60: 0 | AC60: Yes | AD60: 0 | AE60: 0 | AF60: 0 | AG60: 1 | AL60: Yes | AM60: Not sure | AN60: 1 hr | AO60: 0 | AP60: 1 | AQ60: 0 | BK60: Yes | BL60: 0 | BM60: 0 | BN60: 0 | BO60: 1 | BP60: 0 | BQ60: 2 | BR60: 0 | BS60: 0 | BT60: 0 | BU60: 0 | BV60: 0 | BW60: 1 | BX60: Yes | BY60: 0 | BZ60: 0 | CA60: 0 | CB60: 1 | CC60: 0 | CD60: Yes | CE60: 0 | CF60: 0 | CG60: 0 | CH60: 0 | CI60: 1 | CR60: 59 | CS60: =Qual_FreeText!Z60 -> Not sure | CT60: =Qual_FreeText!X60 -> Bal Suraksha course. Not sure if this was a course from last year but the teacher recalled completing this. | CU60: 0 | CV60: 0 | CW60: =Qual_FreeText!M60 -> The teacher could recall the subject specific training and attending a few CLSS. Could not recall exact months. | CY60: 1

Sheet Sheet1
A1: Annual Enagement | D1: Look for the other activities participated by teachers in the qualitative data set
A2: Subject Training | B2: 56
A3: Digital Training | B3: 40
A4: CLSS | B4: 53
A5: SKG | B5: 9
A6: Webex | B6: 1
A7: YTL | B7: 21
A8: APF Demo Sessions | B8: 0
A9: SIR | B9: 9
A10: Muskaan Dreams- DIET Training | B10: 2
A11: HM Training | B11: 7
A12: Election related Duties | B12: 17
A13: Any other | B13: 26

Sheet Qual_FreeText
A1: Teacher_ID | B1: Name of the interviewer | C1: Name of the note-taker | D1: District of respondent teacher | E1: Gender of respondent | F1: Date of the interview | G1: Subject taught by teacher | H1: Years of teaching experience | I1: Teachers Academic Responsibilities in a Day | J1: Teachers non-academic responsibilities in a Day | K1: Key response note on teacher's daily engagement | L1: Activities participated over 2025-26 academic year | M1: List all the participated activities with timeline such as CLSS Aug, Dec | N1: Key response notes on teacher's annual engagement | O1: Key feedback to improve training session design or in-person training in general | P1: Training resources received from in-person training | Q1: Name of the material__lesson plan or strategy teacher tried using in class- | R1: Key feedback__response on training material and resources | S1: Examples of classroom implementation of any topic__ plan or material | T1: Key response note on teachers' experience with follow-up activities. | U1: Reasons for finding particular follow-up activity useful or not useful | V1: Are there any challenges which might limit teachers participation in online discussion calls | W1: Post in person training or follow up calls, what makes classroom implementation difficult | X1: Name of the Govt__ Department promoted courses | Y1: Name of the non-govt promoted courses__ done on own will | Z1: Name of the online platforms used by the teacher | AA1: Reason for perceived effectiveness of online or digital medium learning | AB1: Key response note on teacher's perception on digital learning | AC1: Any other general insights or information shared by teachers with respect to their digital learning engagement and preference | AD1: Key response note on DIKSHA course engagement and features | AE1: Specific feedback to improve the course quality | AF1: Key response or observation note Overall | AG1: Reason for not doing DIKSHA course | AH1: Key response on reasons for not doing DIKSHA courses | AI1: CLSS topics recalled | AJ1: Key response or feedback or observation on CLSS topics choice | AK1: Two things liked about CLSS | AL1: What makes a successful and helpful peer learning community | AM1: Instance of CLSS learning solving classroom challenge | AN1: Two things to be changed or done differently in CLSS | AO1: Usefulness and relevance of facilitation guide and PPT | AP1: Processes to cascade CLSS learnings at school level | AQ1: Key response note on current practice to cascade CLSS learning | AR1: Teachers suggestion on process and arrangement to promote cascade learning or peer learning at school level | AS1: What challenges do they face in filling attendance and feedback form post the samwad | AT1: Key response or observation note on teachers experience with CLSS attendance and other logistics | AU1: Reasons of non-participation in CLSS | AV1: Key response on CLSS non participation reasons | AW1: As per the teacher, how can CLSS be made more helpful for teachers | AX1: Key observation on teacher's motivation, awareness, challenges of non-participation | AY1: General perception on Teacher mentoring and classroom observation process | AZ1: What should be kept in mind by mentor official mentors while doing CRO & Mentoring | BA1: Support expectation from mentor and process | BB1: Any other suggestions to improve professional development support for teachers | BC1: Insight on teacher's motivation Intrinsic VS extrinsic with respect to professional development | BD1: Any unexpected insight, not in questionnaire | BE1: Are there any gender specific insights, concerns or suggestion highlighted or observed
A2: 1 | B2: Rashmi Mishra | C2: Vaibhav Tambe | D2: Bhind | E2: Male | F2: 46183 | G2: Social Science | H2: 24 | I2: Teacher daily takes 3 period which is fix. since he is the only teacher in the school, he has to take rest of subjects as well like Hindi and Sanskrit. | J2: Student documentations, Attendence, school level data collection (MDM/SIR/Election duty )and update into various platforms and portal. | K2: Being a individual teacher at school. he has to perform various academics and non-academics duties in a day. which is sometime very challenging for him as teacher and as HM | M2: Subject Training, CLSS, Digital Training (PLC) | N2: Throughout annual engagement teacher was involved in various activities (SIR, BLO Duty, Election Duty, Census, other data related work at school level ) | O2: real classroom demo video help to connect more during training. | P2: Margdarshika - Teaching Plan/Modules | R2: Teacher mentioned he has attended training and received margdarsika and used it but not very often. but not able to share the learning experience | T2: Teacher was not able to share any experience related to follow-up activities | V2: Network challenge | W2: Low engagement of students (they not able to connect the topic) , Low attendance, Lack of resources | X2: Education Department (DIET) | Z2: DIKSHA | AA2: Because online learning is not so useful. offline training is more effective and useful. | AB2: According to teacher online platform is not so effective for learning because it has not one to one interaction as training has. | AD2: Teacher were not able to recall what feature he find engaging. after giving prompt question, he was able to share one feature. | AH2: According to teacher he mentioned doing online course is not effective. | AK2: Get platform to share an experience and get a chance to co- create solutions | AL2: No response | AM2: No response | AN2: As Facilitator must have good communication to convey thoughts and learning. Resources and Infrastructure | AO2: He mentioned if teacher gets Facilitation guide and PPT then it will be useful. | AP2: Other | AQ2: Being a single teacher there is no benefit to share the same. | AS2: Not perceived important | AT2: Venue should be accessible and also with at least basic facilities | AU2: Others | AY2: according to teacher classroom observation means any official comes to classroom for observation on student assessment, syllabus completion. | AZ2: After giving prompt question teacher explained mentoring means - CAC/ Officials should support in classroom process, take lectures when it required | BA2: Officials should identify actual support and requirements of teachers and plan accordingly | BF2: Good
A3: 2 | B3: Ritesh Pandey | C3: Vaibhav Kurwade | D3: Balaghat | E3: Male | F3: 46183 | G3: Social Science | H3: 37 | I3: Teacher conducts 4 classes in the day, beyond that he took some extra classes like moral education, give some time to improve student learning skills. During the break he also oversee over the children during they were playing the game. As he is senior teacher and have some health so he hardly participate in the other activities. | J3: Due to health concern and as senior teacher he dont do any non-academic activity on regular basis. But sometimes he needs to take part of social activity of that village, like if village is organizing in games, etc. | K3: Teachers conduct four classes a day, except that he supports the students with N-1, n-2, n-3. | M3: Teacher took part in three days block level training in the month of July, after that he participated in the almost all CLSS from Aug to Jan. | N3: Teacher mainly took part in the academic activities, CLSS, In person training, Digital training of DIKSHA & Igot -Karmayogi courses. | O3: Teacher finds in person training, but he highlighted that there is issue at the block level. At the block level official look at this activity as timepass, so People dont take training seriously. He highlighted the issue in the structure of training, he suggested there should be four group based on the geograpahies and context. So, training should cater differently for all these group based on their experiences. Select MTs from the more interior like tribal areas and select the MTs who are more interested in training and that subject. | P3: Margdarshika - Teaching Plan/Modules | R3: Teacher was not able to recall the any topic from the training material or classroom implementation, but he shared some feedback on training material should be grounded according to context, easy to follow. | T3: Teacher did not take in part of any follow up activities due to unavailability of network. | Z3: DIKSHA and Karmayogi | AA3: As teacher said it is the due to the human tendency as human can learn more effectively from audio and visual. | AB3: Techer have interest in the learning through mainly digital format, and most of the learning should be in the online format. Human have tendency to learn effectively from the audio and video. | AC3: Teacher keenly shown his interest in the digital learning he expressed he can do digital course 27 hrs in the week. | AD3: Teacher highlighted key features as te way of explanation, and CFUs and Post work. | AF3: Teacher has shown interest in the digital learning but at the same time he was not able to recall what he learned except diksha features. | AK3: Teacher not specifically highlighted any two things he liked, except that he said only this is good platform. The objective is also a good thing about the CLSS. | AL3: Sahajkarta should be active, it should be compulsory to all teachers, also need to ensure the teacher attendance. Half time should be pre decided agenda on any subject but half time should be there for discussion teacher local academic challenges. Those official from JSK who are interested should take part in CLSS, these official can be Sankul Pracharya, High school teacher. CLSS can be in the online format. | AM3: He is not able to recall. | AN3: Sahajkarta should be active, it should be compulsory to all teachers, also need to ensure the teacher attendance. Half time should be pre decided agenda on any subject but half time should be there for discussion teacher local academic challenges. Those official from JSK who are interested should take part in CLSS, these official can be Sankul Pracharya, High school teacher. | AP3: Other | AQ3: Not mentioned by teacher. | AS3: Unwilling teachers | AT3: Network issues can be one of the challenges in the filling the attendance form of clss. Teacher was clearly aaware of the CLSS Process, where he need to go to at the JSK and attend the samvad, the overall process of discussion and teacher experience sharing. He was also aware the feedback form filling process, timing and day of the CLSS. | AU3: Others | AW3: NA, Teacher took part in CLSS. | AY3: Teacher has affirmative response about the CRO and TM, He highlighted this need to be there in the place. At least once a month every teacher classroom needs to observe by any official or even villagers can come, and time to time mentoring from senior also needed. Teacher mainly see CRO as mainly seeing the class of the teacher how he is teaching and how children were responding. Teacher overally find this process as supportive mechanism for the teacher. | AZ3: The official who ever coming should come with the helping mindset, and coordination between both need to be there. Official should come as mentor (salahkar) rather than doing any disciplinary action, Also come with mindset of the exact reality and context of school. | BA3: Support in finding any mistake and guidance with respect to that. Teacher was not able to describe this in the greater details. | BB3: Digital program needed more, except that teacher mainly highlighed his challenges as administrative challenges like staff need to be increase, remove workload, Syllabus need to in the more easy format. | BC3: Teacher was intrinsically shown keen to learn, he is also working in the very interior of the balaghat. He engage students in multiple ways. So overally teacher was intrinscially motivated. | BF3: Average
A4: 3 | B4: Aishwarya Yadav | C4: Jay Prakash | D4: Rajgarh | E4: Male | F4: 46184 | G4: Social Science | H4: 40 | I4: मैं शाला आने के बाद बच्चों को प्रार्थना कराता हूँ , teaching करता हूँ , जरुरत पढ़ने पर दुसरे शिक्षक की कक्षा में पढ़ने भी जाता हूँ और साथ ही डाक का काम भी करता हूँ I | J4: पेड़ पोधो को पानी देना, साफ शाला और शौचालय की साफ सफाई देखना I | K4: शिक्षक ने इसका कोई क्लियर आंसर नहीं दिया, आप बोले की मैं अपने sub पढ़ाता हूँ, जरुरत पढ़ने पर दुसरे शिक्षक की प्रेड लेने भी जाता हूँ, डाक बनता हूँ. | L4: Subject Training Digital Training CLSS Webex YTL | M4: Digital course, CLSS, sub Training | N4: शिक्षक ने बताया वो सभी CLSS में भाग लिए हैं और कोर्स भी किये हैं | O4: लगातार होते रहना चाहिए ऐसी चर्चा और कम से कम 10 दिन का होना चाहिए. | P4: Not received | R4: केवल नोटबुक मिलता हैं और LED टीवी में दिखा कर डिस्कशन करते हैं. | T4: इसमें शिक्षक चालू करके मोबाइल रख देते हैं, इसे ध्यान से नहीं सुनते हैं. | U4: NOT USEFULL | V4: NO | W4: इसका ने इसका कोई क्लियर जवाब नहीं दिया | X4: आपने बताया की आपने मानसिक तनाव कैसे कम करें इस पर online कोर्स किया हैं. | Y4: शिक्षक इसका जवाब नहीं दे पाए | Z4: दीक्षा App | AA4: इसमें सिखने को मिलता है, क्या सिखने को मिलता हैं पूछने पर आपने स्पष्ट जवाब नहीं दिए. | AB4: Digital course बंद करके training शुरू करना चाहिए. | AC4: शिक्षक ने पहले बताया की वह घर में भी course का लेते हैं, और बाद में बोले की घर में दुसरे जिम्मदारी होने के कारण नहीं कर पाते हैं, स्कूल और घर दोनों में करते हैं. स्कूल में करने से बच्चों की पढाई प्रभावित होती हैं. | AD4: Most engaging features याद नहीं आ रहा हैं, ये कोर्स लम्बा होने कारण बोर लगता हैं. | AE4: Digital course बंद करके training शुरू करना चाहिए. | AF4: WhatsApp's ज्यदा अच्छा हैं इससे जानकारी जल्दी मिल जाती हैं. | AK4: U सर्कल में बैठना, सभी के विचारो को शामिल करना अच्छा लगा. | AL4: बैठक के दौरान एक अच्छी बातचीत सभी को मौका | AM4: हाँ | AN4: दो चीज़ होनी चाहिए अच्छी बातचीत और सभी शिक्षकों को बोलने का मौका | AO4: शिक्षक को ये याद नहीं था | AP4: Other | AQ4: शिक्षक ने इसका क्लियर जवाब नहीं दिया | AR4: इस पर कुछ नहीं बताये | AS4: others | AT4: शिक्षक ने बताया की इसमें उनको कुछ challenges नहीं आता हैं. | AY4: इसमें कुछ तैयारी नहीं करनी पढ़ती हैं, अपना अनुभव काम आता हैं. | AZ4: सभी अधिकारी अलग अलग होते हैं, अधिकारीयों को शिक्षकों से सम्मान पूर्वक बात करना चाहिए, अच्छे शब्दों का प्रयोग करना चाहिए, और अच्छे system से आगे आना चाहिए. | BA4: Resource provide करना चाहिए | BB4: शिक्षकों के लिय स्टेट लेवल ट्रेंनिंग होना चाहिए, Digital कोर्स को बंद करना चाहिए ये शिक्षकों को कम फायदा पहुचता हैं. | BD4: Nothing | BE4: Nothing | BF4: Average
A5: 4 | B5: Rajesh Solanki | C5: Shalu Sharma | D5: Betul | E5: Female | F5: 46184 | G5: Hindi Social Science | H5: 31 | I5: Teaching class 6,7 and 8 Hindi and social science. Conducting baaal sabhas on Saturday | J5: Apaar id, birth certificate of children, samagra id, mid day meal updating any data asked from JSK | K5: The teacher starts her day by conducting assembly and then she is engaged in her subject classes throughout the day | L5: Subject Training Digital Training CLSS SKG YTL | M5: She could not recall | N5: She did not remember any activity apart from leadership training without probing. | O5: She suggested infrastructural changes like better seating arrangements and washroom etc. | P5: ToT | R5: She could not give any concrete examples of using the resources | T5: She does not like anything done online. Kyoki ve thik se phone chlana nahi janti hai. Mobile me thik se dikhayi nahi deta hai. F2F jyada behtr hai, school ke alawa milne ka mauka mil jata hai. | U5: She said, she does not get time during the school hours to attend YTL and also the school is in low network area | V5: Network issue, time issue, mobile data | W5: Did not use. Also from her explanation we got to know that even when she joined the call, she never paid attention to it. | X5: Suchna ka adhikar | Z5: Mygov and DIKSHA | AA5: According to her small videos and written material is useful | AB5: She likes taking digital courses because they are self-paced | AC5: She thought she should also show these courses to children as well. | AD5: She likes the small videos and the questions, she likes the multiple choice question format. She also like reading material | AE5: She thinks that the videos can be a smaller and the written material shorter | AF5: There are 2 major groups one sankul group and another group made during in person training for social science teachers run by the master trainer | AK5: सबका अनुभव सुन ने को मिलता है, अपने को बोलने का मौका मिलता है और झिझक कम होती है | AL5: The facilitator and participants should be active | AN5: Suggestion only on infrastructure | AP5: No learnings shared or no set process adopted | AQ5: She only has information on the clss that she herself attended | AR5: She could not recall any of the clss apart from u shape seating arrangement | AS5: Session end rush for teachers to leave the venue | AT5: login issue on RSKMP Portal | AY5: अच्छा लगता है कोई आता है तो | AZ5: They should give feedback on teaching and what can be done better in class | BA5: Support in difficult topics | BD5: She shared that the new textbook is good, but it should have more questions in between the chapter and at the end. She shared that this new book pushes teacher to prepare questions herself and prepare for the class. | BE5: She shared absence of functional female toilets at training centres is a problem | BF5: Average
A6: 5 | B6: Pushpendra Singh | C6: Other | D6: Satna | E6: Male | F6: 46183 | G6: Social Science | H6: 16 | I6: Teaching social science in class 6 to 8 daily 6 classes of 40 to 45 minutes. Maintaining the academic register of the school. | J6: Taking care of the preparation and distribution of mid-day meal. Making Daak for the school. In charge of daily assembly as well. MUN Work. | K6: Teaching and Preparation of mid-day meal. | M6: Teacher has participated in 5 CLSS throughout the year at JSK and one Block level subject training on new NCERT book of Class-6. | N6: The teacher was highly engaged in TPD activities and also engaged in learning and completing the DIKSHA courses. | O6: The teacher suggested; the training should be given more than once, it should be more introductory, and the training of Sanskrit and Hindi grammar should be added as well. | P6: PPT Margdarshika - Teaching Plan/Modules | Q6: The teacher has applied the assessment method included in lesson plan, and he implement this on availability of time sometimes daily, weekly and monthly. The teacher has been using the strategy of asking questions before starting any topic to include the pre-knowledge of students. | R6: The training material was helpful as he said, but he also said that he uses it sometimes and most of the times the material and module stay in a corner, and he look at material when he requires. | T6: The teacher was aware about the follow-up activities such as quiz and other interventions, but he was not able to join mostly due to the internet issues and other non-academic duties. | U6: The teacher finds the quiz helpful, and he said that it recalls his memory and help to prepare questions for the classroom teaching. | V6: Non-academic duties and internet connectivity are the primary challenge. | W6: Post in person training the material was too much for him and he said it looks very easy in the training but student absenteeism and lack of time in classroom period stop him to implement learned things in the classroom. He said in the first period 10-15 minutes goes in attendance and settling in for the day therefore he was not able to implement things in first period specifically. | X6: DIKSHA | Z6: DIKSHA APP | AA6: The teacher said DIKSHA courses are helping him to understand the new social science book better and he looks at videos and stories specifically to implement and show in the classroom. | AB6: Teacher was familiar with online courses, and he has been a MT in the past therefore he was aware about the DIKSHA app and courses; he said he uses videos and it makes him understand better about each topic. | AC6: The teacher said he sometimes complete 2 courses in a day on DIKSHA app and sometimes one in a day it depends on the time availability in his schedule but mostly he completes courses in the school time or in the weekends. | AG6: Time issue Other engagement | AH6: The teacher was aware about the DIKSHA courses, but time management and non-academic duties are main challenges of not doing it sometimes. | AK6: The conversation among fellow teachers and sharing of their thoughts in the CLSS. | AL6: He said sharing and learning from each other is very helpful. | AM6: The teacher said classroom management and giving homework to students has helped him a lot. After the CLSS on Homework he was able to give better homework to students. | AN6: One thing was time he said the time should be less than 2.5 hours. Another suggestion was on interest he said sometimes the CLSS is boring and that can be changed. | AO6: Activities and Facilitation was helpful he said but he was not able to give any example at that time in the conversation he said he has but nothing is coming in the mind at that time. | AP6: Participating teacher share their notes Participating teacher verbally cascade the learning (Peer learning discussions | AQ6: The teacher said, In the staff meetings all teachers discuss and the one who were not able to attend the CLSS understand and get the learning through the discussion. | AR6: The teachers suggested and emphasized on the discussion about CLSS in the school time. | AS6: Awareness Issue others | AT6: The teacher was positive and aware about the marking of attendance. | AU6: Others | AV6: The teacher has attended all the CLSS sessions. But he said sometimes due to the non-academic work it has been difficult to join. | AW6: As per the teacher the CLSS can be made more helpful if it can be more engaging because sometimes it is boring for him as well. Not every section but some section he said. | AY6: On the General perception on teacher mentoring and classroom observation process he said if we are not aware or don't know anything about the observer then it gets difficult to perform better due to fear about the consequences. | AZ6: The teacher said while the visit the officials should make them comfortable so that the teacher can feel comfortable and perform duties better. | BA6: Conversations and need of more learning opportunities and resources as well. | BB6: No | BD6: No | BE6: No | BF6: Vgood
A7: 6 | B7: Dharmendra Mishra | C7: Bhanu Priya | D7: Sagar | E7: Male | F7: 46183 | G7: Maths Science | H7: 15 | I7: Teach grade 6-8, science and ,Math | J7: 1. Online registration 2. Portal Update 3. Dress and book distribution 4. Scholarship Distribution | K7: 1. Take six period a day 2. No free time 3. classroom teaching takes a back place in case of official work 4. More time consumed in the portal update 5. Non academic work along with classroom teaching becomes burdening sometimes | L7: Subject Training Digital Training CLSS SKG SIR Election related Duties Any other | M7: 1. Attended 4 CLSS - August, sept, oct, Jan 2. SIR- Nov- Dec 3. Subject Specific Training- June -July | N7: 1. Attended 4 CLSS - August, sept, oct, Jan 2. SIR- Nov- Dec 3. Subject Specific Training- June -July | O7: The Content should be focused more on the application of the topics from the subject and less theories, there should be more time allotted for the training | P7: Not received | V7: 1. Time 2. Connectivity 3. Other engagements | X7: PLC, AI | Z7: DIKSHA, Karmyogi | AA7: 1. The teacher can do it on their own pace 2. These trainings can be done after the class which do not disruput the classroom teaching | AB7: 1. Courses were very helpful as one can do them on their own pace without disturbance | AD7: Test in between the course are interesting as they do not allow the participant to go forward which is why they have to go back again and again results in recalling and remembering the concepts | AF7: The teacher get most of the information from the JSK WhatsApp group, but the teacher is not able to enroll in most of the activities as there are only 2 teachers in the school and the other is the principle who is engaged in other tasak most of the time. | AK7: 1. The topics are decided prior and helps the teacher to prepare beforehand 2. The teacher come to a common solution to any problem that they are facing, through the discussion in the CLSS | AL7: Group Discussion | AN7: 1. Increase teacher attendance and regularity 2. The discussion should not deviate from the main topic | AP7: Other | AQ7: There is no sharing of this on any platform. | AR7: 1. The schools should be shut down on the last Saturdays so that it can maintain the regularity of the teachers 2. the discussion should not be deviated from the main topic 3. 3. the teacher should share their learning at the school after coming back | AS7: others | AT7: The teacher was the facilitator 4 times, all those times he ensured that everybody has marked the attendance but he himself has faced issue in filling the attendance as the teacher got transferred from other school and there was a location erroe | AY7: Did not know about teacher mentoring but CACs visit the school for the school observation | AZ7: 1. The Officials should come as a supporter and not as officers 2. Teachers' problem should be heard 3. Officials should not scold the teachers | BA7: 1. The officials should see the classroom teaching and give feedback on them | BB7: 1. The training should have less technicality as majority of the teachers are older and they are not very comfortable with them | BF7: Vgood
A8: 7 | B8: Shalu Sharma | C8: Rajesh Solanki | D8: Betul | E8: Male | F8: 46185 | G8: Maths Science | H8: 34 | I8: Assembly and subject classes | J8: MDM, attendance, Apaar Id, birth certificate, caste certificate, panchayat work, janganna, shaala ki safai urgent daak, vidhaan sabha sawaal, exam duty | K8: according to him teachers have a lot of responsibilities towards the school apart from teaching. meeting parents amd attending panchayat meetings for SMC is also part of it. | L8: Subject Training CLSS YTL SIR | M8: He participated in both Math and Science in person training. He mentioned that he attends YTL sometimes but he could not recall any topic discussed but he had idea about the paathyojana shared for science. he also shared an example from science training (chumbak). | N8: he said that he makes children watch youtube live along with him (for context YTL is specific for teacher only), which indicates that he paid very less attention to the content shared in the YTLs as he cannot remember what is meant for what. | P8: PPT Margdarshika - Teaching Plan/Modules | Q8: He could remember magnet related just the topic or chapter and related resources from the training but could not specify the activities or module prescribed activities which he might have implemented in classroom. He also has created a lab set-up and broadly he was mentioning activities he is trying to do with children there( not necessarily related to training) | R8: He showed a picture of children using magnet in the classroom, which he got to know about in the training. he also shared about the shikshan chakr but this was shared in the start of the conversation which felt like as if he had prepared for the questions being asked. | T8: he said that he attended YTL but could not recall anything. He shared that he had seen science module on the CAC group and also quoted some examples from measurement chapter. | U8: According to him YTLs allow him to be in his school and attend learning sessions, he need not go anywhere else. | V8: internet connectivity | W8: he mentioned limited time as one of the reasons. Also he is mainly mathematics teacher but he could only recall resources or training of Science. Also we found out that he only gets information related to science becuase he is only added to science subject whatsapp group. The master trainer of Science is very active, he shares all information with teachers and also does his own seekh ki yatra | X8: Some course on mulyanakan, couldn't remember the name of the course done on DIKSHA | Z8: MyGov and DIKSHA courses | AA8: short videos | AB8: He was positive about digital content for follow-up learning but also expressed concerns about excessive screen time. | AC8: he thinks login process should be smooth and videos are interesting but he cannot read very small text. also he did not actually mention any course also any kind of time that he invests in doing those courses in the week. | AE8: Improving login process, text size should be more legible. | AG8: Time issue | AH8: He did not say he did not do any course but could not recall anything | AK8: he said that teachers share their experience and the venue of CLss is near the school unlike training | AL8: he just shared the format of the clss. like teachers from cluster come togeather and discuss on given topic and share each other idea also he mentioned design principles like 30-70 ratio and focus on academic discussion he also mentioned about the post work (there is postwork which teacher needs to complete after going to their school and bring it to next CLSS) | AO8: did not share anything | AP8: Participating teacher verbally cascade the learning (Peer learning discussions | AQ8: he shared that always two people go from school and if he does not go other teachers verbally tells hi, what happened | AS8: Session end rush for teachers to leave the venue | AT8: He could not recall any topic of CLSS and on probing he only mentioned one topic from last year- importance of questioning. Also he mentioned that the most important group for infomation is JSK group and master trainer group. | AY8: Mostly around infrastructure- Mentioned thaat officials in past have come to school looking for school infrastructure and kept - building, painting, garden, cleanliness. | AZ8: he had nothing concrete to share | BA8: he needs infrastrutural support only. Like school me extra room bne, colour ho jaye, plaster gir raha vo thik ho jaye, boudary wall, ek teacher ho hr class me. | BB8: he shared nothing concrete, but he feels that continuous professional development is important | BD8: If someone is not recongnising main speaker of YTL then they have not attended it. In both the schools of Betul associated master trainers are very active they are sharing most of the information. teachers are also receiving follow up resources. | BE8: The JSk tried to do CLSS in different schools but it was not successful because there was no public transport, the school was in interior amd female teachers faced a lot of problem. | BF8: Average
A9: 8 | B9: Rashmi Mishra | C9: Vaibhav Tambe | D9: Morena | E9: Female | F9: 46185 | G9: Maths | H9: 17 | I9: Student Attendence, 6 period in a day and planning for the same | J9: Community Visit, student follo-up though WhatsApp group, student profile related work, support HM in other data related work | K9: Teacher mention that she take 6 period everyday also get involved in student profile and student follow-up. sometimes she does help HM to other data releted work | L9: Subject Training Digital Training CLSS | M9: Subject training, CLSS, Digital Training | N9: Teacher has done above given activities. she mentions that this activity supports her in a classroom process. | O9: Teacher clearly mention that giving training is a one part. but after training what? there is no follow-up mechanism which support because many things left after traning. | P9: Margdarshika - Teaching Plan/Modules | Q9: Teacher mention that she has use cold calling and group work during teaching. | R9: teacher mention that margdarshika was useful. it has activity base which help my student to engage and understand. | U9: Due to various engagement in a classroom and low network at place hence teacher unable to join any follow-up activates. | V9: Low network connection. and engagement in the classroom | W9: there are diverse grade level students so it's difficult to cater them during teaching. | X9: Didn't remember course name. | Z9: DIKSHA | AB9: Every Learning should be in person there should be no digital learning because in-person training get more opportunity to interact asking doubt etc | AC9: Teacher has clearly mention that there is lot more work is there at home. as women i have many responbiities and school work is also there so in between not get any time to complete the course | AE9: Teacher has mention she has done may not able to recall anything from course even the course name | AF9: teacher earlier has done course but when we asked about anything that they remember she was not able to reacall. also she showed her strong intrest in in person not in digital lernning | AK9: It's a space to connect with other teacher who teach same subject also helps to solve problems through discussion also new thoughts emerge | AL9: Helping each other, co-create solution. | AM9: teacher mention she used 30:70 ratio in her classroom stdent get active those who sit behind they are also start talking. There was no concrete explanation on how they try to do this classroom, broadly mentioned that she ask student to speak 70 % of time and she will for 30% (for context- this is one of the design principle laid in CLSS which teacher here mentioning implementing in her class) | AN9: Discussion should be around the topic. not anything beyond that because it difficult to gain understanding on that. it should be monitoring mechanisim | AO9: Teacher said she did not get guide | AP9: Other | AQ9: NA (since school has sufficient teacher so all teacher was able to attend CLSS) | AS9: Awareness Issue others | AT9: sometime there is network issue to mark attendance | AY9: teacher mentions observation means other officials observing for student's syllabus completion and understanding students progress | AZ9: Monitering means to support and guide how to particular topic transact into classroom. support in specific subject | BA9: any official come as mentor and a official mind set. because it create fear in mind that things need to complete before CAC visit. as Mentor they can supoort and help | BB9: teacher clearly mention that there should be follow-up mechanism to support teacher on ground. because after training there any many questions but we are unable to get responses | BF9: Average
A10: 9 | B10: Ritesh Pandey | C10: Vaibhav Kurwade | D10: Balaghat | E10: Female | F10: 46184 | G10: Hindi Social Science Sanskrit | H10: 18 | I10: Teacher engages in the different set of activities, firstly she will take around 4 periods in grade 6 to 8. Rather than that she also sometimes takes part in the organizing Painting and sports related activities for students. | J10: Sometimes, she also needs to complete some non-academic tasks like providing information mainly asked for by the CACs and BRCCs. The information related to the bicycles, textbook information. | K10: In addition to classroom teaching, she supports co-curricular activities such as painting and sports events for students. Teachers also undertake non-academic responsibilities, including providing school-related information requested by CACs and BRCCs. Common administrative tasks include sharing data related to textbooks, bicycles, and other school records | L10: Subject Training, CLSS, DIKSHA & I got Trainings | M10: Teacher took part in the subject training in the month of july, after that teacher attended 2 CLSS, and she attended digital training on I got karmayogi and on diksha. | N10: Teacher took part in in person training, 2 CLSS and did some digital course on diksha and i got karmyogi but she hardly able to recall the timeline and name of the course. Also teacher mentioned she got a link of Youtube live but she was not able to take part in it. | O10: Teacher expressed that at block level everything got delivered in the very short due to time constraints- covered time is not sufficient for particular topics, so time need to be more to go in detail. Content needs to be interesting, where opportunities for evryone to take part should be there, it is not interesting enough. Also as of now many teacher dont take part in the group task- no separate mechanism to make passive participants participate and manage dominate participants. | P10: Not received | R10: she did not receive any material during training not in the hard copy as well as soft copy. | S10: No examples remembered or shared. | T10: Teacher did not take part in any follow up activities. | V10: Teacher received link of follow up activities but at that time teacher she was taking period in her class, so not joined due to that. | X10: AI course, Inclusive education (Samavesi shiksha on DIKSHA) | Z10: Diksha and I-got | AA10: Teacher perceives it as effective way of learning as something new she can learn. | AB10: Teacher finds digital course effective, but teacher finds difficult to continue or time to complete in one go, if she can't complete in the one go, she finds her learning as missing. Teacher also struggle to find time in the school as there she need to take class and spend time with the children. Observation- Teacher response on doing inclusive education course on DIKSHA is contradictory as there is no such course available or promoted. | AC10: Being a female teacher, she hardly can allocate the time for her learning at her home, she needs to complete the household chores at her home. | AD10: Teachers finds the content of course engaging as video, where everything was explained. She also feels that quiz is very important feature as after attending correct question she feels something accomplished or achieve. But teacher was hardly able to recall the course name or content matter. | AE10: Teacher feels the learning from courses taking classroom difficultés, and that need to be aligned with ground reality. There is need more demonstration and activity like content. Sometime language which usually academic language create difficulty in the learning for understanding meaning of particualr word. | AF10: Teacher find the digital learning useful but she hardly finds the time. She was not able to recall any course name. | AK10: Some activities like cold calling, group work. Discussion and conversations. | AL10: If got opportunity to work in group and something amazing comes out. Topic needs to be interesting. | AM10: not mentioned any thing. | AN10: CLSS need to organise before the academic start or at the end of the session. | AP10: Participating teacher verbally cascade the learning (Peer learning discussions | AQ10: Teacher share something from CLSS verbally mainly with the fellow teachers. | AR10: Not suggested any thing | AS10: others | AT10: Teacher took part in 2 clss, she finds it useful but her main concern is finding out time from her classroom teaching and taking part in the clss. | AU10: Others | AV10: Teacher took part in the 2 CLSS. | AY10: Teacher understood CRO as something that is with classroom observation (where officials are observing her teaching practice and student performance), In such case teacher tend to be worried about the children responses (when officials ask them). Teachers are not always confidence on students performance or learning level to answer officials question and teacher has sense of unwanted action, punitive in that case which creates fear and hesitation. | AZ10: Mentor should motivate the teachers, guide them how to do certain things in the classroom and outside classroom. | BA10: Mentor keep motivating the teacher along with the suggestion for improvement. | BB10: Keep teacher from other work which are non-academic in nature. | BF10: Good
A11: 10 | B11: Aishwarya Yadav | C11: Jay Prakash | D11: Rajgarh | E11: Male | F11: 46185 | G11: Maths Science | H11: 27 | I11: शाला आने के बाद शिक्षक अपना Attendance लगा के बच्चों के साथ कक्षा में काम करते हैं, और उनके साथ अपने सब्जेक्ट के period लेते हैं I शनिवार के दिन बच्चो के साथ अलग अलग गतिविधि करते हैं साथ ही शाला में जितने भी डाक के काम होते हैं या ऑनलाइन काम होते हैं करते हैI | J11: शिक्षक अपने सब्जेक्ट के period बच्चों के साथ लेते हैं, जिसमें गणित और विज्ञान शामिल हैं. बच्चों के साथ अन्य शैक्षिकण गतिविधि करते हैं जिसमें बालसभा, शनिवारी की गतिविधि आदि शामिल होती हैंI | K11: 1.अपने विषयगत गतिविधि 2.बच्चों के साथ अन्य शाला गतिविधि 3.शनिवार की गतिविधि 4.डाक और ऑनलाइन से जुड़े कार्य | L11: Subject Training Digital Training CLSS YTL HM Training | M11: SUB TRAININING, DIGITAL COURCE, CLSS, YTL, HM TRAINING | N11: सारे गतिविधि में आपको बहुत सारा सिखने को मिला, आपने अपने द्वारा सीखे गए गतिविधि को कक्षा में भी किया। ट्रैंनिंग में मिले बुकलेट के लेशन प्लान का भी आपने उपयोग किया जिसका बच्चों के लर्निंग पर अच्छा प्रभाव देखने को मिला I | O11: प्रशिक्षण में हार्ड कॉपी बुकलेट मिलना चाहिए, क्योंकि ये बहुत मददगार होता हैं, इसे जब चाहे पढ़ सकते हैं। और उपयोग में ला सकते हैं. | P11: Margdarshika - Teaching Plan/Modules | Q11: शिक्षक मार्गदर्शिका जिसमें दिए गए लेसन प्लान को आपने कक्षा में उपयोग में लाया I आपने इसमें दिए विभिन्न पाठयोजना को अपने कक्षा में किया जैसे धातु अधातु वाला पाठ योजना। | R11: प्रशिक्षण में हार्ड कॉपी बुकलेट मिलना चाहिए, क्योंकि ये बहुत मददगार होता हैं. कई बार सॉफ्टकॉपी देते हैं जिसे पढ़ना आसान नहीं होता हैं. | T11: Teacher was not able to recall anything related to followup activities. | U11: Useful, The teacher said that YouTube videos are linked to their classroom processes, which is why they are useful to us. | V11: इंटरनेट की समस्या, सही समय पर कार्यक्रम का चालू न होना, कार्यक्रम के बारें में 1 -2 दिन पहले पता चलना, एक साथ सभी विषय का programme चलाना | W11: शिक्षक को इसका जवाब नहीं दिए. | X11: कोर्स का नाम याद नहीं आ रहा हैं. | Z11: कर्मयोगी App के माध्यम से किये हैं. And DIKSHA | AA11: यह हमारे लिय उपयोगी हैं और ये हमारे फील्ड से जुड़ा भी हुआ है. इसमें पढ़ने का नया तरीका मिलता हैं, जो बच्चों के लिय बहुत लाभ होता हैं. | AB11: इसमें सीखे गए गतिविधि को हम कक्षा में उपयोग में लाते हैं जिसका बच्चों को बहुत अच्चा लाभ होता हैं, उनकी विषय आधारित समझ विकसित होती हैं. | AC11: इसमें Log-in कि समस्या आती हैं जिसके कारण जुड़ने में कठिनाई होती हैं, साथ ही कम समय में ज्यदा कोर्स होते हैं. | AD11: शिक्षक इसके बारे में कोई विशेष जवाब नहीं दिए, उनको सिर्फ दीक्षा app का नाम याद था. | AE11: शिक्षक ने इसका जवाब नहीं दिया | AF11: WhatsApp के माध्यम से जानकारी जल्द ही हमारे तक पहुँच जाती हैं. शिक्षक जल्दी जल्दी कोर्स करना चाहते हैं जिसके वे समझ कम पाते हैं सर्टिफिकेट इकठ्ठा करने में लगे रहते हैं. | AK11: एक दुसरे से सिखाना, पूर्व तैयारी करके आना (Pre-test & Post test) Observation- However, there is no concept of prework in CLSS, teacher might be confusing it with in-person training. | AL11: एक अच्छी चर्चा, सभी की सहभागिता | AM11: yes, इससे बच्चों को सिखाने की नई नई विधि का पता चलता है. | AN11: Planning and preparation | AO11: Teacher didn't offer any specific answers to this | AP11: Processes shared in the school staff meeting and WhatsApp group | AQ11: आपने इसका क्लियर आंसर नहीं दिया | AR11: प्रशिक्षण में हार्ड कॉपी बुकलेट मिलना चाहिए (Another point showing that teacher might be confusing CLSS with in-person training) | AS11: others | AT11: सभी शिक्षक टेक्नोलोजी फ्रेंडली नहीं होते हैं जिसके कारन उन्हें समस्या आती हैं.We are able to learn different teaching methods which we implementation in the classroom जिससे स्कूलो में बच्चों की उपस्थिति में सुधर देखने को मिला हैं बच्च्चों को सहभागिता में वृध्दि हुई हैं, बच्चे नियमित आने लगे हैं. Observation- Teacher couldn't share any specific learnt methods or implementation case to solidify the claim that it improves student enagage ment or actual implementation of CLSS learning. | AY11: Nothing | AZ11: अधिकारी हमें proper फीडबैक दे हमारा मार्गदर्शन करें। कक्षा प्रक्रिया को बेहतर करने का सुझाव दे. | BA11: उनका सहयोगी होना, सुझाव देना, बच्चों से चर्चा करना, विषय आधारित सहयोग, अकादमिक सुझाव | BB11: Teaching शिक्षकों को दूसरे कामो में न लगाना, प्रशिक्षण २ दिन का होना, ऐसा प्लेटफार्म होना जहाँ ऑनलाइन कोर्स और चर्चा को कभी भी देख पाए. टीचर्स से गर्मी की छुट्टी में काम न कराये। | BC11: Active in term of participation, doing activities with students on bagless Saturday, baal cabinet- extracurricular activities of teachers. Generally motivated teacher. | BD11: आज की चर्चा के लिए शिक्षक ने अपनी पूरी तैएरी के साथ आये थे, और अपने साथ मटेरियल भी लेकर आये थे like- In-person training booklet (margdarshika). Teacher mentioned that he spoke to otther MTs and teachers regarding this interview and seemingly prepared for the answers. | BE11: शिक्षक ने बताया की शाला में लड़कियों की संख्या ज्यादा है, क्योंकि पालक लड़को Private स्कूलों में डालती हैं, और लड़कियों को सरकारी स्कूलों में | BF11: Average
A12: 11 | B12: Ritesh Pandey | C12: Vaibhav Kurwade | D12: Balaghat | E12: Female | F12: 46185 | G12: Social Science | H12: 16 | I12: Teacher starts her day with morning prayers and then take 6 periods. After 4 Pm she conducts the games for children. | J12: If any information related to information comes out, she needs to complete that like Cycle distribution, Uniform, CSWN related work, scholarship and sometime work related to ULLAS | K12: Teacher engagement are across non academic and academic work, she need to take 6 classes each day, and along with that she also needs to complete some work which is nonacademic in nature. Mainly related to information filling or work related to the adult literacy program ULLAS. | M12: Teacher took part in the two days subject training at block level in the month of July, She attended all CLSS from Aug to Jan, and completed the digital course on I got platform. Also did one course on diksha but not able to recall the name of the course. | N12: Teacher took part in subject training, CLSS, completed digital course also sometimes joined the YouTube live. She also took part in the SKY Quiz. Along with that this year teacher took part in the census exercise. | O12: There was no feedback given from the teacher, although teacher mentioned that the MTs who gave training was good, and the activities were also good. | P12: Not received | R12: Not received. | T12: Teacher mentioned both was useful but not able describe why both was useful. | U12: reason not provided. | V12: Teacher mentioned that it was really difficult to take part in the follow up activities as there was running the classes at the same time, second sometimes teacher also forgot the timing and date of youtube live. | W12: Some strategies teacher applied in her classroom like cold calling, TPS but sometimes students dont respond in the classroom that makes students participation difficult. | X12: not able to recall the name of the courses | Z12: I got Karmayogi, Diksha | AA12: video makes it as effective way of learning tool. | AB12: Teacher finds the digital learning as useful tool for its video feature. | AD12: Teacher did one course in the last year but not able to recall the name of the course, also she mentioned she previosly more than 20 plus course on diksha during covid. | AE12: The video needs to be there. Also, PDF but she affirmatively said yes after interviewer specifically asked her. | AF12: Teacher completed the course on two platform mainly I-got Karma yogi on AI, and diksha but she is not able to recall the name of the course. | AK12: In the CLSS teacher get opportunities discuss with each other’s, get opportunity to share the thoughts, Also get problem solved. | AL12: Effective PLC can be when everyone get opportunities to speak, if the ration of 30:70 maintained in between Sahajkarta and participants. | AM12: Teacher did not share any classroom implementation case learnt from the CLSS | AN12: Not suggested any changes. | AP12: Participating teacher verbally cascade the learning (Peer learning discussions | AQ12: Teacher verbally shares the discussion points with the teachers. | AR12: not given any suggestion | AS12: others | AT12: Network issues can be one of the challenges in the filling the attendance form of clss. | AU12: Others | AV12: Teacher took part in the CLSS. | AY12: Classroom observation for teacher is mainly monitoring and testing how much children are learning in the classroom. | AZ12: Mentor should provide the guidance to the teacher. Teacher sometimes feels little uncomfortable with CRO as they are mainly worried about the students responses in the classroom. | BA12: mentor should provide feedback and suggestion and mainly the guudance. | BB12: Not provided | BF12: Good
A13: 12 | B13: Sonali Patidar | C13: Dilip Kag | D13: Khargone | E13: Female | F13: 46184 | G13: Social Science Maths | H13: 3 | I13: प्रार्थना करवाना। कक्षा 6, 7 एवं 8 में गणित पढ़ाना और जब जरुरत होती है तब आवश्यकता अनुसार सामाजिक विज्ञान पढ़ाना, TLM एवं गतिविधि आधारित शिक्षण करना l शिक्षण के दौरान विषय वस्तु अनुसार विद्यार्थियों को मैदान और अन्य जगह पर विजिट कराना। पुनरावलोकन एवं प्रश्नोत्तर गतिविधियाँ कराना। | J13: मैंडम ने बताया कि शिक्षण कार्य के अलावा उन्हें ऑनलाइन रिपोर्टिंग, विद्यार्थियों की जानकारी एकत्रित करना जैसे गैर अकादमिक कार्य भी करते हैं। | K13: मैडम ने बताया कि उनका अधिकांश समय शिक्षण कार्य में व्यतीत होता है। वे कक्षा में केवल पुस्तक आधारित शिक्षण नहीं करतीं बल्कि TLM आधरित शिक्षण और गतिविधियों के माध्यम से बच्चों को समझाने का प्रयास करती हैं। आवश्यकता पड़ने पर वे बच्चों को मैदान में ले जाकर गतिविधियाँ भी करवाती हैं। | L13: Subject Training Digital Training CLSS YTL Any other | M13: विषय आधारित प्रशिक्षण, अगस्त, सितम्बर और दिसम्बर में शैक्षिक संवाद में सहभागिता, जीवन कौशल प्रशिक्षण, TLM मेला, जनगणना में ड्यूटी आदि SIR ड्यूटी – लगभग 1 से 1.5 माह तक कार्य किया l | N13: मैडम ने बताया कि उन्होंने वर्ष भर में विभिन्न प्रशिक्षणों एवं शैक्षणिक गतिविधियों में भाग लिया। वे नियमित रूप से शैक्षिक संवाद में शामिल होती रही हैं। TLM मेले में भी उन्होंने सक्रिय सहभागिता की तथा विद्यार्थियों को जिला स्तर तक ले गईं। | O13: उन्होंने बताया कि प्रशिक्षण उपयोगी होते हैं और शिक्षकों के पढ़ाने के तरीको में सुधार लाते हैं। उन्होंने सुझाव दिया कि 3 से 5 दिन की अवधि वाले प्रशिक्षण जून माह में आयोजित किए जाना चाहिए स्कूल शुरू होने के बाद कक्षाएँ प्रभावित न हों। | P13: Margdarshika - Teaching Plan/Modules | Q13: टीएलएम आधारित शिक्षण, गतिविधि आधारित शिक्षण, लर्निंग आउट कम आधारित प्लानिंग, U आकार बैठक व्यवस्था, रिव्यू, एवं रिफ्लेक्शन, 16 चिट्ठी गतिविधि को लागू किया जायेगा l | R13: प्रशिक्षण के दौरान प्राप्त सामग्री और मॉड्यूल उपयोगी रहे। प्रशिक्षण के दौरान साझा की गई रणनीतियों का उपयोग उन्होंने अपनी कक्षाओं में किया। हालांकि मोबाइल पर प्राप्त PDF सामग्री का उपयोग अपेक्षाकृत कम हो पाता है, जबकि पुस्तक या मुद्रित सामग्री अधिक उपयोगी रहती है। | T13: वे समय-समय पर ऑनलाइन प्रशिक्षण और यूट्यूब आधारित सत्रों में भाग लेती हैं। इन गतिविधियों से प्रशिक्षण में प्राप्त सीख का रिवीजन करने से बेहतर समझ विकसित करने में सहायता मिलती है। हालांकि कई बार ऐसे सत्र विद्यालय समय में आयोजित होने के कारण उन्हें पूरी तरह से देख पाना कठिन होता है। | U13: फॉलोअप गतिविधियाँ (YTL) प्रशिक्षण में सीखी गई बातों को याद रखने और कक्षा में लागू करने में मदद करती हैं। हालांकि यदि ये गतिविधियाँ विद्यालय समय में आयोजित होती हैं तो शिक्षण कार्य और प्रशिक्षण दोनों को संतुलित करना कठिन हो जाता है। | W13: प्रशिक्षण का समय और कक्षा का समय एक होना। अतिरिक्त प्रशासनिक कार्य। सीमित समय। | X13: DIKSHA Courses, iGOT Courses. | Z13: DIKSHA, YouTube, WhatsApp, Attendance App. | AA13: डिजिटल माध्यम से सीखने से नई जानकारी और नए शिक्षण तरीकों तक आसानी से पहुंच बनती है। शिक्षक अपनी सुविधा के अनुसार सामग्री देख सकते हैं और आवश्यकता पड़ने पर उसे दोबारा भी देख सकते हैं। | AB13: डिजिटल सीखने को उपयोगी मानती हैं, लेकिन नेटवर्क संबंधी समस्याएँ और तकनीकी चुनोतियाँ कभी-कभी सीखने की प्रक्रिया को प्रभावित करती हैं। उन्होंने बताया कि कुछ DIKSHA कोर्स में प्रगति से संबंधित समस्याएँ भी आई हैं। कोर्स पूर्ण होने के बाद फिर से शुरुआत हो जाती है l | AD13: मैडम ने बताया कि वे समय-समय पर DIKSHA एवं अन्य ऑनलाइन कोर्स करती हैं। उन्हें विशेष रूप से ऐसे कोर्स पसंद आते हैं जिनमें कक्षा से जुड़े वास्तविक उदाहरण दिए जाते हैं और जिनकी सामग्री सीधे शिक्षण कार्य में उपयोगी होती है। वीडियो आधारित सामग्री और प्रश्नोत्तरी जैसी गतिविधियाँ सीखने को अधिक रोचक बनाती हैं। | AE13: कई बार कोर्स पूरा करने के बाद भी प्रोग्रेस अपडेट नहीं होती और कोर्स दोबारा शुरू से दिखाई देने लगता है। कुछ मॉड्यूल में टिक मार्क या कम्प्लीशन स्टेटस सही तरीके से नहीं दिखता। यदि तकनीकी समस्याओं का समाधान किया जाए तो अनुभव और बेहतर हो सकता है। | AF13: मैडम ने बताया कि अधिकांश कार्यक्रमों, प्रशिक्षणों और डिजिटल कोर्सों की जानकारी उन्हें JSK व्हाट्सएप समूह के माध्यम से प्राप्त होती है। यदि कोई जानकारी छूट जाती है तो विद्यालय के अन्य शिक्षक भी उसे साझा कर देते हैं। उनके अनुसार व्हाट्सएप वर्तमान समय में सबसे प्रभावी संचार माध्यम है। | AK13: 1. सभी विद्यालयों के शिक्षकों को आपस में मिलकर अनुभव साझा करने का अवसर मिलता है। 2. अन्य शिक्षकों के नवाचारों और गतिविधियों से सीखने का मौका मिलता है। | AL13: जब शिक्षक खुलकर अपने अनुभव, चुनौतियाँ और नवाचारी प्रयासों साझा करते हैं तो सीखने का माहौल बनता है। यदि शिक्षक एक-दूसरे को व्यावहारिक सुझाव दें और समस्याओं के समाधान साझा करें तो ऐसा मंच अधिक प्रभावी बन जाता है। | AM13: मैडम ने बताया कि CLSS के दौरान एक अन्य शिक्षक द्वारा साझा की गई "16 चिट्ठी गतिविधि" को उन्होंने अपनी गणित कक्षा में लागू किया। इस गतिविधि में खेल के माध्यम से प्रश्नों का अभ्यास कराया गया, जिससे बच्चों की सहभागिता और रुचि दोनों बढ़ीं। | AN13: 1. सत्र का समय सुबह रखा जाए। 2. परिवहन सुविधा और स्थानीय परिस्थितियों को ध्यान में रखकर समय निर्धारित किया जाए। | AO13: CLSS के बाद साझा की गई PPT उपयोगी रहती है और आवश्यकता पड़ने पर उसे देखकर कक्षा में गतिविधियों को लागू किया जा सकता है। हालांकि अधिकतर सामग्री डिजिटल रूप में मिलती है, इसलिए कई बार उसे दोबारा देखने का अवसर नहीं मिल पाता। | AP13: Resources shared in the school whatsapp group Participating teacher verbally cascade the learning (Peer learning discussions | AQ13: Participating Teacher verbally shares learning with colleagues. WhatsApp Group में सामग्री साझा की जाती है। | AR13: मैडम ने बताया कि CLSS में भाग लेने वाले शिक्षक विद्यालय वापस आकर अन्य शिक्षकों से चर्चा करते हैं। कई बार PPT या अन्य सामग्री भी साझा की जाती है ताकि अन्य शिक्षक भी सीख सकें। | AS13: Awareness Issue, Unwilling teachers | AT13: मैडम ने बताया कि अधिकांश चुनौतियाँ तकनीकी नहीं बल्कि समय और यात्रा से जुड़ी होती हैं। कई बार सत्र समाप्त होने के बाद शिक्षकों को तत्काल वापस लौटना पड़ता है l कई बार नेटवर्क की समस्या होती है जिससे फीडबैक या अन्य औपचारिकताएँ पूरी करने में कठिनाई होती है। | AY13: मैडम का मानना है कि यदि मेंटर सहयोगात्मक दृष्टिकोण से कार्य करें और शिक्षकों को व्यावहारिक सुझाव दें तो यह प्रक्रिया शिक्षण गुणवत्ता सुधारने में सहायक हो सकती है। शिक्षक ऐसे फीडबैक को अधिक महत्व देते हैं जो सीधे कक्षा में लागू किया जा सके। | AZ13: सहयोगात्मक दृष्टिकोण अपनाना। शिक्षक की वास्तविक परिस्थितियों को समझना। केवल कमियाँ बताने के बजाय समाधान सुझाना। व्यावहारिक और लागू किए जा सकने वाले सुझाव देना। | BA13: मेंटर कक्षा संबंधी चुनौतियों के समाधान सुझाएँ, अच्छे उदाहरण साझा करें तथा समय-समय पर मार्गदर्शन प्रदान करें जिससे शिक्षण कार्य और प्रभावी बन सके। | BB13: मैडम TLM और गतिविधि आधारित शिक्षण में रुचि रखती हैं। उन्होंने स्वयं अतिरिक्त संसाधन खोजने और प्रयोग करने का प्रयास किया है। उन्होंने सुझाव दिया कि टैबलेट के साथ-साथ प्रोजेक्टर जैसे संसाधन भी विद्यालयों को उपलब्ध कराए जाएँ। जिससे शिक्षण और अधिक बेहतर हो सकता है l | BC13: मैडम की बातों से यह स्पष्ट होता है कि उनकी प्रेरणा मुख्य रूप से आंतरिक है। उन्होंने कई बार यह उल्लेख किया कि वे बच्चों की बेहतर समझ और सहभागिता के लिए नई गतिविधियाँ, TLM और अन्य शिक्षकों से सीखी गई रणनीतियाँ अपनी कक्षा में लागू करती हैं। CLSS में सीखी गई "16 चिट्ठी" जैसी गतिविधि को कक्षा में आजमाना और बच्चों की सीखने की प्रक्रिया को बेहतर बनाने के प्रयास यह दर्शाते हैं कि उनका ध्यान प्रमाणपत्र या औपचारिक आवश्यकताओं से अधिक बच्चों के सीखने के परिणामों पर है। हालांकि प्रशिक्षणों में भाग लेना विभागीय अपेक्षाओं का भी हिस्सा है, लेकिन उनके उत्तरों से सीखने और स्वयं को बेहतर शिक्षक बनाने की व्यक्तिगत इच्छा अधिक दिखाई देती है। | BF13: V Good
A14: 13 | B14: Rahul Kumar | C14: Ashish Nigam | D14: Ujjain | E14: Female | F14: 46184 | G14: Maths | H14: 25 | I14: 3 Class a day is fixed, preparation for the next day classroom | J14: Portal records, maintaining registers | K14: in the school time, she takes 3 classes and after that in the rest time, she maintain some nonacademic works like- register maintenance etc. | M14: Participated in Block level subject training, One CLSS in August 2025, one digital course has been completed in December 2025. | N14: she was unable to recall all the activities right now. She told that If you could elaborate a little more, I may be able to remember and provide the details. I do remember participating in the CLSS held in August and attending the related training sessions. I also completed one PLC course during the academic year. | O14: She emphasized that while training programs are important, there should be minimal repetition of content across trainings. Repeated coverage of the same topics can reduce engagement and the perceived value of the sessions. She also suggested that trainings be scheduled before the reopening of schools, as conducting them during the academic session can disrupt classroom teaching and affect student engagement. | P14: Margdarshika - Teaching Plan/Modules | R14: Customization of the modules is important, as classroom realities often vary significantly. In many cases, the available infrastructure and resources may not be sufficient to implement the learnings exactly as presented. Adapting the content to the local context can help ensure that the strategies and approaches remain practical, relevant, and effective for teachers | T14: not sure about particular activities related link because of large no of messages and the other priority and compulsory works. The information or link has not been reached to the teachers and she is not sure about it. | U14: The followup activities or SKY, YTL is not compulsory and it any information or activities would come as compulsory then we will definitely participate. | V14: Nonacademic work, multiple communication from different interventions and priority of the same | W14: Non-Academic work are more and it consumes lot of their school hours which allows them less time in classroom to teach and do suggested activities or approaches (As covered in trainings) | X14: PLC course, Mansikta Course on IGot on Karmyogi app | Z14: Diksha, Igot and Education portal | AA14: It can be done in their own space and time | AB14: There should be content for children also, there are lot of technological issues on digital learnings like login issues. | AC14: The digital course should more contextualized in terms of classrooms and children | AD14: Animation videos and questions after each video are engaging. | AE14: This is specific to DIKSHA course App- for now Teachers can forward the course and it shows completed. there should be time tracker to track teachers time spent on DIKSHA also so that no one can forward the videos | AF14: The experience is good but I am (respondent) not able to recall the learnings | AG14: Teacher has done one course on PLC, For other courses, there was no awareness because of communication overlow in dedicated groups. | AH14: There are lot of daily basis information coming on whats app technical challenges also (Login Issues) | AJ14: Teacher was able to recall first month (August) CLSS topic correctly. | AK14: It is the platform where we can share our thoughts, the discussion is around classrooms like seating arrangements | AL14: It is academic platform and notes should be shared in JSK and school groups | AM14: CLSS of August 2025 was around seating arrangement and that was helpful | AN14: No comments | AO14: No comments | AP14: No learnings shared or no set process adopted | AQ14: No process is there but I think that could be done | AR14: The notes should be shared on whatsapp group with everyone | AS14: There is no challenges | AT14: There is no challenges | AY14: Mentoring, especially through classroom demonstrations, can be very important and effective. Teachers should not feel fearful when someone visits the school to discuss teaching practices or observe the classroom. Classroom observations should be conducted in a supportive and developmental manner so that teachers feel comfortable and open to learning. | AZ14: He/She should talk and discuss in a respectful manner. He/She should understand our challenges as well. The mentor should be from the same subject area. The mentor should come with innovative practices. There should not be any pressure from the mentors. The mentor-teacher talk ratio should be 30:70. The dignity and image of the teachers should be kept in mind. The way of explaining things should be effective. They should be polite. First, they should ensure that the teacher feels comfortable. | BA14: The feedback process should be one to one, not in front of all, the support from the mentor should be ongoing after visit also, There should be subject wise discussion after the observation or mentoring visit , as geometry in the mathematics | BB14: There should be training sessions or discussions on Geometry as well, as it is often difficult to work with children on these topics. Additional support and guidance on teaching Geometry would help teachers address students' learning challenges more effectively. | BC14: There is not much active participation in TPD related activities, has general awareness around CLSS topics (that too on prompted), has participation because of departmental obligation. Average level of extrinsic motivation only, no intrinsic motivation as such shown. However, prompt on taking her academic periods | BF14: Average
A15: 14 | B15: Rahul Kumar | C15: Ashish Nigam | D15: Ujjain | E15: Female | F15: 46185 | G15: Science | H15: 25 | I15: No. of classroom periods taken: 4 periods daily Academic responsibilities: checking copies, profile update. | J15: Register update, profile completion, Apar ID | K15: took 4 classrooms daily of Science Subject and rest of the time non academic work | M15: Digital course - PLC Dec, Subject training - July 2025, other 5 Days training - February 2026 | N15: regular classroom, trainings and non academic work | O15: There should be some experiential learning session in In-person training, there should be no time pass, Training is only time pass | P15: Not received | R15: Not able to recall the learnings from any materials | T15: Not participated in any of the follow up activities, even not known any of them | U15: The information was not shared; CAC or CRC did not share any information of any follow up activities. | V15: Information not shared | W15: The attendance and student learning level is low, and children are not able to read and write and that is the main reason we did not implement any learning of trainings in the classroom | X15: PLC digital course | Z15: Diksha and Igot | AC15: There is no time available for digital learning, We do Diksha courses in pieces but there is no learning remain in the pieces. | AE15: The course should be for 45 min only. The pdf can be provided after Diksha course | AF15: Not able to recall any learning from digital course because it took lot of time we completed it in bit and pieces | AL15: There should be a mechanism to share the learning at the school level as well. Whoever attends CLSS should also share their learnings with colleagues at the school level. | AP15: No learnings shared or no set process adopted | AQ15: Learning of each CLSS should be shared at school level | AR15: There should be one combined meeting at school level also to share the learning of CLSS | AU15: Not instructed to attend Didn't find any information | AV15: Only one teacher from our school attended the CLSS, and I did not get the opportunity to participate in the CLSS | AW15: Everyone should get opportunity to participate | AY15: Classroom observation can be helpful for the teachers, but no one came to do this till date. | AZ15: The respect and communication should be clear | BA15: The mentor should have in-depth knowledge of the subject. Feedback should be provided privately and not in front of the children. While there is pressure to improve performance, teachers are doing their best with the available resources and circumstances. The mentor should listen to and understand the real challenges faced in the classroom. They should be able to demonstrate effective classroom practices through model lessons and visit schools at regular intervals. The mentor should also be supportive, approachable, and willing to help teachers address their concerns and improve their teaching practices. | BB15: The professional development journey has not been visualized but I want to learn the computer more as most of the things are based on technology now. | BC15: It has been observed that teacher has no motivation to learn because of system is not promoting the academics | BD15: No has taken place over the past three years and nothing has been read for the same. There should be a provision to retain students who have not achieved the required learning outcomes, as many students are being promoted without sufficient learning. As a result, teachers continue to face the same challenges in the classroom, with students struggling to cope with grade-level expectations. Parents are not aware and that is the real challenge. | BF15: Good
A16: 15 | B16: Rashmi Mishra | C16: Rajshree Behera | D16: Gwalior | E16: Male | F16: 46184 | G16: Social Science Sanskrit | H16: 25 | I16: Conducting prayers with children in morning, Taking subject periods – Sanskrit and social science , Lesson planning (at home) , Test preparation | J16: Looking after the cleanliness of the school premise before school starts either with the help of school mid-meal staffs or on their own, going to children to bring children/ students to school., Admission responsibilities , UDISE Data related work, APAR ID related work, on call visits to BRC offices to collect books and all | K16: I try to allocate minimum 50% of my time to teaching and students. हम तो पहले ही पहुँच जाते हैं वहाँ पे peon तो है नहीं, यहाँ पे तो साफ सफाई भी बाइ वगैरह उनसे करवा लेते हैं। की बच्चे ग्रामीणों में हैं तो बुलवाने जाना ही पड़ता है। | L16: Subject Training Digital Training CLSS YTL Election related Duties Any other | M16: Subject training (August), CLSS (November & December), I got training (Across the year), Tree plantation (Across the year), YTL ( September), | N16: I participated in Tree plantation program, S Attended subject training in Balaji school, Every Saturday there is shaikshik samwaad. Observation note- 26 courses completed in last academic years, mostly after school at home. With a few prompts he could remember the shaikshik samwad platform and subject training with elaborated clues. On first instance, teacher was able to recall more non-academic related activities such as tree plantation drive, Yoga workshop etc. Reported attending shaikshik samwaad twice with Head Teacher. | O16: Reason for finding it useful: Through training, teacher or I tend to get new zeal to take new learnings to classroom, experiment in teaching or teach something mew students. मैं चाहूँगा इस तरह का (in-person training) बीच बीच में होते रहना चाहिए” I would prefer such trainings to be condducted in more frequencies at least 2-3 times in a year. It provides platform for us to learn from other teachers practices, when they share their learning and practices. We also tend to find some contextual solutions from there. कुछ मेरे से ऐसा लग रहा था की मेरे से कोई छूट रहा है तो जो वहाँ पे सहपाठी और लोग थे मेरे वहाँ पे उन्होंने बताया था तो वो ही मेरे लिए नया लगा था उनकी जो उन्होंने बताया था की मतलब इस पद्धति से आप पढ़ाई में बच्चों को देंगे तो ज़्यादा बेहतर रहेगा। Training was good, facilitators were knowledgeable, facilities are imporving and were satisfactory at the centers, we didn’t face any issues. One practice/ learning recalled- samuhik charcha (group discussed), which teacher also tried applying in classroom and found useful to bring excitement in children. He also mentioned about cold calling (chit wali gatividhi) saying it alerts students that anyone’s turn might come to respond. | P16: Margdarshika - Teaching Plan/Modules | Q16: Hook and Group Discussion | R16: I read margdarshika after but cannot remember anything as such at the moment from the booklet. Observation- Teacher was not able to recall any content matter from the booklet and couldn’t share any concrete usecase with the margdarshika. He seemingly liked the hardcopy as reference material for future use. | T16: Session during school timing and internet connection issue with other teachers may need to be think around. “मेरे हिसाब से तो ये फायदेमंद रहेगा। यदि ये क्योंकि जो अपने को नहीं आ रहा है तो उसको सीख जाएंगे।“ | U16: Different topic are being discussed there which we as teacher might also be struglling to teach in class, so we get to learn simple technique or pedagogy which helps. Continuity or interval learning learning helps teacher. | V16: No Observation Note: While speaking for himself, he shared the positive feedback and experience on Yutube live whereas on further probing he highlight practical issues from other teachers front which can be applicable to his context as well such as session during school time where teacher is already strugging to maximize instruction time. | W16: No response | X16: PLC and Karmyogi Course series | Z16: DIKSHA and I GoT | AA16: Absence in two way communication | AB16: Teacher spoke about him completing 26 digital courses on Karmyogi very proudly, he likes to complete the tasks or prompt on completing the orders from the officials. However, not very sure if he would do on his own interest. | AC16: Teacher spoke about him completing 26 digital courses on Karmyogi very proudly, he likes to complete the tasks or prompt on completing the orders from the officials. However, not very sure if he would do on his own interest. | AD16: Narrators language use was very effective and simple to understand, in-between quizes was good because it checked our knowledge and in a way ensures that people focus on the content otherwise teacher may just put it in start and continue with their other work. Assessments also had questions related to content that also helps in learning and knowledge. | AE16: There are no specific feedback on the content, it’s all fine. If BRC sir decides for every teacher or send them the order that we have to do xyz course in this month then teachers would follow it more seriously other it doesn’t happens on teac’er's will. | AF16: Lot of aspects of the DIKSHA digital course teacher was able to remember except the learning content. It also took him a while after showing posters and all that he could recall what the course was about. Though he shared about his busy life after school but with that too he reported to be comfortable in dedicating 4 hours in a week for online courses. There was general preference for the in-person, face to face modality in learning than the online mode. | AK16: Facilitators are good and knowledgeable. The platform for same subject or senior teachers to come at one place and exchange learnings. “हम एक जगह आके, जो नहीं आ रहा उसका दिसरे शिक्षको से सुनके निवारण कर लेते है।“ सामुहिक चर्चा हो जाती है. There is no restriction of the theme but | AL16: Exchange of knowledge and best practices between teachers. | AM16: Not able to remember | AN16: It should be longer, a day can be dedicated and it should be subject wise | AO16: Not able to recall about facilitation guide or ppt | AP16: Participating teacher verbally cascade the learning (Peer learning discussions | AQ16: हाँ, विद्यालय से शैक्षिक संवाद में उपस्थित शिक्षक शाळा में अन्य शिक्षकों को सीख को साझा करेगा एवं पूरी प्रक्रिया को समझाएगा | AR16: जिला/ब्लाक/जन शिक्षा केंद्र स्तर से सभी अधिकारीयों द्वारा समय समय पर इसका फोलो उप होना चाहिए ताकि सभी शिक्षक साथी कार्य को गंभीरता से लें एवं विद्यालय स्तर पर कार्यक्रम प्रभावी रूप से लागू हो सके। | AS16: Not perceived important others | AT16: There is no issue in using the platform, sometime teachers may face internet issues. It should be enforced more seriously that it has to be done and there no other way then teachers may take it more seriously to mark their attendance. Observation- Teacher recalled RSK MP on their own, shows familiarity and engagement with the portal. He also has attended CLSS twice in a year and looks diligent in following seniors all instructions. he also responded to be decently familiar and ok with the technology. | AY16: By classroom observation or kaksha avlokan, we mean observing students in classroom, what they are studying, how they are doing in the subject or teaching plan. Secondly, from teachers observation perspective, it’s observing teachers classs period end to end and identifying where they are making mistakes or they can do better and then sharing the same with the teachers. I have experience and some good experience of having my classroom obbserved by officials. There are no classroom observed in last few years. It is a good and helpful practice. It should be done atleast twice in a year for every teacher. | AZ16: They should not overwhelm teacher with administrative and logistical asks such as where are all the registers, why those are not complete etc. for these matter they can have doscussion with Head master or teacher. With teacher their discussion should be academic and pertaining to their classroom teaching and practices. Language should also be professionl and respectful to make teacher comfortable. Feedback should not be shared in front of students to respect teacher’s decorum in the class and with their students. They can have the discussion later in office or separately with the teacher | BA16: Academic feedback, respectful behaviour. | BB16: There should be less data related work burden on the teachers to increase their instruction time in classroom. There should be dedicated data professional in schools to do these tasks. | BC16: Teachers sounded very occupied and busy with his personal life commitments such as ill wife, personal health and household responsibility. Because of which he quoted to be not keen in going for any training or added responsibilties. Repeatedly he tried to ensure if this interview would not add any work in his already busy schedule. He also looked sincere in following official instructions which tells about his participation in most of our interventions. However, the participation was just for the sake of it. He quoted to be motivated and interested to teach students in classroom but non-academic responsibilities adds burden. Emphasize on relaying more on official instruction and direction to get teacher participate in activities. No personal initiative to learn or participate. | BD16: The recall value of the content and subject matter was dismisally low. | BE16: nO | BF16: Good
A17: 16 | B17: Naushad Mirza | C17: Deeksha Singh | D17: Panna | E17: Male | F17: 46183 | G17: Maths | H17: 16 | I17: Teaching students | J17: tasks such as ensuring school cleanliness, responding to information requirements from the state, overseeing bookdistribution, managing basic resources like chalk and other teaching materials, and coordinating tasks related to student attendance and other school operations. | K17: According to him, as a Head Master (HM), around 70% of his time is dedicated to academic responsibilities, while theremaining 30% goes into administrative tasks. He believes that students should always remain at the centre of aschool’s functioning and ideally, he would like to devote 100% of his time towards supporting his students’ learningand development. He shared that he tries to plan and complete administrative tasks in advance so that last-minuterequirements do not aff ect his availability for students and academic work. He also mentioned that he often worksbeyond school hours to complete his HM responsibilities and ensure that both academic and administrative dutiesare managed eff ectively. He referred to a leadership training based on NEP 2020, where he learned that an HM’s roleis not limited to individual responsibilities but also includes ensuring that all stakeholders in the school workcollaboratively towards a common goal. He further shared that eff ective management skills help an HM balanceboth administrative and academic responsibilities. However, he feels that having additional support, such as acomputer operator dedicated to administrative tasks, would help reduce the administrative burden and allow HMsto focus more on academic leadership and student development. | L17: Subject Training Digital Training CLSS SKG HM Training | M17: He shared that he participated in a three-day subject training conducted at the block level in Ajaygarh. He alsomentioned completing one or two digital courses; however, he was unable to recall the specifi c names or details ofthese courses. Additionally, he has attended CLSS as participants. | N17: Based on the conversation, it appeared that he was sharing his experiences genuinely; however, he was not able to recall specific details, instances, or examples related to the trainings he had attended. His understanding and recollection of the trainings seemed somewhat unclear, and he appeared to be combining aspects from multiple training programs while explaining his experiences. Despite probing and providing support to help him recall specific programs or experiences, it remained challenging to identify the exact trainings he was referring to, as his responses often moved between different topics and ideas. As a result, it was difficult to gather detailed insights about his participation, learnings, and experiences from these trainings. | O17: Teacher thinks that only if trainings are being conducted in diets or conducted by senior teacher/ master trainer who is from outside that has better experience as compared to people around them and this is beneficial for them. * PPT | P17: Margdarshika - Teaching Plan/Modules | T17: He didnt join or participated in follow up activities. he might have done Sheekh ki Yatra (Quizzes) but he isn't sure and can't recall about it. | U17: According to him, all trainings are useful, and he expressed a very positive outlook towards professional development opportunities. He shared that he has gained several learnings from different trainings throughout his career. Some of the key learnings he mentioned included ensuring that everyone moves forward together, including both students and teachers; addressing the diverse learning levels of students; and understanding different pedagogical approaches. He specifically mentioned learning about Aagman and Nigman methods of teaching Mathematics, ways to develop students’ interest and curiosity towards Mathematics, and the effective use of TLMs and charts in the classroom. He also highlighted the importance of activity-based learning (gatividhi aadharit shikshan) and shared that he applies the Shikshan Chakra approach and its different elements in his teaching practices. | V17: due to administrative work as being an HM and personal reasons. | W17: He shared that he has learned a lot through various trainings; however, he believes that every learning or strategy cannot be directly applied in the classroom. According to him, he has to change quite often acc to his students. He mentioned that he uses the Shikshan Chakra approach in his teaching practices. However, he shared that concepts often need to be revisited and explained repeatedly until students develop a clear understanding of the topic. | X17: It was shared in the group, and the CAC has been consistently encouraging participants and sending timelymessages and nudges to support them in completing the courses. | Z17: diksha app, whatsapp | AA17: This teacher has a very positive outlook toward any kind of training and its learning (be it in-person or digital). HEbelieves that any training and any digita courses you get to see something new which eventually will be good for the students. | AB17: can't recall much about the courses. | AI17: पूर्वज्ञान से शुरु, समूहकार्य से सीख प्रभावी गृहकार्य पुनरवलोकन एवं समेकन | AJ17: he was talking very highly about clss, as this is the platfrm where he gets to discuss with his fellow teachers and it helps him a lot. | AK17: 1. fellow teachers come and share their teaching experience. 2. He learned about TLM, making diff students learn together, how to give good homework. | AL17: Discussion among teachers. | AM17: giving homework daily, helping students to believe in them, helping students build curiosity. | AN17: Changing its frequence to twice in the year and also making it in a way that teachers gets motivated. | AP17: Participating teacher verbally cascade the learning (Peer learning discussions | AQ17: He would rate current CLSS 3/5. He wasnt sure about how many clss he has attended. Also he wasnt sure that what were the topics of these clss. | AR17: He thinks that maste trainers can be better, maybe one person can be from Diet. | AS17: Session end rush for teachers to leave the venue | AT17: Acc to the teacher to make CLSS better, teachers should have a teacher diary where they write and share their learnings and experiences. Teacher was claiming that he went for clss but he couldn't recall anything related to topics. He has very blurmemory of it, which suggest that quality of CLSS isn't good enough that teachers recall and remember their conversation of CLSS for the long duration. | AY17: Teacher thinks mentoring is good for their development and also for students. | AZ17: To check register, look to the class and see what teacher is teaching, Note down, Also show the teacher how to teach by giving a demo, At the same time dont torture the teacher as well. | BA17: mentioned above | BF17: VGood
A18: 17 | B18: Pushpendra Singh | C18: Krishna | D18: Rewa | E18: Female | F18: 46188 | G18: Hindi Social Science | H18: 22 | I18: Teaching Social Science and Hindi to Classes 6-8. Taking 4 teaching periods daily. | J18: All roles and responsibilities of School Leader, Morning assembly duties, Taking and maintaining student attendance, Admission-related work and record maintenance, UDISE data entry and updating records, APAR-related administrative work, Scholarship-related documentation and verification, Mid-Day Meal monitoring and supervision, Maintaining school records and registers, Completing reports and other administrative paperwork assigned by the school or department, Coordination of various school activities and government programs, Monitoring student attendance and follow-up on absenteeism, | K18: The teacher remains actively engaged in both academic and administrative responsibilities throughout the school day. A significant portion of time is devoted to classroom teaching of Social Science and Hindi for Classes 6–8, using discussion-based and activity-oriented methods. Alongside teaching, the teacher manages various non-academic duties such as attendance, admission work, UDISE, APAR, scholarship-related tasks, and mid-day meal monitoring. Despite administrative responsibilities, the teacher demonstrates continued involvement in professional development through trainings, CLSS sessions, and digital learning platforms. | L18: Subject Training Digital Training CLSS YTL SIR Election related Duties | M18: The teacher could not recall the exact dates and duration of participation. However, the teacher reported attending Subject Training, CLSS, Digital Training, YouTube Live sessions, follow-up activities, and DIKSHA courses during the academic year. | N18: The teacher was able to recall participation in different training and learning activities and shared experiences from these programs. Exact dates and timelines were not remembered. | O18: The teacher shared that the training was helpful and provided useful information related to teaching. The teacher mentioned that the content was relevant and could be used in classroom teaching. The teacher felt that training programs should be monitored effectively and conducted regularly at intervals so that teachers can continue learning and improving their teaching practices. | P18: Not received | R18: The teacher did not recall receiving any training materials or resources and therefore could not share feedback on their usefulness or classroom application. | S18: The teacher starts class with a hook (concept not clear to the teacher) related to the topic and the teacher shared an example of using pre-knowledge questions before starting a new lesson. The teacher also reported using questioning techniques and student participation strategies learned during the training to make classroom discussions more interactive and engaging. | T18: The teacher found the follow-up activities useful. These sessions helped the teacher learn new ideas, stay updated, and continue discussions related to teaching and classroom practices. | U18: The teacher found the follow-up activities useful because they helped in providing good homework ideas and classroom tasks that could be used with students. | V18: Network connectivity issues, clash with school timings and mobile data exhaustion were reported as the main challenges that may limit teachers' participation in online discussion calls. | W18: Different learning levels of students and irregular student attendance were reported as the main challenges in implementing training learnings in the classroom. And lack of willingness of the teachers are also a major issue teacher said. | X18: The teacher reported completing courses on the DIKSHA platform during the last year but was unable to recall the exact course names. | Y18: No non-government or self-enrolled courses were reported by the teacher. | Z18: The teacher reported using DIKSHA, YouTube Live, and WhatsApp as online platforms for learning and accessing training-related information. | AA18: The teacher felt that digital courses are an effective way of learning because they provide useful information, can be accessed easily, and help teachers improve their classroom teaching practices. | AB18: The teacher considered digital learning useful because it provides opportunities to learn new things and supports classroom teaching. The teacher reported using DIKSHA courses and viewed them as a helpful source of learning. | AC18: The teacher shared that information about digital courses and training opportunities is usually received through the Jan Shiksha Kendra WhatsApp group. The teacher preferred accessing digital learning opportunities through these communication channels and reported network and data limitations as occasional challenges. | AD18: The teacher was unable to recall the names of the DIKSHA courses completed. However, the DIKSHA app is installed on the teacher's device, and the teacher referred to the books and resources available there for learning and teaching support. | AE18: The teacher did not provide any specific suggestions for improving the quality of the DIKSHA courses. | AF18: The teacher shared that digital courses help improve understanding and make classroom teaching easier. The teacher is able to complete courses from home and finds the content useful. Features such as animated videos, quizzes, assessments, and course resources were found helpful. The teacher suggested that digital courses should also be developed for students. Information about courses is usually received through WhatsApp and phone calls. Network issues are sometimes faced, and the teacher uses a personal hotspot for internet access on the tablet. | AI18: कक्षा प्रबंधन के शुरुआती प्रयास प्रभावी गृहकार्य पुनरवलोकन एवं समेकन | AJ18: The teacher found topics such as cold calling, classroom rules, and classroom management useful, as they provided practical strategies for improving student participation, maintaining discipline, and managing classroom activities effectively. | AK18: It provides an opportunity to learn and share experiences with other teachers. It helps in understanding classroom challenges and finding practical solutions through discussion. | AL18: A helpful peer learning community is one where teachers regularly discuss their experiences and share key learnings with others. The teacher felt that even when someone is unable to attend a session, they should be informed about the important discussions, suggestions, and practical ideas shared during the meeting. | AM18: The teacher was not able to recall any specific instance where CLSS learning helped solve a classroom challenge. She shared that she is currently undergoing medical treatment, which made it difficult to remember specific examples. However, she mentioned that the experiences and discussions shared during CLSS have been helpful in her teaching practice. | AN18: The teacher suggested that TLMs should be provided through CLSS. The teacher also felt that supporting content and learning materials should be shared with participants to make the sessions more useful and easier to implement in the classroom. | AO18: The teacher did not provide any feedback on the facilitation guide or PPT. | AP18: Participating teacher verbally cascade the learning (Peer learning discussions | AQ18: CLSS learnings are usually shared through informal discussions with colleagues in the staff room, either before the start of the school day or whenever teachers get time to discuss. | AR18: The teacher suggested that teachers who attend CLSS sessions should share the key learnings with colleagues who could not attend. Regular discussions among teachers and sharing experiences from the sessions can help spread learning and promote peer learning at the school level. | AS18: others | AT18: The teacher suggested that attendance and feedback forms should be completed before the CLSS session ends. The teacher also mentioned that teachers who finish the feedback process early can support other teachers in filling out their forms. | AY18: The teacher felt that classroom observation and mentoring are helpful when officials try to understand the teacher's context and provide constructive support. However, when observations create pressure or fear and teachers feel misunderstood, the process becomes less comfortable and less useful. | AZ18: The teacher felt that mentors should have clarity about the purpose of the observation and should provide proper handholding and support to teachers. Mentors should focus on suggesting practical solutions rather than only highlighting problems, communicate in a simple and respectful manner, and provide appropriate guidance based on the teacher's needs. | BA18: The teacher expected mentors to ask direct and clear questions (Officials coming for the visit lacks trust on teachers and it is not very professional to ask indirect questions coming from the ground of mistrust), as this makes it easier to share challenges and seek support. The teacher felt that unnecessary complications can create disinterest, while simple communication and practical suggestions help build a supportive mentoring process. | BB18: The teacher suggested that professional development opportunities should be provided in a supportive environment without creating pressure on teachers. The teacher also felt that regular monitoring by the district team would help improve the effectiveness of these initiatives. | BC18: No response given by the teacher. | BD18: No | BE18: No | BF18: VGood
A19: 18 | B19: Sonali Patidar | C19: Dilip Kag | D19: Harda | E19: Male | F19: 46185 | G19: Social Science Sanskrit | H19: 15 | I19: प्रतिदिन कक्षाओं का संचालन, बच्चों का पठन पाठन, विषय अध्यापन, समूह कार्य करवाना, बच्चों की सीखने की प्रगति पर ध्यान देना तथा खेलकूद गतिविधियों में सहभागिता सुनिश्चित करना। | J19: ऑनलाइन एमडीएम उपस्थिति दर्ज करना, एमडीएम व्यवस्था देखना, विभिन्न विभागीय जानकारियाँ एवं रिपोर्ट तैयार करना, विद्यालय प्रबंधन एवं प्रशासनिक कार्यों का संचालन। | K19: HM प्रभारी होने के कारण प्रशासनिक दस्तावेज़ों और विभागीय जानकारियों का काम प्रतिदिन रहता हैशिक्षक शैक्षणिक एवं प्रशासनिक दोनों जिम्मेदारियाँ निभाते हैं। विद्यालय में सीमित स्टाफ होने के बावजूद नियमित अध्यापन के लिए समय निकालते हैं। | L19: Subject Training CLSS SKG HM Training Any other | M19: ELIT प्रशिक्षण 2025, सामाजिक विज्ञान राज्य स्तरीय प्रशिक्षण 2025, CLSS अगस्त 2025 से नियमित, प्रशिक्षण उपरांत सीख की यात्रा , उमंग प्रशिक्षण 2025, जनगणना कार्य 2025-26 | N19: शिक्षक ने वर्ष भर विभिन्न शैक्षणिक गतिविधियों एवं प्रशिक्षणों में भाग लिया। शैक्षिक संवाद और विषय प्रशिक्षण को उपयोगी बताया तथा सीख को अन्य शिक्षकों के साथ साझा भी किया। | O19: प्रशिक्षण व्यावहारिक और कक्षा आधारित होना चाहिए। जिला या ब्लॉक स्तर पर प्रशिक्षण कम से कम 3 दिनों का होना चाहिए ताकि शिक्षकों को चर्चा और अनुभव साझा करने का पर्याप्त अवसर मिले। | P19: PPT Margdarshika - Teaching Plan/Modules ToT | Q19: समूह कार्य, चर्चा आधारित शिक्षण, प्रभावी गृहकार्य, पुनरावलोकन गतिविधियाँ। | R19: प्रशिक्षण सामग्री उपयोगी है तथा कक्षा शिक्षण में सीधे उपयोग की जा सकती है। | S19: शिक्षक ने CLSS एवं प्रशिक्षण से प्राप्त समूह कार्य, प्रभावी गृहकार्य, पुनरावलोकन तथा पूर्वज्ञान आधारित शिक्षण रणनीतियों का कक्षा में उपयोग किया। इन गतिविधियों से विद्यार्थियों की सहभागिता बढ़ी तथा सीखने की प्रक्रिया अधिक प्रभावी हुई। | T19: फॉलो-अप गतिविधियाँ प्रशिक्षण की सीख को दोहराने और व्यवहार में लाने में मदद करती हैं। शिक्षक ने सीख की यात्रा में कुछ गतिविधियाँ और क्विज पूरे किए। | U19: इन गतिविधियों से सीखी गई बातों पर पुनर्विचार करने और कक्षा में लागू करने का अवसर मिलता है। | V19: नेटवर्क समस्या, समय की कमी तथा विद्यालयीय कार्यभार। | W19: समय की कमी, प्रशासनिक कार्य और सीमित संसाधन। | AA19: डिजिटल माध्यम से शिक्षक अपनी सुविधा के अनुसार सीख सकते हैं तथा नई शिक्षण विधियों की जानकारी प्राप्त कर सकते हैं। | AB19: शिक्षक ने कोरोना के बाद कोई डिजिटल कोर्स नहीं किया। वे प्रत्यक्ष प्रशिक्षण को डिजिटल लर्निंग की तुलना में अधिक उपयोगी मानते हैं। | AC19: डिजिटल कोर्स 40-45 मिनट की छोटी इकाइयों में हों तो अधिक उपयोगी होंगे। | AG19: Other engagement Technical issue Not aware | AI19: कक्षा प्रबंधन के शुरुआती प्रयास पूर्वज्ञान से शुरु, समूहकार्य से सीख प्रभावी गृहकार्य प्रभावी पुनरावृत्ति | AJ19: समूह कार्य, प्रभावी गृहकार्य एवं पुनरावलोकन। | AK19: शिक्षकों के बीच अनुभव साझा करने का अवसर। व्यावहारिक शिक्षण रणनीतियों पर चर्चा। | AL19: खुली चर्चा, अनुभव साझा करना, नियमित सहभागिता और सहयोगी वातावरण। | AM19: समूह कार्य और चर्चा आधारित गतिविधियों को अपनाकर विद्यार्थियों की सहभागिता बढ़ाने में सहायता मिली। | AN19: अधिक व्यावहारिक उदाहरण शामिल हों। सत्र समय पर और संक्षिप्त हों। JSK केंद्र पर स्मार्ट टीवी हो और उसमे पीपीटी या module प्रेजेंट किये जाये | AO19: बहुत उपयोगी, क्योंकि ये चर्चा को संरचित और उद्देश्यपूर्ण बनाते हैं। | AP19: Resources shared in the school whatsapp group Participating teacher verbally cascade the learning (Peer learning discussions | AQ19: CLSS की सीख सहकर्मी शिक्षकों के साथ चर्चा के माध्यम से साझा की जाती है, लेकिन इसके लिए कोई नियमित या औपचारिक व्यवस्था नहीं है। | AR19: प्रत्येक CLSS के बाद विद्यालय स्तर पर छोटी साझा बैठक आयोजित की जाए। | AS19: Session end rush for teachers to leave the venue Not perceived important | AT19: शिक्षक CLSS में नियमित उपस्थिति दर्ज करते हैं और सत्रों में सक्रिय भागीदारी करते दिखाई दिए। लॉजिस्टिक व्यवस्थाओं को लेकर कोई प्रमुख चुनौती सामने नहीं आई, हालांकि कार्यभार एवं समय संबंधी बाधाएँ कभी-कभी सहभागिता को प्रभावित कर सकती हैं। | AY19: कक्षा अवलोकन शिक्षकों के लिए उपयोगी और आवश्यक प्रक्रिया है। इससे शिक्षक अपनी कमियों और अच्छी विधियों को पहचान पाते हैं तथा सुधार के अवसर मिलते हैं। | AZ19: शिक्षक को असहज न किया जाए। समय का ध्यान रखा जाए। विषय से संबंधित प्रश्न पूछे जाएँ। रचनात्मक फीडबैक दिया जाए। अवलोकन यथासंभव वास्तविक और आकस्मिक हो। | BA19: शिक्षण सुधार हेतु सुझाव, कक्षा संसाधनों की उपलब्धता, विद्यालय रखरखाव में सहयोग तथा मार्गदर्शन। | BB19: नियमित शैक्षिक संवाद जारी रहें, प्रशिक्षण छोटे एवं व्यावहारिक हों तथा डिजिटल कोर्स की तकनीकी समस्याओं को दूर किया जाए। | BD19: शिक्षक, प्रशिक्षण और शैक्षिक संवाद को डिजिटल कोर्स की तुलना में अधिक उपयोगी मानते हैं क्योंकि इनमें प्रत्यक्ष चर्चा और अनुभव साझा करने का अवसर मिलता है। | BF19: Good
A20: 19 | B20: Rahul Kumar | C20: Ashish Nigam | D20: Neemuch | E20: Male | F20: 46188 | G20: Social Science | H20: 13 | I20: 6 classes in a day, checking copies, daily prayer and extracurricular activities | J20: Attendance, managing mid-day meal, Jangadna, register work, logistics work of Science Exhibition, inspire award, Khel Mahotsav, | K20: usually 6 class on an average and responsibiltes is diveded among teacher and rotate also. | L20: Subject Training Digital Training CLSS SIR Election related Duties | M20: Participated in all CLSS except last one, In person training- July 2025, Digital course - Jan 2026 | N20: 70% Daily basis classes 30% non academic work | O20: Training should include experiential learning, the learning should be contextualize, The training was useful but not able to recall the content. | P20: Margdarshika - Teaching Plan/Modules | R20: they were not sure about the implementation of teaching materials. | S20: Vague example of topic related to Panchayat was shared. | T20: Not participated in any quiz like SKY but according to him participated in YTL. | V20: According to the teacher, he received information regarding these activities, but it has been conducted during school timing to it was tough to partciapte actively. He mentioned that he has partciapted in all YTL but nit able to reacll any learning or content. | W20: There should not be any training or activity conducted during regular class hours. It could be scheduled between 1:00 p.m. and 1:30 p.m. or between 2:00 p.m. and 3:00 p.m., when many teachers are engaged in non-academic activities. Alternatively, it could be conducted on Saturdays, which are designated as bagless days. | X20: PLC and courses on Karmyogi | Z20: Diksha App, I-GOT | AA20: Teacher can do in their own space and time | AB20: There are lot of online courses are coming. Courses on Karmyogi are compulsory so we are doing that regularly. | AC20: Teacher are doing 2 courses per month and completed on Igot and the PLC course also but not able to share any learning. | AE20: The courses should be of shorter duration, ideally 40–45 minutes, so that teachers can complete them more easily. Since a large number of courses are being offered, the learning from different digital courses tends to overlap and become mixed, making it difficult for teachers to recall specific content or comment on the quality of individual courses. | AF20: Overall, the teacher was not able to recall the key features or specific learnings from the digital courses. Even after considerable probing, he was unable to share concrete examples of learning. However, he mentioned that learning is not stagnant, as various activities and initiatives are continuously taking place. | AI20: कक्षा प्रबंधन के शुरुआती प्रयास प्रभावी गृहकार्य | AJ20: All the topics were useful. The session on seating arrangements and circulation in the classroom was particularly helpful, and he has tried to implement these practices in his classroom. He also learned about entry routines through CLSS and has been using them regularly in the classroom. | AK20: The colleagues can share their challenges openly, and new ideas and experiences are discussed so that everyone can learn from each other. After learning from each other we can apply the same in the classroom. | AL20: Everyone can share their ideas and experience | AM20: Circulate, sitting arrangement and entry routine helped | AN20: The impact and outcomes of CLSS should be systematically studied and documented at state levl. The findings should then be shared with all stakeholders to demonstrate how classroom practices and teaching-learning processes have improved across the state. | AO20: Not able to recall | AP20: Resources shared in the school whatsapp group Participating teacher verbally cascade the learning (Peer learning discussions | AQ20: The learning shared on school level regularly | AR20: There should be some short animated videos that can be shared with all teachers after the CLSS sessions so that everyone can benefit from them. | AS20: others | AY20: In observation includes, observing if strudents are sitting well (Disciplines, timetable, teaching practices (teacher & student engagement), if all stuents are able to see board etc. Mentoring should help teachers understand their growth areas, and these should be shared continuously through constructive feedback. Mentoring can support teachers in improving their classroom practices, and BACs and CACs are already conducting regular classroom observations to provide ongoing support. | AZ20: The behaviour of the mentor should be polite and respectful. He or she should avoid highlighting mistakes in front of others or focusing only on shortcomings. The mentor should be supportive and maintain a positive mindset throughout the mentoring process. Mentoring should include elements of recognition and appreciation, and the feedback provided should be constructive and actionable. The mentor should also be capable of demonstrating effective classroom practices through classroom demonstrations when needed. | BA20: He should be able to provide subject wise classroom demo. | BB20: All the agency and NGO should align on content beacuse variuos content did not help any tecaher. There should be oneness in all the activities | BC20: The teacher independently read about classical dance and discussed the topic with the children, indicating a sense of intrinsic motivation. However, the direction for further learning and professional growth appears to be somewhat unclear or not well-defined. | BF20: V good
A21: 20 | B21: Rajesh Solanki | C21: Jay Prakash | D21: Shivpuri | E21: Female | F21: 46188 | G21: Maths Science | H21: 24 | I21: सुबह शाला आने के बाद भागमभाग रहती हैं ,बच्चों का attendance लेते है, प्रार्थना कराते है, हमारा E attendance लगाते हैं हमारे शिक्षक App में क्योंकि उसी के आधार पर हमारा salary बनती हैं, हमारे शाला में 2 teacher हैं और 43 students हैं. बालसभा करते हैं | J21: आपार ID बनाते हैं, सर्वे करते हैं, डाक का काम करते हैं स्कूल का सभी डाक बनाते हैंI | K21: हर दिन 6 प्रेड लेते हैं, हमारा पूरा दिन बिलकुल भी फ्री नहीं होता हैंI syllabus पूरा करना होता हैं, मासिक टेस्ट लेना होता हैं. पेपर की तैयरी करनी होती हैं, साप्ताहिक बालसभा भी करते हैं.क्या पढ़ना ई कैसे पढ़ना है इसकी तैयरी करना पड़ता हैं | L21: Subject Training, Digital Training, CLSS | M21: मैंने 3 CLSS की चर्चा में भाग लिया था जिसमें हमने एक दुसरे के अनुभव से सीखना, पुस्तिका के आधार पर सभी के साथ चर्चा होती थी, किसी भी प्रकार के डिजिटल चीजों का ऊपयोग नहीं होता था. आपने बाद बताया की आपने 3 CLSS और हेल्थ वेलनेस कोर्स में भी भाग लिया था. | N21: CLSS की चर्चा में बच्चों की समस्या पर चर्चा होती है, सभी मिलकर उस पर चर्चा करते थे. पूरी प्रक्रिया बहुत अच्छा था, बहुत सारी चीज़े सिखने को मिलीI जब आपसे सीखे गए चीजों के बारे में बात किया गया तो आप इसका ठीक से उत्तर नहीं दे पा रहे थे I आपने ये भी बताया की आपने डिजिटल कोर्स भी किया हैI | O21: सब अच्छा था, इस पर शिक्षक ने किसी भी प्रकार का विशेष सुझाव नहीं दिया, आपने ये कहा की ट्रेंनिंग 2 से ज्यादा दिन की होनी चाहिए क्योंकि पहले दिन शिक्षक लेट से आते हैं और दुसरे दिन जल्दी जाने के लिय करते हैं. | P21: Margdarshika - Teaching Plan/Modules | Q21: शिक्षक ने बातचीत में किसी भी प्रकार का क्लियर उत्तर नहीं दे पा रहे थे, आपने यह कहा की ट्रेंनिंग अच्छी थी, लेकिन हम लोग पूरी तरह से से नहीं कर पा रहे थे , थोड़ा थोड़ा ही कर पायें. | R21: आपने इस पर कोई सुझाव नहीं दिया | S21: The teacher could not provide an answer when asked this question; he said he could not recall it at the moment. | T21: शिक्षक ने किसी भी प्रकार के follow-up activity में भाग नहीं लिया. | U21: Nothing | V21: Nothing | W21: Nothing | X21: AI, प्रिंट समृद्ध वातावरण, सिख एंड सहयोग, कर्मयोगी के कोर्से में भी भाग लिया था. | Y21: Nothing | Z21: Diksha App, I-GOT | AA21: इसमें बहुत सारे अच्छे विडिओ होते थे जिसके माध्यम से हमें सिखाया जाता था, इसमें बच्चों को सिखाने के लिय नए नए तरीको के बारे में पता चलता था. | AB21: इसके विडिओ बहुत interesting होते थे जिसके कारण इसमें भाग लेना अच्छा लगता था. आपने ये भी कहा की कोर्स में अधिक से अधिक विडियो होना चाहिए पढ़ने वाला कम होना चाहिएI | AC21: तकनिकी समस्या के कारण बिच-बिच रुक जाता था और बाद में फिर से शुरू से शुरू होता थाI | AD21: इसमें Pree-test, post-test question होते हैं जिसके मदद से हम बार बार करके सिखने का मौका मिलता है, विडियो से चीज़े जल्दी समझ में आती हैI | AE21: Teacher did not provide any feedback. | AK21: सभी से मिलने का मौका मिलता हैं, सभी की सहभागिता होती हैं, सभी को अपनी बात रखने का पूरा मौका दिया जाता हैं. | AM21: कक्षा की समस्या पर बातचीत होती हैं, लेकिन उसे हम पूरी तरह से अपनी कक्षा में नहीं कर पाते हैं. | AO21: पुस्तिका के आधार पर संवाद होता है, लेकिन आपने इसका किसी भी प्रकार से क्लियर answer नहीं दियाI | AP21: Teachers verbally discuss what they learned in class with other teachers at their school. | AQ21: शिक्षक एक दुसरे से अपने सीखे हुए नोट्स साझा करते हैं. | AS21: Awareness Issue | AT21: आपने कहा था की बहुत सरे शिक्षक technology के साथ familiars नहीं है जिसके कारण उन्हें चुनौती आती हैं I | AZ21: हमें सुझाव मिलना चाहिए, | BA21: शिक्षक को डेमो करके दिखाना चाहिए, कक्षा प्रक्रिया और बेहतर कैसे किया जा सकता हैं इस पर चर्चा होना चाहिए, हम चाहते है की कोई भी अधिकारी आये वो जितना जल्दी हो सके चले जाये. | BF21: V good
A22: 21 | B22: Ritesh Pandey | C22: Naushad Mirza | D22: Chhindwara | E22: Male | F22: 46189 | G22: Maths Science | H22: 28 | I22: He takes 6 Periods in a day encluding science and Math subject for class 6-8. | J22: In a tipical day, he start a day with prayer whcih taking approx 20-25 minutes, he also involeve in data compiled work, like MDM, JSk level data, children mapping etc. he also he takes 30-40 minute games period ending of the day. | K22: He takes 6 Periods in a day encluding science and Math subject for class 6-8. In a tipical day, he start a day with prayer whcih taking approx 20-25 minutes, he also involeve in data compiled work, like MDM, JSk level data, children mapping etc. he also he takes 30-40 minute games period ending of the day. | L22: Subject Training CLSS YTL | M22: 3 CLSS in diffiernt month on the basis of availibility of the teacher in school. 2 days Math and 2 days Science subject training at Block level. 2-3 times Youtube live attended. He also participated in JSK level Science exhibition. He also involved in Sansad khel pratiyogita. Participated in JSK level CAC Organized Samiksha meeting. | N22: He shared that Mostly time engaged in teaching time. and the other activity he engaged in Schience Exhibition, Khelkud Pratiyogita, CLSS, 2 Days Inperson Subject training, where he involved in Math and Science subject. | O22: In- Person training have less opportunity to share our thoughts, he shared that if there will be opportunity to share participants thoughts, it will help those teacher who did not partcipated more. and other thing he shared to create opportunity to explore theoritical concept in experience mode. like if inductive method we should use in the classroom, but how we can impliment in the actual classroom, the training itself not give clear understanding. | P22: Not received | S22: He shared that he did not recieved any material related to training, but during training he experienced lesson planning of 1 topic, he used same for his classroom. | T22: He attended 2-3 YTL for Math and Science, He shared that it is based on specific subject, also he shared that during this YTL subject specific teaching prectices shared and ask questions from teachers. | U22: He shared that it is very useful for teaching. but not shared specific reason. | V22: Yes, He shared that sometimes teachers involved in other stuff related to school, and due to time of YTL, there is less chance to participation. also there is no traking por monitoring machanism to track attendance and imlimentation if the learning is happening. also he shared there is no consiquences for not doing this activity. | W22: He shared that mostly time constrant, Teacher belives, and also the approach takes more time, which leads to less course complition. | X22: Karm Yogi | Z22: I GoT | AA22: He shared that it gives information of new teaching practices, which i have not. | AB22: Last year he did not used DIKSHA plateform at all beacuse of login issue, he also shared that he reachout to CAC for resolve tis issue, but stiil not resolved. He also shared that the information related to Diksha course got from Whatsapp channel.He also shared that he is able to engage 2 hours in a day. | AG22: Technical issue | AH22: login issue, he also shared that he reachout to CAC for resolve tis issue, but stiil not resolved. | AI22: प्रभावी पुनरावृत्ति | AJ22: He shared that CLSS plateform is gives opportunity to explore ourselves which inhance learning, he also shared that CLSS facilitator change 2 times in a year, which gives opportunity to learn, most of the time teacher comes late, which affect CLSS quality and also shared if the CLSS have a dadicated one day, it will help to ensure quality conversation and also | AK22: Every particpants have opportunity to share or thought and a space to reflect our work and learn from another. | AL22: One day dadicated for CLSS, 3 hour seems less for discussion and complete topic. He also shared that after CLSS Monitoring should happen, when school visit happened, it should part of the monitoring, which help to ensure classroom level implimentation of CLSS learning. | AM22: He share that he used activity based learning in the classroom, Table learning through Khargosh activity, Memory game for increase children memory, He also used cald calling to insure all children participants, but some time due to time constrant he rendomly ask children. | AN22: CLSS should have a dadicated one day. | AP22: No learnings shared or no set process adopted | AQ22: Firstly interviever asked when you attended 3 CLSS than you have not any idea of the other CLSS discussion, for that he shared that no, but when i asked that are you shared that your learning with those teacher who did not able to participated, than he shared that, yes we shared about the topic, but discussion not happened deeply. | AS22: others | AT22: He shared that CAC ensured to complete the form before leaving the space. also not have any issue to fill this form. | AY22: HE shared about that when someone visit my clssroom when i teaching, i should not affect from their prasence, they should come and sit in the classroom and observe my class, and if there is any mistake, they should give feedback after the classroom. they should sit on classroom silently when i teach, they should not stood at the gate of classroom or window, it distract me and children. | AZ22: HE shared about that when someone visit my clssroom when i teaching, i should not affect from their prasence, they should come and sit in the classroom and observe my class, and if there is any mistake, they should give feedback after the classroom. they should sit on classroom silently when i teach, they should not stood at the gate of classroom or window, it distract me and children. they should behave friendly and give feedback positively so that teacher feel motivated to incorporate the feedback. | BA22: They should behave friendly and give feedback positively so that teacher feel motivated to incorporate the feedback. | BB22: No specific point shared by teacher. | BC22: He is motivated to inhance self learning through all this intervantions, but sometimes external factors affect to engage in this activity and also same as for application of this learning. | BF22: Good
A23: 22 | B23: Rashmi Mishra | C23: Vaibhav Tambe | D23: Datia | E23: Female | F23: 46188 | G23: Social Science | H23: 23 | I23: Classroom teaching, | J23: Student Data releted work, APAR ID, Commnunity Visit | K23: teacher mentioned that she is HM at school and only she conduct classess with the help with guest teacher. so she has to do many things on daily basis | L23: Subject Training Digital Training CLSS Election related Duties Any other | M23: Shaishik Samvaad, Subject Traning, DIgital Traning, Jangana (Cencus Duty) BRC Meetings | N23: Teacher mention that thoughout the annual engeament she could participate above given activites. "i got to learn many things from traning " is what she mentioned further | O23: The taning includes various activites espacifically cold calling which helped to make my classroom engaging. it helpeing me everyday/ | P23: Margdarshika - Teaching Plan/Modules | R23: Teacher mention that she has recived the margdrashika, but did not go fully time to go thorugh it, beacuse she is HM in school holding various works. | S23: Not applicable bacause teacher haven't read anything from margdarshika. | T23: Not Applicable | U23: Not Applicable - because teacher is not able to recall anything from follow-up activity. she did not shared anything. | X23: बहुविधि शिक्षण और बहुविधि अभिव्यक्ति | Y23: Not applicable | Z23: DIKSHA | AA23: It's effective because in digital course explnation part it very engaging. anyone can understand. I like the way of it ariculate thhing in the course "Digital course achhe lagte hain. Samjhane ka tareeka bahut achha hota hai. Koi bhi aasani se samajh sakta hai aur apne time ke hisaab se course kar sakte hain." | AB23: Teacher mentioned that it is an effiective mode to engage and learn online. she was statisfied after doing two course and shared positive feedback about digital learning | AD23: teacehr mentioned that after every video there was CFU which was really nice to reacall what i learn so far. "Har video ke baad jo quiz aur CFU aata tha woh achha laga. Usse yaad rehta tha ki abhi tak kya seekha." | AE23: Teacher mentioned that it would be really great if we design subject specific courses. becuase at the end we have to teach subjects. so this will help | AF23: Teacher have a clear idea from where being message get circulated. | AI23: कक्षा प्रबंधन के शुरुआती प्रयास | AJ23: Teacher has attended 5 CLSS also shared few thing about what she learnt during CLSS. she showed postive responses and share insights about CLSS like it's a good platfom to connect more teacher to solve problem. our voice being heard in spaces like CLSS | AK23: 30: 70 ratio where facilitator speak 30% and rest of conversation led by teachers. sharing best pracitces, Problem solving | AL23: teacher shared that when dicusssion goes around the topic and emerge more insights then we can say that it went successful. "Jab discussion topic ke aas-paas hi rahe aur teachers apne anubhav share karein, tab zyada seekhne ko milta hai." | AM23: teacher did not mention any challnges | AN23: teacher mention that there should be two way communication between teacher and facilitator. which stays dicussion around the topic being discuss. | AO23: teacher did not recived guide from CLSS | AP23: Other | AQ23: Cascade model is not application becuase she is the only teacher at school. | AR23: Not applicable | AS23: others | AT23: Teacher only shared that there is a possiblity of network challnges. otherwise she did not mention anything. | AY23: By observation CAC come observe classes , ask question to students, etc and mentoring academic person come to school and support in subjects "CAC aakar class dekhe, bachchon se baat kare aur bataye ki aur achha kaise padha sakte hain. Sirf pending kaam dekhne ke liye nahi, padhai mein bhi support karna chahiye." | AZ23: CAC should come and support when we required. not to just follow-up on what is pending. there are challngeing when we teach, so it would be really helpful if CAC can support. | BA23: CAC should support in subject specific topics. take a classes | BB23: Teacher did not shared anything furhter
A24: 23 | B24: Rashmi Mishra | C24: Vaibhav Tambe | D24: Datia | E24: Male | F24: 46189 | G24: Maths | H24: 10 | I24: subject teaching | J24: School management, APAR ID - Student data releted work, Community visit. | K24: Teacher shared that they serve as both the Headmaster (HM) and the only teacher in the school. As a result, they are responsible for multiple non-academic and administrative duties in addition to teaching responsibilities. | L24: Subject Training Digital Training CLSS Election related Duties Any other | M24: Participated in Subject Training, Digital Training, CLSS (Aug, Dec), and election-related duties during the 2025–26 academic year; no other activities were mentioned. | N24: Participated in Subject Training, Digital Training, CLSS (Aug, Dec), and election duties during 2025–26. As HM and the only teacher in the school, managed trainings along with teaching and administrative work. | O24: Include real-life classroom demo videos/examples in the training sessions so teachers can better relate the concepts to their own classrooms and understand practical implementation. | P24: Margdarshika - Teaching Plan/Modules | R24: Teacher found the Margdarshika useful as it includes classroom activities and practical examples that help increase student engagement and make lessons more interactive. | S24: Teacher has not sahred anything specific that he implement. | T24: Follow-up activities were not undertaken due to technical issues and competing work commitments, which limited the teacher's ability to participate beyond the training sessions. | X24: Teacher not able to recall course name | Z24: DIKSHA | AA24: Teacher did not perceive online/digital learning as effective. They mentioned that online sessions lack attentiveness and are mostly one-way communication. In contrast, in-person trainings allow two-way interaction, discussions, and better engagement, making them more useful. | AB24: Teacher perceived digital/online learning as less effective due to limited interaction and lower attentiveness during sessions. | AD24: Teacher did not reall anything from course engagement | AF24: Teacher did not share any specific feedback or experiences related to the course despite multiple prompts and follow-up questions. | AI24: No topic recalled | AJ24: Teacher found the CLSS topics useful as they provided opportunities to connect with other teachers, exchange experiences, and learn new teaching practices from peers. | AK24: Group discussions and shared activities during the sessions. The teacher appreciated opportunities to interact with peers, exchange ideas, and learn through collaborative activities. | AL24: Teacher felt that a peer learning community is most effective when discussions remain focused on the topic and all participants actively contribute to the conversation. | AM24: Teacher not able to recall anything | AN24: No specific changes were suggested. The teacher shared that strategies introduced during CLSS, particularly Think-Pair-Share and Welcome Routine activities, were implemented in the classroom and helped improve student engagement. | AO24: Teacher did not recived anything | AP24: Resources shared in the school whatsapp group | AQ24: Cascading of CLSS learning was not applicable, as the respondent is the only teacher in the school and therefore has no peers within the school to share or disseminate learnings with. | AR24: NOT applicabe | AS24: others | AY24: Teacher perceived mentoring and classroom observation as a process to understand how students are learning and to review classroom practices. The teacher mentioned that the CAC visits the school, monitors classroom processes, and asks about syllabus completion and student learning progress. | AZ24: Mentor should focus on understanding how students are learning during classroom observations, provide practical suggestions for improvement, and maintain a supportive approach. | BA24: Teacher expects mentors to provide practical classroom support, share strategies for improving student learning, and offer constructive feedback | BB24: Teacher suggested that more subject-specific courses should be made available on DIKSHA to support continuous professional development and address subject-wise teaching needs. | BF24: Good
A25: 24 | B25: Vaibhav Kurwade | C25: Anjali | D25: Narsinghpur | E25: Male | F25: 46188 | G25: Social Science Sanskrit | H25: 43 | I25: Starts the day by interacting with students on cleanliness, yoga, and moral values. Recites poems on values (Sanskar) and Narmada Geet with students. Marks student attendance. Takes two classroom periods for each grade, mainly teaching Social Science and Sanskrit. Supports students in various learning and co-curricular activities. | J25: Maintains attendance and school records. Facilitates student participation in school activities. Participated in textbook distribution and bicycle distribution programs during the previous year. Attends training programs through DIKSHA and Karmayogi platforms. Participates in block-level meetings and orientation sessions related to curriculum and textbook changes. | K25: The teacher begins the school day with value-based discussions focusing on cleanliness, yoga, and moral education. Regularly engages students through poems and songs promoting cultural and moral values. Balances academic teaching with administrative and co-curricular responsibilities. Actively participates in government-led school programs and student welfare initiatives. Demonstrates commitment to continuous professional development through online and block-level training programs. | L25: Subject Training Digital Training CLSS YTL | M25: CLSS in July, YTL, Digital training, subject training- (not remember the exact time), | N25: participated in various professional development activities throughout the year, including in-person training, digital learning courses, YouTube Live sessions, and Cluster Level Shakshik Samvad (CLSS | O25: The teacher suggested that greater participant engagement and active involvement would make training sessions more effective. More opportunities for discussion, sharing of experiences, and collaborative learning should be incorporated into training sessions. Training should continue to focus on practical classroom strategies, activity-based learning, and changes in teaching-learning practices. Interactive activities and participation-oriented approaches can help improve the overall quality and impact of training programs. | P25: Margdarshika - Teaching Plan/Modules | R25: The teacher found the training materials relevant and supportive for classroom teaching. He suggested that training sessions would be more effective if participants showed greater interest and active involvement. Increased participation from all attendees would improve the quality of discussions and learning outcomes. | S25: Changes suggested in the Shikshan Chakra Ghatak have been implemented in classroom transactions. | T25: The teacher has not attended any SKY follow-up activities but has participated in YouTube Live sessions. The teacher reported a positive experience with these sessions and found them useful for improving classroom practices. | U25: The teacher found the YouTube Live sessions useful because they provided practical insights that helped achieve better classroom outcomes and improve student learning. The sessions offered guidance that could be directly applied in classroom teaching. | V25: The teacher identified network connectivity and server-related issues as the primary challenges affecting participation in online discussion calls. | W25: The teacher did not report any major pedagogical challenges in implementing learnings from training. However, network and technical issues can limit access to follow-up support and online discussions, which may affect continued implementation and learning | X25: not able to recall | Y25: Not able to recall | Z25: DIKSHA and IGOT | AA25: The teacher finds digital courses effective because they include short learning modules, interactive questions, and engaging teaching-learning materials (TLMs). The flexibility to learn at one's own pace, time, and location makes digital learning highly convenient. The teacher emphasized that digital learning proved especially valuable during and after the COVID period, enabling continuous professional development. | AB25: The teacher perceives digital learning as an effective and accessible mode of professional development. Digital platforms provide opportunities to learn independently and revisit content whenever required. The teacher regularly engages with digital courses after school hours and values the convenience they offer. | AD25: It is engaging | AE25: To improve course quality, the teacher suggested: Keeping modules shorter (around 10–13 minutes). Breaking content into smaller sections. Including more new and topic-related activities. Increasing interactivity to maintain learner engagement | AF25: the teacher was saying he did all the courses but not able to recall any course name and content. | AI25: No topic recalled | AJ25: The teacher appreciated the way the Sahajakarta facilitates discussions, particularly around lesson planning. The teacher valued the opportunity to interact with peers who work at a similar level and face similar classroom challenges. The platform provides a safe and open space for teachers to freely share experiences, challenges, and solutions. | AK25: The teacher appreciated the way the Sahajakarta facilitated discussions, particularly around lesson planning. The teacher valued the opportunity to interact with peers who work at a similar level and face similar classroom challenges. | AL25: A successful peer learning community provides a safe and open environment where teachers can freely discuss challenges and share experiences. Equal participation, collaborative discussions, and practical classroom-focused solutions make the community more meaningful. Effective facilitation and opportunities for peer interaction strengthen learning and engagement | AM25: not able to recall | AN25: Include more activity-based discussions and practical learning opportunities during the sessions. Share Sahajakarta notes and key discussion points with participants after the session for future reference and classroom application. | AO25: The teacher found the facilitation process useful in guiding discussions and focusing on classroom-related topics. | AP25: Resources shared in the school whatsapp group Participating teacher share their notes | AQ25: CLSS learnings are primarily shared through informal discussions among teachers. The teacher believes that sharing key notes and discussion summaries can support wider dissemination of learnings within the school. | AR25: Develop a structured process for sharing CLSS learnings with all teachers in the school. Share written notes, discussion summaries, and practical classroom examples after each session. | AS25: others | AT25: The teacher did not report any major concerns regarding attendance or logistics. However, attendance and feedback completion may be affected by time constraints at the end of the session when teachers are preparing to leave the venue. Clear communication and adequate time allocation for attendance and feedback submission can improve compliance and participation. | AY25: The teacher views classroom observation and mentoring as a supportive process that helps identify students' learning levels and classroom needs. The teacher believes the primary purpose of observation should be to understand classroom realities and provide constructive support rather than evaluate or inspect teachers. Mentoring should focus on helping teachers address challenges and improve teaching-learning practices. | AZ25: Mentors should adopt the role of a facilitator (Sahajakarta) rather than an inspector. They should create a supportive and comfortable environment for both teachers and students. Mentors should come prepared with a clear observation plan and understanding of the teaching-learning process. The observation process should avoid creating fear or nervousness among teachers and students. Constructive feedback and guidance should be provided to help teachers improve classroom practices. | BA25: The teacher expects mentors to provide practical support in addressing classroom challenges. Mentors should help teachers identify solutions to teaching and learning difficulties. Guidance should be focused on improving student learning outcomes and strengthening classroom practices. | BB25: The teacher shared that the various professional development initiatives and programs have been effective in strengthening teachers' knowledge, skills, and classroom practices. According to the teacher, most teachers have become more capable and confident through these training and support mechanisms. However, a small group of teachers remains less active and less engaged in professional development activities. The teacher suggested that additional support, motivation, and follow-up mechanisms should be developed to encourage greater participation from these teachers. Targeted strategies may be required to understand the reasons for low engagement and to ensure that all teachers benefit from professional development opportunities. Overall, the teacher views the existing professional development ecosystem positively and believes that continued support, mentoring, and active participation can further enhance teacher effectiveness and student learning outcomes. | BF25: Good
